Workbook

Sheet HOW TO USE
A1: CityAI — Requirements Gathering Workbook
A2: Capture business cases from any function · the built-in brain recommends a CityAI tool
B5: HOW IT WORKS
B6: 1. Open the REQUIREMENTS tab. Each row = one business case.
B7: 2. Fill columns A–U. White = free text. Colored = dropdown. Some cells show a hover tooltip with guidance.
B8: 3. As soon as you describe the pain point / current process / expected outcome, the four 🧠 columns auto-fill: recommended tool, fit-score %, matched keywords (rationale), and a 2nd-best alternative.
B9: 4. Override the recommendation in column AB (Final decision) if you disagree.
B10: 5. Open TOOL CATALOG to read what each of the 6 tools does.
B11: 6. Open BRAIN to tune the scoring (add keywords, adjust function-affinity scores). Formulas pick changes up live.
B14: THE 6 TOOLS THE BRAIN PICKS FROM
B15: ● PULSE — HR & Hiring AI — AI hiring + candidate matching + HR Brain chatbot.
B16: ● PG-MCP-RTM — Route-to-Market Classifier — Classify retail outlets per branch using Pareto 80/15/5 + workload sizing.
B17: ● RO-ED-Lang — Customs PDF Extractor — Extract structured data from typed + handwritten customs declarations.
B18: ● City-KONTACT — Catalog Vision RAG — Snap catalog photos → searchable product + vendor DB with chat agent.
... B47: Built for CityAI · v2.0 · Edit BRAIN keywords to evolve the recommender over time.

Sheet REQUIREMENTS
A1: 📋 REQUIREMENTS INTAKE · describe your business case · brain recommends a tool
A2: Fill columns A–U (white cells = free text · colored cells = dropdown). Columns V–Y auto-fill: recommended tool, fit %, matched keywords, and a 2nd-best alt. Override the recommendation in column Z if you disagree.
A3: IDENTITY | H3: WHAT | L3: HOW | P3: HOW MUCH | S3: WHO | V3: BRAIN | Z3: DECISION
A4: Req ID | B4: Date submitted | C4: Requester name | D4: Requester email | E4: Function / Department | F4: Sub-team | G4: Business unit | H4: Business case title | I4: Pain point / problem | J4: Current process / workaround | K4: Expected outcome / solution | L4: Data sources involved | M4: Document types involved | N4: Frequency | O4: Volume per cycle | P4: Urgency | Q4: Effort estimate | R4: Est. annual value (USD) | S4: Stakeholders / sponsors | T4: Compliance type | U4: Target go-live | V4: 🧠 Recommended tool | W4: 🧠 Fit score | X4: 🧠 Rationale / keywords | Y4: 🧠 Alt #2 tool | Z4: Project stage | AA4: Final decision | AB4: Owner / next step | AE4: score_PULSE | AF4: score_RTM | AG4: score_ROED | AH4: score_KONTACT | AI4: score_SCOUT | AJ4: score_DASH | AK4: _concat | AL4: tool_name | AM4: rat_PULSE | AN4: rat_RTM | AO4: rat_ROED | AP4: rat_KONTACT | AQ4: rat_SCOUT | AR4: rat_DASH
A5: REQ-001 | B5: 46153 | C5: Alice Tan | D5: alice.tan@city.com | E5: Talent Acquisition | F5: Tech hiring | G5: Tech / IT Services | H5: Faster CV screening for engineering roles | I5: We get 200+ CVs per open engineering role. Recruiters take 2 weeks to shortlist and many strong candidates drop off because we don't reply fast enough. | J5: Manual review of every resume in a shared Excel. JD written in Word. Interview scorecards on paper. | K5: Auto-match CVs to the JD, rank top candidates, draft scorecards and interview questions, and a chatbot answering recruiter questions about the candidate pool. | L5: PDF documents | M5: CVs / resumes | N5: Weekly | O5: 100-1k | P5: High | Q5: M — 3-6 weeks | R5: 120000 | S5: VP Engineering, Head of TA | T5: GDPR / PII | U5: 46204 | V5: =IF(SUM(AE5:AJ5)=0,"",INDEX(AL$5:AL$10,MATCH(MAX(AE5:AJ5),AE5:AJ5,0))) -> PULSE — HR & Hiring AI | W5: =IF(SUM(AE5:AJ5)=0,"",ROUND(MAX(AE5:AJ5)/SUM(AE5:AJ5)*100,0)/100) -> 0.79 | X5: =IF(SUM(AE5:AJ5)=0,"",IFERROR(INDEX(AM5:AR5,MATCH(MAX(AE5:AJ5),AE5:AJ5,0)),"—")) -> recruit, recruiter, candidate, cv, resume, interview, scorecard, shortlist, jd, screening | Y5: =IF(COUNTIF(AE5:AJ5,">0")<2,"",INDEX(AL$5:AL$10,MATCH(LARGE(AE5:AJ5,2),AE5:AJ5,0))) -> CHL Scout — Agentic RAG / Doc Q&A | Z5: Validated | AE5: =IF(LEN(AK5)=0,0,2*SUMPRODUCT((LEN(KW_PULSE)>0)*--ISNUMBER(SEARCH(KW_PULSE,AK5))) + 1*IFERROR(INDEX(Affinity_PULSE,MATCH(E5,AffinityFunctions,0)),0)) -> 23 | AF5: =IF(LEN(AK5)=0,0,2*SUMPRODUCT((LEN(KW_RTM)>0)*--ISNUMBER(SEARCH(KW_RTM,AK5))) + 1*IFERROR(INDEX(Affinity_RTM,MATCH(E5,AffinityFunctions,0)),0)) -> 0 | AG5: =IF(LEN(AK5)=0,0,2*SUMPRODUCT((LEN(KW_ROED)>0)*--ISNUMBER(SEARCH(KW_ROED,AK5))) + 1*IFERROR(INDEX(Affinity_ROED,MATCH(E5,AffinityFunctions,0)),0)) -> 0 | AH5: =IF(LEN(AK5)=0,0,2*SUMPRODUCT((LEN(KW_KONTACT)>0)*--ISNUMBER(SEARCH(KW_KONTACT,AK5))) + 1*IFERROR(INDEX(Affinity_KONTACT,MATCH(E5,AffinityFunctions,0)),0)) -> 0 | AI5: =IF(LEN(AK5)=0,0,2*SUMPRODUCT((LEN(KW_SCOUT)>0)*--ISNUMBER(SEARCH(KW_SCOUT,AK5))) + 1*IFERROR(INDEX(Affinity_SCOUT,MATCH(E5,AffinityFunctions,0)),0)) -> 5 | AJ5: =IF(LEN(AK5)=0,0,2*SUMPRODUCT((LEN(KW_DASH)>0)*--ISNUMBER(SEARCH(KW_DASH,AK5))) + 1*IFERROR(INDEX(Affinity_DASH,MATCH(E5,AffinityFunctions,0)),0)) -> 1 | AK5: =LOWER(IFERROR(_xlfn.TEXTJOIN(" ",1,H5,I5,J5,K5,L5,M5),"")) -> faster cv screening for engineering roles we get 200+ cvs per open engineering role. recruiters take 2 weeks to shortlist and many strong candidates drop off because we don't reply fast enough. manual review of every resume in a shared excel. jd written in word. interview scorecards on paper. auto-match cvs to the jd, rank top candidates, draft scorecards and interview questions, and a chatbot answering recruiter questions about the candidate pool. pdf documents cvs / resumes | AL5: PULSE — HR & Hiring AI | AM5: =IFERROR(IF(RIGHT((IF(LEN(BRAIN!$C$26)>0,IF(ISNUMBER(SEARCH(BRAIN!$C$26,AK5)),BRAIN!$C$26&", ",""),"") & IF(LEN(BRAIN!$C$27)>0,IF(ISNUMBER(SEARCH(BRAIN!$C$27,AK5)),BRAIN!$C$27&", ",""),"") & IF(LEN(BRAIN!$C$28)>0,IF(ISNUMBER(SEARCH(BRAIN!$C$28,AK5)),BRAIN!$C$28&", ",""),"") & IF(LEN(BRAIN!$C$29)>0,IF(ISNUMBER(SEARCH(BRAIN!$C$29,AK5)),BRAIN!$C$29&", ",""),"") & IF(LEN(BRAIN!$C$30)>0,IF(ISNUMBER(SEARCH(BRAIN!$C$30,AK5)),BRAIN!$C$30&", ",""),"") & IF(LEN(BRAIN!$C$31)>0,IF(ISNUMBER(SEARCH(BRAIN!$C$31,AK5)),BRAIN!$C$31&", ",""),"") & IF(LEN(BRAIN!$C$32)>0,IF(ISNUMBER(SEARCH(BRAIN!$C$32,AK5)),BRAIN!$C$32&", ",""),"") & IF(LEN(BRAIN!$C$33)>0,IF(ISNUMBER(SEARCH(BRAIN!$C$33,AK5)),BRAIN!$C$33&", ",""),"") & IF(LEN(BRAIN!$C$34)>0,IF(ISNUMBER(SEARCH(BRAIN!$C$34,AK5)),BRAIN!$C$34&", ",""),"") & IF(LEN(BRAIN!$C$35)>0,IF(ISNUMBER(SEARCH(BRAIN!$C$35,AK5)),BRAIN!$C$35&", ",""),"") & IF(LEN(BRAIN!$C$36)>0,IF(ISNUMBER(SEARCH(BRAIN!$C$36,AK5)),BRAIN!$C$36&", ",""),"") & IF(LEN(BRAIN!$C$37)>0,IF(ISNUMBER(SEARCH(BRAIN!$C$37,AK5)),BRAIN!$C$37&", ",""),"") & IF(LEN(BRAIN!$C$38)>0,IF(ISNUMBER(SEARCH(BRAIN!$C$38,AK5)),BRAIN!$C$38&", ",""),"") & IF(LEN(BRAIN!$C$39)>0,IF(ISNUMBER(SEARCH(BRAIN!$C$39,AK5)),BRAIN!$C$39&", ",""),"") & IF(LEN(BRAIN!$C$40)>0,IF(ISNUMBER(SEARCH(BRAIN!$C$40,AK5)),BRAIN!$C$40&", ",""),"") & IF(LEN(BRAIN!$C$41)>0,IF(ISNUMBER(SEARCH(BRAIN!$C$41,AK5)),BRAIN!$C$41&", ",""),"") & IF(LEN(BRAIN!$C$42)>0,IF(ISNUMBER(SEARCH(BRAIN!$C$42,AK5)),BRAIN!$C$42&", ",""),"") & IF(LEN(BRAIN!$C$43)>0,IF(ISNUMBER(SEARCH(BRAIN!$C$43,AK5)),BRAIN!$C$43&", ",""),"") & IF(LEN(BRAIN!$C$44)>0,IF(ISNUMBER(SEARCH(BRAIN!$C$44,AK5)),BRAIN!$C$44&", ",""),"") & IF(LEN(BRAIN!$C$45)>0,IF(ISNUMBER(SEARCH(BRAIN!$C$45,AK5)),BRAIN!$C$45&", ",""),"") & IF(LEN(BRAIN!$C$46)>0,IF(ISNUMBER(SEARCH(BRAIN!$C$46,AK5)),BRAIN!$C$46&", ",""),"") & IF(LEN(BRAIN!$C$47)>0,IF(ISNUMBER(SEARCH(BRAIN!$C$47,AK5)),BRAIN!$C$47&", ",""),"") & IF(LEN(BRAIN!$C$48)>0,IF(ISNUMBER(SEARCH(BRAIN!$C$48,AK5)),BRAIN!$C$48&", ",""),"") & IF(LEN(BRAIN!$C$49)>0,IF(ISNUMBER(SEARCH(BRAIN!$C$49,AK5)),BRAIN!$C$49&", ",""),"") & IF(LEN(BRAIN!$C$50)>0,IF(ISNUMBER(SEARCH(BRAIN!$C$50,AK5)),BRAIN!$C$50&", ",""),"") & IF(LEN(BRAIN!$C$51)>0,IF(ISNUMBER(SEARCH(BRAIN!$C$51,AK5)),BRAIN!$C$51&", ",""),"") & IF(LEN(BRAIN!$C$52)>0,IF(ISNUMBER(SEARCH(BRAIN!$C$52,AK5)),BRAIN!$C$52&", ",""),"") & IF(LEN(BRAIN!$C$53)>0,IF(ISNUMBER(SEARCH(BRAIN!$C$53,AK5)),BRAIN!$C$53&", ",""),"") & IF(LEN(BRAIN!$C$54)>0,IF(ISNUMBER(SEARCH(BRAIN!$C$54,AK5)),BRAIN!$C$54&", ",""),"") & IF(LEN(BRAIN!$C$55)>0,IF(ISNUMBER(SEARCH(BRAIN!$C$55,AK5)),BRAIN!$C$55&", ",""),"") & IF(LEN(BRAIN!$C$56)>0,IF(ISNUMBER(SEARCH(BRAIN!$C$56,AK5)),BRAIN!$C$56&", ",""),"") & IF(LEN(BRAIN!$C$57)>0,IF(ISNUMBER(SEARCH(BRAIN!$C$57,AK5)),BRAIN!$C$57&", ",""),"")),2)=", ",LEFT((IF(LEN(BRAIN!$C$26)>0,IF(ISNUMBER(SEARCH(BRAIN!$C$26,AK5)),BRAIN!$C$26&", ",""),"") & IF(LEN(BRAIN!$C$27)>0,IF(ISNUMBER(SEARCH(BRAIN!$C$27,AK5)),BRAIN!$C$27&", ",""),"") & IF(LEN(BRAIN!$C$28)>0,IF(ISNUMBER(SEARCH(BRAIN!$C$28,AK5)),BRAIN!$C$28&", ",""),"") & IF(LEN(BRAIN!$C$29)>0,IF(ISNUMBER(SEARCH(BRAIN!$C$29,AK5)),BRAIN!$C$29&", ",""),"") & IF(LEN(BRAIN!$C$30)>0,IF(ISNUMBER(SEARCH(BRAIN!$C$30,AK5)),BRAIN!$C$30&", ",""),"") & IF(LEN(BRAIN!$C$31)>0,IF(ISNUMBER(SEARCH(BRAIN!$C$31,AK5)),BRAIN!$C$31&", ",""),"") & IF(LEN(BRAIN!$C$32)>0,IF(ISNUMBER(SEARCH(BRAIN!$C$32,AK5)),BRAIN!$C$32&", ",""),"") & IF(LEN(BRAIN!$C$33)>0,IF(ISNUMBER(SEARCH(BRAIN!$C$33,AK5)),BRAIN!$C$33&", ",""),"") & IF(LEN(BRAIN!$C$34)>0,IF(ISNUMBER(SEARCH(BRAIN!$C$34,AK5)),BRAIN!$C$34&", ",""),"") & IF(LEN(BRAIN!$C$35)>0,IF(ISNUMBER(SEARCH(BRAIN!$C$35,AK5)),BRAIN!$C$35&", ",""),"") & IF(LEN(BRAIN!$C$36)>0,IF(ISNUMBER(SEARCH(BRAIN!$C$36,AK5)),BRAIN!$C$36&", ",""),"") & IF(LEN(BRAIN!$C$37)>0,IF(ISNUMBER(SEARCH(BRAIN!$C$37,AK5)),BRAIN!$C$37&", ",""),"") & IF(LEN(BRAIN!$C$38)>0,IF(ISNUMBER(SEARCH(BRAIN!$C$38,AK5)),BRAIN!$C$38&", ",""),"") & IF(LEN(BRAIN!$C$39)>0,IF(ISNUMBER(SEARCH(BRAIN!$C$39,AK5)),BRAIN!$C$39&", ",""),"") & IF(LEN(BRAIN!$C$40)>0,IF(ISNUMBER(SEARCH(BRAIN!$C$40,AK5)),BRAIN!$C$40&", ",""),"") & IF(LEN(BRAIN!$C$41)>0,IF(ISNUMBER(SEARCH(BRAIN!$C$41,AK5)),BRAIN!$C$41&", ",""),"") & IF(LEN(BRAIN!$C$42)>0,IF(ISNUMBER(SEARCH(BRAIN!$C$42,AK5)),BRAIN!$C$42&", ",""),"") & IF(LEN(BRAIN!$C$43)>0,IF(ISNUMBER(SEARCH(BRAIN!$C$43,AK5)),BRAIN!$C$43&", ",""),"") & IF(LEN(BRAIN!$C$44)>0,IF(ISNUMBER(SEARCH(BRAIN!$C$44,AK5)),BRAIN!$C$44&", ",""),"") & IF(LEN(BRAIN!$C$45)>0,IF(ISNUMBER(SEARCH(BRAIN!$C$45,AK5)),BRAIN!$C$45&", ",""),"") & IF(LEN(BRAIN!$C$46)>0,IF(ISNUMBER(SEARCH(BRAIN!$C$46,AK5)),BRAIN!$C$46&", ",""),"") & IF(LEN(BRAIN!$C$47)>0,IF(ISNUMBER(SEARCH(BRAIN!$C$47,AK5)),BRAIN!$C$47&", ",""),"") & IF(LEN(BRAIN!$C$48)>0,IF(ISNUMBER(SEARCH(BRAIN!$C$48,AK5)),BRAIN!$C$48&", ",""),"") & IF(LEN(BRAIN!$C$49)>0,IF(ISNUMBER(SEARCH(BRAIN!$C$49,AK5)),BRAIN!$C$49&", ",""),"") & IF(LEN(BRAIN!$C$50)>0,IF(ISNUMBER(SEARCH(BRAIN!$C$50,AK5)),BRAIN!$C$50&", ",""),"") & IF(LEN(BRAIN!$C$51)>0,IF(ISNUMBER(SEARCH(BRAIN!$C$51,AK5)),BRAIN!$C$51&", ",""),"") & IF(LEN(BRAIN!$C$52)>0,IF(ISNUMBER(SEARCH(BRAIN!$C$52,AK5)),BRAIN!$C$52&", ",""),"") & IF(LEN(BRAIN!$C$53)>0,IF(ISNUMBER(SEARCH(BRAIN!$C$53,AK5)),BRAIN!$C$53&", ",""),"") & IF(LEN(BRAIN!$C$54)>0,IF(ISNUMBER(SEARCH(BRAIN!$C$54,AK5)),BRAIN!$C$54&", ",""),"") & IF(LEN(BRAIN!$C$55)>0,IF(ISNUMBER(SEARCH(BRAIN!$C$55,AK5)),BRAIN!$C$55&", ",""),"") & IF(LEN(BRAIN!$C$56)>0,IF(ISNUMBER(SEARCH(BRAIN!$C$56,AK5)),BRAIN!$C$56&", ",""),"") & IF(LEN(BRAIN!$C$57)>0,IF(ISNUMBER(SEARCH(BRAIN!$C$57,AK5)),BRAIN!$C$57&", ",""),"")),LEN((IF(LEN(BRAIN!$C$26)>0,IF(ISNUMBER(SEARCH(BRAIN!$C$26,AK5)),BRAIN!$C$26&", ",""),"") & IF(LEN(BRAIN!$C$27)>0,IF(ISNUMBER(SEARCH(BRAIN!$C$27,AK5)),BRAIN!$C$27&", ",""),"") & IF(LEN(BRAIN!$C$28)>0,IF(ISNUMBER(SEARCH(BRAIN!$C$28,AK5)),BRAIN!$C$28&", ",""),"") & IF(LEN(BRAIN!$C$29)>0,IF(ISNUMBER(SEARCH(BRAIN!$C$29,AK5)),BRAIN!$C$29&", ",""),"") & IF(LEN(BRAIN!$C$30)>0,IF(ISNUMBER(SEARCH(BRAIN!$C$30,AK5)),BRAIN!$C$30&", ",""),"") & IF(LEN(BRAIN!$C$31)>0,IF(ISNUMBER(SEARCH(BRAIN!$C$31,AK5)),BRAIN!$C$31&", ",""),"") & IF(LEN(BRAIN!$C$32)>0,IF(ISNUMBER(SEARCH(BRAIN!$C$32,AK5)),BRAIN!$C$32&", ",""),"") & IF(LEN(BRAIN!$C$33)>0,IF(ISNUMBER(SEARCH(BRAIN!$C$33,AK5)),BRAIN!$C$33&", ",""),"") & IF(LEN(BRAIN!$C$34)>0,IF(ISNUMBER(SEARCH(BRAIN!$C$34,AK5)),BRAIN!$C$34&", ",""),"") & IF(LEN(BRAIN!$C$35)>0,IF(ISNUMBER(SEARCH(BRAIN!$C$35,AK5)),BRAIN!$C$35&", ",""),"") & IF(LEN(BRAIN!$C$36)>0,IF(ISNUMBER(SEARCH(BRAIN!$C$36,AK5)),BRAIN!$C$36&", ",""),"") & IF(LEN(BRAIN!$C$37)>0,IF(ISNUMBER(SEARCH(BRAIN!$C$37,AK5)),BRAIN!$C$37&", ",""),"") & IF(LEN(BRAIN!$C$38)>0,IF(ISNUMBER(SEARCH(BRAIN!$C$38,AK5)),BRAIN!$C$38&", ",""),"") & IF(LEN(BRAIN!$C$39)>0,IF(ISNUMBER(SEARCH(BRAIN!$C$39,AK5)),BRAIN!$C$39&", ",""),"") & IF(LEN(BRAIN!$C$40)>0,IF(ISNUMBER(SEARCH(BRAIN!$C$40,AK5)),BRAIN!$C$40&", ",""),"") & IF(LEN(BRAIN!$C$41)>0,IF(ISNUMBER(SEARCH(BRAIN!$C$41,AK5)),BRAIN!$C$41&", ",""),"") & IF(LEN(BRAIN!$C$42)>0,IF(ISNUMBER(SEARCH(BRAIN!$C$42,AK5)),BRAIN!$C$42&", ",""),"") & IF(LEN(BRAIN!$C$43)>0,IF(ISNUMBER(SEARCH(BRAIN!$C$43,AK5)),BRAIN!$C$43&", ",""),"") & IF(LEN(BRAIN!$C$44)>0,IF(ISNUMBER(SEARCH(BRAIN!$C$44,AK5)),BRAIN!$C$44&", ",""),"") & IF(LEN(BRAIN!$C$45)>0,IF(ISNUMBER(SEARCH(BRAIN!$C$45,AK5)),BRAIN!$C$45&", ",""),"") & IF(LEN(BRAIN!$C$46)>0,IF(ISNUMBER(SEARCH(BRAIN!$C$46,AK5)),BRAIN!$C$46&", ",""),"") & IF(LEN(BRAIN!$C$47)>0,IF(ISNUMBER(SEARCH(BRAIN!$C$47,AK5)),BRAIN!$C$47&", ",""),"") & IF(LEN(BRAIN!$C$48)>0,IF(ISNUMBER(SEARCH(BRAIN!$C$48,AK5)),BRAIN!$C$48&", ",""),"") & IF(LEN(BRAIN!$C$49)>0,IF(ISNUMBER(SEARCH(BRAIN!$C$49,AK5)),BRAIN!$C$49&", ",""),"") & IF(LEN(BRAIN!$C$50)>0,IF(ISNUMBER(SEARCH(BRAIN!$C$50,AK5)),BRAIN!$C$50&", ",""),"") & IF(LEN(BRAIN!$C$51)>0,IF(ISNUMBER(SEARCH(BRAIN!$C$51,AK5)),BRAIN!$C$51&", ",""),"") & IF(LEN(BRAIN!$C$52)>0,IF(ISNUMBER(SEARCH(BRAIN!$C$52,AK5)),BRAIN!$C$52&", ",""),"") & IF(LEN(BRAIN!$C$53)>0,IF(ISNUMBER(SEARCH(BRAIN!$C$53,AK5)),BRAIN!$C$53&", ",""),"") & IF(LEN(BRAIN!$C$54)>0,IF(ISNUMBER(SEARCH(BRAIN!$C$54,AK5)),BRAIN!$C$54&", ",""),"") & IF(LEN(BRAIN!$C$55)>0,IF(ISNUMBER(SEARCH(BRAIN!$C$55,AK5)),BRAIN!$C$55&", ",""),"") & IF(LEN(BRAIN!$C$56)>0,IF(ISNUMBER(SEARCH(BRAIN!$C$56,AK5)),BRAIN!$C$56&", ",""),"") & IF(LEN(BRAIN!$C$57)>0,IF(ISNUMBER(SEARCH(BRAIN!$C$57,AK5)),BRAIN!$C$57&", ",""),"")))-2),(IF(LEN(BRAIN!$C$26)>0,IF(ISNUMBER(SEARCH(BRAIN!$C$26,AK5)),BRAIN!$C$26&", ",""),"") & IF(LEN(BRAIN!$C$27)>0,IF(ISNUMBER(SEARCH(BRAIN!$C$27,AK5)),BRAIN!$C$27&", ",""),"") & IF(LEN(BRAIN!$C$28)>0,IF(ISNUMBER(SEARCH(BRAIN!$C$28,AK5)),BRAIN!$C$28&", ",""),"") & IF(LEN(BRAIN!$C$29)>0,IF(ISNUMBER(SEARCH(BRAIN!$C$29,AK5)),BRAIN!$C$29&", ",""),"") & IF(LEN(BRAIN!$C$30)>0,IF(ISNUMBER(SEARCH(BRAIN!$C$30,AK5)),BRAIN!$C$30&", ",""),"") & IF(LEN(BRAIN!$C$31)>0,IF(ISNUMBER(SEARCH(BRAIN!$C$31,AK5)),BRAIN!$C$31&", ",""),"") & IF(LEN(BRAIN!$C$32)>0,IF(ISNUMBER(SEARCH(BRAIN!$C$32,AK5)),BRAIN!$C$32&", ",""),"") & IF(LEN(BRAIN!$C$33)>0,IF(ISNUMBER(SEARCH(BRAIN!$C$33,AK5)),BRAIN!$C$33&", ",""),"") & IF(LEN(BRAIN!$C$34)>0,IF(ISNUMBER(SEARCH(BRAIN!$C$34,AK5)),BRAIN!$C$34&", ",""),"") & IF(LEN(BRAIN!$C$35)>0,IF(ISNUMBER(SEARCH(BRAIN!$C$35,AK5)),BRAIN!$C$35&", ",""),"") & IF(LEN(BRAIN!$C$36)>0,IF(ISNUMBER(SEARCH(BRAIN!$C$36,AK5)),BRAIN!$C$36&", ",""),"") & IF(LEN(BRAIN!$C$37)>0,IF(ISNUMBER(SEARCH(BRAIN!$C$37,AK5)),BRAIN!$C$37&", ",""),"") & IF(LEN(BRAIN!$C$38)>0,IF(ISNUMBER(SEARCH(BRAIN!$C$38,AK5)),BRAIN!$C$38&", ",""),"") & IF(LEN(BRAIN!$C$39)>0,IF(ISNUMBER(SEARCH(BRAIN!$C$39,AK5)),BRAIN!$C$39&", ",""),"") & IF(LEN(BRAIN!$C$40)>0,IF(ISNUMBER(SEARCH(BRAIN!$C$40,AK5)),BRAIN!$C$40&", ",""),"") & IF(LEN(BRAIN!$C$41)>0,IF(ISNUMBER(SEARCH(BRAIN!$C$41,AK5)),BRAIN!$C$41&", ",""),"") & IF(LEN(BRAIN!$C$42)>0,IF(ISNUMBER(SEARCH(BRAIN!$C$42,AK5)),BRAIN!$C$42&", ",""),"") & IF(LEN(BRAIN!$C$43)>0,IF(ISNUMBER(SEARCH(BRAIN!$C$43,AK5)),BRAIN!$C$43&", ",""),"") & IF(LEN(BRAIN!$C$44)>0,IF(ISNUMBER(SEARCH(BRAIN!$C$44,AK5)),BRAIN!$C$44&", ",""),"") & IF(LEN(BRAIN!$C$45)>0,IF(ISNUMBER(SEARCH(BRAIN!$C$45,AK5)),BRAIN!$C$45&", ",""),"") & IF(LEN(BRAIN!$C$46)>0,IF(ISNUMBER(SEARCH(BRAIN!$C$46,AK5)),BRAIN!$C$46&", ",""),"") & IF(LEN(BRAIN!$C$47)>0,IF(ISNUMBER(SEARCH(BRAIN!$C$47,AK5)),BRAIN!$C$47&", ",""),"") & IF(LEN(BRAIN!$C$48)>0,IF(ISNUMBER(SEARCH(BRAIN!$C$48,AK5)),BRAIN!$C$48&", ",""),"") & IF(LEN(BRAIN!$C$49)>0,IF(ISNUMBER(SEARCH(BRAIN!$C$49,AK5)),BRAIN!$C$49&", ",""),"") & IF(LEN(BRAIN!$C$50)>0,IF(ISNUMBER(SEARCH(BRAIN!$C$50,AK5)),BRAIN!$C$50&", ",""),"") & IF(LEN(BRAIN!$C$51)>0,IF(ISNUMBER(SEARCH(BRAIN!$C$51,AK5)),BRAIN!$C$51&", ",""),"") & IF(LEN(BRAIN!$C$52)>0,IF(ISNUMBER(SEARCH(BRAIN!$C$52,AK5)),BRAIN!$C$52&", ",""),"") & IF(LEN(BRAIN!$C$53)>0,IF(ISNUMBER(SEARCH(BRAIN!$C$53,AK5)),BRAIN!$C$53&", ",""),"") & IF(LEN(BRAIN!$C$54)>0,IF(ISNUMBER(SEARCH(BRAIN!$C$54,AK5)),BRAIN!$C$54&", ",""),"") & IF(LEN(BRAIN!$C$55)>0,IF(ISNUMBER(SEARCH(BRAIN!$C$55,AK5)),BRAIN!$C$55&", ",""),"") & IF(LEN(BRAIN!$C$56)>0,IF(ISNUMBER(SEARCH(BRAIN!$C$56,AK5)),BRAIN!$C$56&", ",""),"") & IF(LEN(BRAIN!$C$57)>0,IF(ISNUMBER(SEARCH(BRAIN!$C$57,AK5)),BRAIN!$C$57&", ",""),""))),"") -> recruit, recruiter, candidate, cv, resume, interview, scorecard, shortlist, jd, screening | AN5: =IFERROR(IF(RIGHT((IF(LEN(BRAIN!$D$26)>0,IF(ISNUMBER(SEARCH(BRAIN!$D$26,AK5)),BRAIN!$D$26&", ",""),"") & IF(LEN(BRAIN!$D$27)>0,IF(ISNUMBER(SEARCH(BRAIN!$D$27,AK5)),BRAIN!$D$27&", ",""),"") & IF(LEN(BRAIN!$D$28)>0,IF(ISNUMBER(SEARCH(BRAIN!$D$28,AK5)),BRAIN!$D$28&", ",""),"") & IF(LEN(BRAIN!$D$29)>0,IF(ISNUMBER(SEARCH(BRAIN!$D$29,AK5)),BRAIN!$D$29&", ",""),"") & IF(LEN(BRAIN!$D$30)>0,IF(ISNUMBER(SEARCH(BRAIN!$D$30,AK5)),BRAIN!$D$30&", ",""),"") & IF(LEN(BRAIN!$D$31)>0,IF(ISNUMBER(SEARCH(BRAIN!$D$31,AK5)),BRAIN!$D$31&", ",""),"") & IF(LEN(BRAIN!$D$32)>0,IF(ISNUMBER(SEARCH(BRAIN!$D$32,AK5)),BRAIN!$D$32&", ",""),"") & IF(LEN(BRAIN!$D$33)>0,IF(ISNUMBER(SEARCH(BRAIN!$D$33,AK5)),BRAIN!$D$33&", ",""),"") & IF(LEN(BRAIN!$D$34)>0,IF(ISNUMBER(SEARCH(BRAIN!$D$34,AK5)),BRAIN!$D$34&", ",""),"") & IF(LEN(BRAIN!$D$35)>0,IF(ISNUMBER(SEARCH(BRAIN!$D$35,AK5)),BRAIN!$D$35&", ",""),"") & IF(LEN(BRAIN!$D$36)>0,IF(ISNUMBER(SEARCH(BRAIN!$D$36,AK5)),BRAIN!$D$36&", ",""),"") & IF(LEN(BRAIN!$D$37)>0,IF(ISNUMBER(SEARCH(BRAIN!$D$37,AK5)),BRAIN!$D$37&", ",""),"") & IF(LEN(BRAIN!$D$38)>0,IF(ISNUMBER(SEARCH(BRAIN!$D$38,AK5)),BRAIN!$D$38&", ",""),"") & IF(LEN(BRAIN!$D$39)>0,IF(ISNUMBER(SEARCH(BRAIN!$D$39,AK5)),BRAIN!$D$39&", ",""),"") & IF(LEN(BRAIN!$D$40)>0,IF(ISNUMBER(SEARCH(BRAIN!$D$40,AK5)),BRAIN!$D$40&", ",""),"") & IF(LEN(BRAIN!$D$41)>0,IF(ISNUMBER(SEARCH(BRAIN!$D$41,AK5)),BRAIN!$D$41&", ",""),"") & IF(LEN(BRAIN!$D$42)>0,IF(ISNUMBER(SEARCH(BRAIN!$D$42,AK5)),BRAIN!$D$42&", ",""),"") & IF(LEN(BRAIN!$D$43)>0,IF(ISNUMBER(SEARCH(BRAIN!$D$43,AK5)),BRAIN!$D$43&", ",""),"") & IF(LEN(BRAIN!$D$44)>0,IF(ISNUMBER(SEARCH(BRAIN!$D$44,AK5)),BRAIN!$D$44&", ",""),"") & IF(LEN(BRAIN!$D$45)>0,IF(ISNUMBER(SEARCH(BRAIN!$D$45,AK5)),BRAIN!$D$45&", ",""),"") & IF(LEN(BRAIN!$D$46)>0,IF(ISNUMBER(SEARCH(BRAIN!$D$46,AK5)),BRAIN!$D$46&", ",""),"") & IF(LEN(BRAIN!$D$47)>0,IF(ISNUMBER(SEARCH(BRAIN!$D$47,AK5)),BRAIN!$D$47&", ",""),"") & IF(LEN(BRAIN!$D$48)>0,IF(ISNUMBER(SEARCH(BRAIN!$D$48,AK5)),BRAIN!$D$48&", ",""),"") & IF(LEN(BRAIN!$D$49)>0,IF(ISNUMBER(SEARCH(BRAIN!$D$49,AK5)),BRAIN!$D$49&", ",""),"") & IF(LEN(BRAIN!$D$50)>0,IF(ISNUMBER(SEARCH(BRAIN!$D$50,AK5)),BRAIN!$D$50&", ",""),"") & IF(LEN(BRAIN!$D$51)>0,IF(ISNUMBER(SEARCH(BRAIN!$D$51,AK5)),BRAIN!$D$51&", ",""),"") & IF(LEN(BRAIN!$D$52)>0,IF(ISNUMBER(SEARCH(BRAIN!$D$52,AK5)),BRAIN!$D$52&", ",""),"") & IF(LEN(BRAIN!$D$53)>0,IF(ISNUMBER(SEARCH(BRAIN!$D$53,AK5)),BRAIN!$D$53&", ",""),"") & IF(LEN(BRAIN!$D$54)>0,IF(ISNUMBER(SEARCH(BRAIN!$D$54,AK5)),BRAIN!$D$54&", ",""),"") & IF(LEN(BRAIN!$D$55)>0,IF(ISNUMBER(SEARCH(BRAIN!$D$55,AK5)),BRAIN!$D$55&", ",""),"") & IF(LEN(BRAIN!$D$56)>0,IF(ISNUMBER(SEARCH(BRAIN!$D$56,AK5)),BRAIN!$D$56&", ",""),"") & IF(LEN(BRAIN!$D$57)>0,IF(ISNUMBER(SEARCH(BRAIN!$D$57,AK5)),BRAIN!$D$57&", ",""),"")),2)=", ",LEFT((IF(LEN(BRAIN!$D$26)>0,IF(ISNUMBER(SEARCH(BRAIN!$D$26,AK5)),BRAIN!$D$26&", ",""),"") & IF(LEN(BRAIN!$D$27)>0,IF(ISNUMBER(SEARCH(BRAIN!$D$27,AK5)),BRAIN!$D$27&", ",""),"") & IF(LEN(BRAIN!$D$28)>0,IF(ISNUMBER(SEARCH(BRAIN!$D$28,AK5)),BRAIN!$D$28&", ",""),"") & IF(LEN(BRAIN!$D$29)>0,IF(ISNUMBER(SEARCH(BRAIN!$D$29,AK5)),BRAIN!$D$29&", ",""),"") & IF(LEN(BRAIN!$D$30)>0,IF(ISNUMBER(SEARCH(BRAIN!$D$30,AK5)),BRAIN!$D$30&", ",""),"") & IF(LEN(BRAIN!$D$31)>0,IF(ISNUMBER(SEARCH(BRAIN!$D$31,AK5)),BRAIN!$D$31&", ",""),"") & IF(LEN(BRAIN!$D$32)>0,IF(ISNUMBER(SEARCH(BRAIN!$D$32,AK5)),BRAIN!$D$32&", ",""),"") & IF(LEN(BRAIN!$D$33)>0,IF(ISNUMBER(SEARCH(BRAIN!$D$33,AK5)),BRAIN!$D$33&", ",""),"") & IF(LEN(BRAIN!$D$34)>0,IF(ISNUMBER(SEARCH(BRAIN!$D$34,AK5)),BRAIN!$D$34&", ",""),"") & IF(LEN(BRAIN!$D$35)>0,IF(ISNUMBER(SEARCH(BRAIN!$D$35,AK5)),BRAIN!$D$35&", ",""),"") & IF(LEN(BRAIN!$D$36)>0,IF(ISNUMBER(SEARCH(BRAIN!$D$36,AK5)),BRAIN!$D$36&", ",""),"") & IF(LEN(BRAIN!$D$37)>0,IF(ISNUMBER(SEARCH(BRAIN!$D$37,AK5)),BRAIN!$D$37&", ",""),"") & IF(LEN(BRAIN!$D$38)>0,IF(ISNUMBER(SEARCH(BRAIN!$D$38,AK5)),BRAIN!$D$38&", ",""),"") & IF(LEN(BRAIN!$D$39)>0,IF(ISNUMBER(SEARCH(BRAIN!$D$39,AK5)),BRAIN!$D$39&", ",""),"") & IF(LEN(BRAIN!$D$40)>0,IF(ISNUMBER(SEARCH(BRAIN!$D$40,AK5)),BRAIN!$D$40&", ",""),"") & IF(LEN(BRAIN!$D$41)>0,IF(ISNUMBER(SEARCH(BRAIN!$D$41,AK5)),BRAIN!$D$41&", ",""),"") & IF(LEN(BRAIN!$D$42)>0,IF(ISNUMBER(SEARCH(BRAIN!$D$42,AK5)),BRAIN!$D$42&", ",""),"") & IF(LEN(BRAIN!$D$43)>0,IF(ISNUMBER(SEARCH(BRAIN!$D$43,AK5)),BRAIN!$D$43&", ",""),"") & IF(LEN(BRAIN!$D$44)>0,IF(ISNUMBER(SEARCH(BRAIN!$D$44,AK5)),BRAIN!$D$44&", ",""),"") & IF(LEN(BRAIN!$D$45)>0,IF(ISNUMBER(SEARCH(BRAIN!$D$45,AK5)),BRAIN!$D$45&", ",""),"") & IF(LEN(BRAIN!$D$46)>0,IF(ISNUMBER(SEARCH(BRAIN!$D$46,AK5)),BRAIN!$D$46&", ",""),"") & IF(LEN(BRAIN!$D$47)>0,IF(ISNUMBER(SEARCH(BRAIN!$D$47,AK5)),BRAIN!$D$47&", ",""),"") & IF(LEN(BRAIN!$D$48)>0,IF(ISNUMBER(SEARCH(BRAIN!$D$48,AK5)),BRAIN!$D$48&", ",""),"") & IF(LEN(BRAIN!$D$49)>0,IF(ISNUMBER(SEARCH(BRAIN!$D$49,AK5)),BRAIN!$D$49&", ",""),"") & IF(LEN(BRAIN!$D$50)>0,IF(ISNUMBER(SEARCH(BRAIN!$D$50,AK5)),BRAIN!$D$50&", ",""),"") & IF(LEN(BRAIN!$D$51)>0,IF(ISNUMBER(SEARCH(BRAIN!$D$51,AK5)),BRAIN!$D$51&", ",""),"") & IF(LEN(BRAIN!$D$52)>0,IF(ISNUMBER(SEARCH(BRAIN!$D$52,AK5)),BRAIN!$D$52&", ",""),"") & IF(LEN(BRAIN!$D$53)>0,IF(ISNUMBER(SEARCH(BRAIN!$D$53,AK5)),BRAIN!$D$53&", ",""),"") & IF(LEN(BRAIN!$D$54)>0,IF(ISNUMBER(SEARCH(BRAIN!$D$54,AK5)),BRAIN!$D$54&", ",""),"") & IF(LEN(BRAIN!$D$55)>0,IF(ISNUMBER(SEARCH(BRAIN!$D$55,AK5)),BRAIN!$D$55&", ",""),"") & IF(LEN(BRAIN!$D$56)>0,IF(ISNUMBER(SEARCH(BRAIN!$D$56,AK5)),BRAIN!$D$56&", ",""),"") & IF(LEN(BRAIN!$D$57)>0,IF(ISNUMBER(SEARCH(BRAIN!$D$57,AK5)),BRAIN!$D$57&", ",""),"")),LEN((IF(LEN(BRAIN!$D$26)>0,IF(ISNUMBER(SEARCH(BRAIN!$D$26,AK5)),BRAIN!$D$26&", ",""),"") & IF(LEN(BRAIN!$D$27)>0,IF(ISNUMBER(SEARCH(BRAIN!$D$27,AK5)),BRAIN!$D$27&", ",""),"") & IF(LEN(BRAIN!$D$28)>0,IF(ISNUMBER(SEARCH(BRAIN!$D$28,AK5)),BRAIN!$D$28&", ",""),"") & IF(LEN(BRAIN!$D$29)>0,IF(ISNUMBER(SEARCH(BRAIN!$D$29,AK5)),BRAIN!$D$29&", ",""),"") & IF(LEN(BRAIN!$D$30)>0,IF(ISNUMBER(SEARCH(BRAIN!$D$30,AK5)),BRAIN!$D$30&", ",""),"") & IF(LEN(BRAIN!$D$31)>0,IF(ISNUMBER(SEARCH(BRAIN!$D$31,AK5)),BRAIN!$D$31&", ",""),"") & IF(LEN(BRAIN!$D$32)>0,IF(ISNUMBER(SEARCH(BRAIN!$D$32,AK5)),BRAIN!$D$32&", ",""),"") & IF(LEN(BRAIN!$D$33)>0,IF(ISNUMBER(SEARCH(BRAIN!$D$33,AK5)),BRAIN!$D$33&", ",""),"") & IF(LEN(BRAIN!$D$34)>0,IF(ISNUMBER(SEARCH(BRAIN!$D$34,AK5)),BRAIN!$D$34&", ",""),"") & IF(LEN(BRAIN!$D$35)>0,IF(ISNUMBER(SEARCH(BRAIN!$D$35,AK5)),BRAIN!$D$35&", ",""),"") & IF(LEN(BRAIN!$D$36)>0,IF(ISNUMBER(SEARCH(BRAIN!$D$36,AK5)),BRAIN!$D$36&", ",""),"") & IF(LEN(BRAIN!$D$37)>0,IF(ISNUMBER(SEARCH(BRAIN!$D$37,AK5)),BRAIN!$D$37&", ",""),"") & IF(LEN(BRAIN!$D$38)>0,IF(ISNUMBER(SEARCH(BRAIN!$D$38,AK5)),BRAIN!$D$38&", ",""),"") & IF(LEN(BRAIN!$D$39)>0,IF(ISNUMBER(SEARCH(BRAIN!$D$39,AK5)),BRAIN!$D$39&", ",""),"") & IF(LEN(BRAIN!$D$40)>0,IF(ISNUMBER(SEARCH(BRAIN!$D$40,AK5)),BRAIN!$D$40&", ",""),"") & IF(LEN(BRAIN!$D$41)>0,IF(ISNUMBER(SEARCH(BRAIN!$D$41,AK5)),BRAIN!$D$41&", ",""),"") & IF(LEN(BRAIN!$D$42)>0,IF(ISNUMBER(SEARCH(BRAIN!$D$42,AK5)),BRAIN!$D$42&", ",""),"") & IF(LEN(BRAIN!$D$43)>0,IF(ISNUMBER(SEARCH(BRAIN!$D$43,AK5)),BRAIN!$D$43&", ",""),"") & IF(LEN(BRAIN!$D$44)>0,IF(ISNUMBER(SEARCH(BRAIN!$D$44,AK5)),BRAIN!$D$44&", ",""),"") & IF(LEN(BRAIN!$D$45)>0,IF(ISNUMBER(SEARCH(BRAIN!$D$45,AK5)),BRAIN!$D$45&", ",""),"") & IF(LEN(BRAIN!$D$46)>0,IF(ISNUMBER(SEARCH(BRAIN!$D$46,AK5)),BRAIN!$D$46&", ",""),"") & IF(LEN(BRAIN!$D$47)>0,IF(ISNUMBER(SEARCH(BRAIN!$D$47,AK5)),BRAIN!$D$47&", ",""),"") & IF(LEN(BRAIN!$D$48)>0,IF(ISNUMBER(SEARCH(BRAIN!$D$48,AK5)),BRAIN!$D$48&", ",""),"") & IF(LEN(BRAIN!$D$49)>0,IF(ISNUMBER(SEARCH(BRAIN!$D$49,AK5)),BRAIN!$D$49&", ",""),"") & IF(LEN(BRAIN!$D$50)>0,IF(ISNUMBER(SEARCH(BRAIN!$D$50,AK5)),BRAIN!$D$50&", ",""),"") & IF(LEN(BRAIN!$D$51)>0,IF(ISNUMBER(SEARCH(BRAIN!$D$51,AK5)),BRAIN!$D$51&", ",""),"") & IF(LEN(BRAIN!$D$52)>0,IF(ISNUMBER(SEARCH(BRAIN!$D$52,AK5)),BRAIN!$D$52&", ",""),"") & IF(LEN(BRAIN!$D$53)>0,IF(ISNUMBER(SEARCH(BRAIN!$D$53,AK5)),BRAIN!$D$53&", ",""),"") & IF(LEN(BRAIN!$D$54)>0,IF(ISNUMBER(SEARCH(BRAIN!$D$54,AK5)),BRAIN!$D$54&", ",""),"") & IF(LEN(BRAIN!$D$55)>0,IF(ISNUMBER(SEARCH(BRAIN!$D$55,AK5)),BRAIN!$D$55&", ",""),"") & IF(LEN(BRAIN!$D$56)>0,IF(ISNUMBER(SEARCH(BRAIN!$D$56,AK5)),BRAIN!$D$56&", ",""),"") & IF(LEN(BRAIN!$D$57)>0,IF(ISNUMBER(SEARCH(BRAIN!$D$57,AK5)),BRAIN!$D$57&", ",""),"")))-2),(IF(LEN(BRAIN!$D$26)>0,IF(ISNUMBER(SEARCH(BRAIN!$D$26,AK5)),BRAIN!$D$26&", ",""),"") & IF(LEN(BRAIN!$D$27)>0,IF(ISNUMBER(SEARCH(BRAIN!$D$27,AK5)),BRAIN!$D$27&", ",""),"") & IF(LEN(BRAIN!$D$28)>0,IF(ISNUMBER(SEARCH(BRAIN!$D$28,AK5)),BRAIN!$D$28&", ",""),"") & IF(LEN(BRAIN!$D$29)>0,IF(ISNUMBER(SEARCH(BRAIN!$D$29,AK5)),BRAIN!$D$29&", ",""),"") & IF(LEN(BRAIN!$D$30)>0,IF(ISNUMBER(SEARCH(BRAIN!$D$30,AK5)),BRAIN!$D$30&", ",""),"") & IF(LEN(BRAIN!$D$31)>0,IF(ISNUMBER(SEARCH(BRAIN!$D$31,AK5)),BRAIN!$D$31&", ",""),"") & IF(LEN(BRAIN!$D$32)>0,IF(ISNUMBER(SEARCH(BRAIN!$D$32,AK5)),BRAIN!$D$32&", ",""),"") & IF(LEN(BRAIN!$D$33)>0,IF(ISNUMBER(SEARCH(BRAIN!$D$33,AK5)),BRAIN!$D$33&", ",""),"") & IF(LEN(BRAIN!$D$34)>0,IF(ISNUMBER(SEARCH(BRAIN!$D$34,AK5)),BRAIN!$D$34&", ",""),"") & IF(LEN(BRAIN!$D$35)>0,IF(ISNUMBER(SEARCH(BRAIN!$D$35,AK5)),BRAIN!$D$35&", ",""),"") & IF(LEN(BRAIN!$D$36)>0,IF(ISNUMBER(SEARCH(BRAIN!$D$36,AK5)),BRAIN!$D$36&", ",""),"") & IF(LEN(BRAIN!$D$37)>0,IF(ISNUMBER(SEARCH(BRAIN!$D$37,AK5)),BRAIN!$D$37&", ",""),"") & IF(LEN(BRAIN!$D$38)>0,IF(ISNUMBER(SEARCH(BRAIN!$D$38,AK5)),BRAIN!$D$38&", ",""),"") & IF(LEN(BRAIN!$D$39)>0,IF(ISNUMBER(SEARCH(BRAIN!$D$39,AK5)),BRAIN!$D$39&", ",""),"") & IF(LEN(BRAIN!$D$40)>0,IF(ISNUMBER(SEARCH(BRAIN!$D$40,AK5)),BRAIN!$D$40&", ",""),"") & IF(LEN(BRAIN!$D$41)>0,IF(ISNUMBER(SEARCH(BRAIN!$D$41,AK5)),BRAIN!$D$41&", ",""),"") & IF(LEN(BRAIN!$D$42)>0,IF(ISNUMBER(SEARCH(BRAIN!$D$42,AK5)),BRAIN!$D$42&", ",""),"") & IF(LEN(BRAIN!$D$43)>0,IF(ISNUMBER(SEARCH(BRAIN!$D$43,AK5)),BRAIN!$D$43&", ",""),"") & IF(LEN(BRAIN!$D$44)>0,IF(ISNUMBER(SEARCH(BRAIN!$D$44,AK5)),BRAIN!$D$44&", ",""),"") & IF(LEN(BRAIN!$D$45)>0,IF(ISNUMBER(SEARCH(BRAIN!$D$45,AK5)),BRAIN!$D$45&", ",""),"") & IF(LEN(BRAIN!$D$46)>0,IF(ISNUMBER(SEARCH(BRAIN!$D$46,AK5)),BRAIN!$D$46&", ",""),"") & IF(LEN(BRAIN!$D$47)>0,IF(ISNUMBER(SEARCH(BRAIN!$D$47,AK5)),BRAIN!$D$47&", ",""),"") & IF(LEN(BRAIN!$D$48)>0,IF(ISNUMBER(SEARCH(BRAIN!$D$48,AK5)),BRAIN!$D$48&", ",""),"") & IF(LEN(BRAIN!$D$49)>0,IF(ISNUMBER(SEARCH(BRAIN!$D$49,AK5)),BRAIN!$D$49&", ",""),"") & IF(LEN(BRAIN!$D$50)>0,IF(ISNUMBER(SEARCH(BRAIN!$D$50,AK5)),BRAIN!$D$50&", ",""),"") & IF(LEN(BRAIN!$D$51)>0,IF(ISNUMBER(SEARCH(BRAIN!$D$51,AK5)),BRAIN!$D$51&", ",""),"") & IF(LEN(BRAIN!$D$52)>0,IF(ISNUMBER(SEARCH(BRAIN!$D$52,AK5)),BRAIN!$D$52&", ",""),"") & IF(LEN(BRAIN!$D$53)>0,IF(ISNUMBER(SEARCH(BRAIN!$D$53,AK5)),BRAIN!$D$53&", ",""),"") & IF(LEN(BRAIN!$D$54)>0,IF(ISNUMBER(SEARCH(BRAIN!$D$54,AK5)),BRAIN!$D$54&", ",""),"") & IF(LEN(BRAIN!$D$55)>0,IF(ISNUMBER(SEARCH(BRAIN!$D$55,AK5)),BRAIN!$D$55&", ",""),"") & IF(LEN(BRAIN!$D$56)>0,IF(ISNUMBER(SEARCH(BRAIN!$D$56,AK5)),BRAIN!$D$56&", ",""),"") & IF(LEN(BRAIN!$D$57)>0,IF(ISNUMBER(SEARCH(BRAIN!$D$57,AK5)),BRAIN!$D$57&", ",""),""))),"") | AO5: =IFERROR(IF(RIGHT((IF(LEN(BRAIN!$E$26)>0,IF(ISNUMBER(SEARCH(BRAIN!$E$26,AK5)),BRAIN!$E$26&", ",""),"") & IF(LEN(BRAIN!$E$27)>0,IF(ISNUMBER(SEARCH(BRAIN!$E$27,AK5)),BRAIN!$E$27&", ",""),"") & IF(LEN(BRAIN!$E$28)>0,IF(ISNUMBER(SEARCH(BRAIN!$E$28,AK5)),BRAIN!$E$28&", ",""),"") & IF(LEN(BRAIN!$E$29)>0,IF(ISNUMBER(SEARCH(BRAIN!$E$29,AK5)),BRAIN!$E$29&", ",""),"") & IF(LEN(BRAIN!$E$30)>0,IF(ISNUMBER(SEARCH(BRAIN!$E$30,AK5)),BRAIN!$E$30&", ",""),"") & IF(LEN(BRAIN!$E$31)>0,IF(ISNUMBER(SEARCH(BRAIN!$E$31,AK5)),BRAIN!$E$31&", ",""),"") & IF(LEN(BRAIN!$E$32)>0,IF(ISNUMBER(SEARCH(BRAIN!$E$32,AK5)),BRAIN!$E$32&", ",""),"") & IF(LEN(BRAIN!$E$33)>0,IF(ISNUMBER(SEARCH(BRAIN!$E$33,AK5)),BRAIN!$E$33&", ",""),"") & IF(LEN(BRAIN!$E$34)>0,IF(ISNUMBER(SEARCH(BRAIN!$E$34,AK5)),BRAIN!$E$34&", ",""),"") & IF(LEN(BRAIN!$E$35)>0,IF(ISNUMBER(SEARCH(BRAIN!$E$35,AK5)),BRAIN!$E$35&", ",""),"") & IF(LEN(BRAIN!$E$36)>0,IF(ISNUMBER(SEARCH(BRAIN!$E$36,AK5)),BRAIN!$E$36&", ",""),"") & IF(LEN(BRAIN!$E$37)>0,IF(ISNUMBER(SEARCH(BRAIN!$E$37,AK5)),BRAIN!$E$37&", ",""),"") & IF(LEN(BRAIN!$E$38)>0,IF(ISNUMBER(SEARCH(BRAIN!$E$38,AK5)),BRAIN!$E$38&", ",""),"") & IF(LEN(BRAIN!$E$39)>0,IF(ISNUMBER(SEARCH(BRAIN!$E$39,AK5)),BRAIN!$E$39&", ",""),"") & IF(LEN(BRAIN!$E$40)>0,IF(ISNUMBER(SEARCH(BRAIN!$E$40,AK5)),BRAIN!$E$40&", ",""),"") & IF(LEN(BRAIN!$E$41)>0,IF(ISNUMBER(SEARCH(BRAIN!$E$41,AK5)),BRAIN!$E$41&", ",""),"") & IF(LEN(BRAIN!$E$42)>0,IF(ISNUMBER(SEARCH(BRAIN!$E$42,AK5)),BRAIN!$E$42&", ",""),"") & IF(LEN(BRAIN!$E$43)>0,IF(ISNUMBER(SEARCH(BRAIN!$E$43,AK5)),BRAIN!$E$43&", ",""),"") & IF(LEN(BRAIN!$E$44)>0,IF(ISNUMBER(SEARCH(BRAIN!$E$44,AK5)),BRAIN!$E$44&", ",""),"") & IF(LEN(BRAIN!$E$45)>0,IF(ISNUMBER(SEARCH(BRAIN!$E$45,AK5)),BRAIN!$E$45&", ",""),"") & IF(LEN(BRAIN!$E$46)>0,IF(ISNUMBER(SEARCH(BRAIN!$E$46,AK5)),BRAIN!$E$46&", ",""),"") & IF(LEN(BRAIN!$E$47)>0,IF(ISNUMBER(SEARCH(BRAIN!$E$47,AK5)),BRAIN!$E$47&", ",""),"") & IF(LEN(BRAIN!$E$48)>0,IF(ISNUMBER(SEARCH(BRAIN!$E$48,AK5)),BRAIN!$E$48&", ",""),"") & IF(LEN(BRAIN!$E$49)>0,IF(ISNUMBER(SEARCH(BRAIN!$E$49,AK5)),BRAIN!$E$49&", ",""),"") & IF(LEN(BRAIN!$E$50)>0,IF(ISNUMBER(SEARCH(BRAIN!$E$50,AK5)),BRAIN!$E$50&", ",""),"") & IF(LEN(BRAIN!$E$51)>0,IF(ISNUMBER(SEARCH(BRAIN!$E$51,AK5)),BRAIN!$E$51&", ",""),"") & IF(LEN(BRAIN!$E$52)>0,IF(ISNUMBER(SEARCH(BRAIN!$E$52,AK5)),BRAIN!$E$52&", ",""),"") & IF(LEN(BRAIN!$E$53)>0,IF(ISNUMBER(SEARCH(BRAIN!$E$53,AK5)),BRAIN!$E$53&", ",""),"") & IF(LEN(BRAIN!$E$54)>0,IF(ISNUMBER(SEARCH(BRAIN!$E$54,AK5)),BRAIN!$E$54&", ",""),"") & IF(LEN(BRAIN!$E$55)>0,IF(ISNUMBER(SEARCH(BRAIN!$E$55,AK5)),BRAIN!$E$55&", ",""),"") & IF(LEN(BRAIN!$E$56)>0,IF(ISNUMBER(SEARCH(BRAIN!$E$56,AK5)),BRAIN!$E$56&", ",""),"") & IF(LEN(BRAIN!$E$57)>0,IF(ISNUMBER(SEARCH(BRAIN!$E$57,AK5)),BRAIN!$E$57&", ",""),"")),2)=", ",LEFT((IF(LEN(BRAIN!$E$26)>0,IF(ISNUMBER(SEARCH(BRAIN!$E$26,AK5)),BRAIN!$E$26&", ",""),"") & IF(LEN(BRAIN!$E$27)>0,IF(ISNUMBER(SEARCH(BRAIN!$E$27,AK5)),BRAIN!$E$27&", ",""),"") & IF(LEN(BRAIN!$E$28)>0,IF(ISNUMBER(SEARCH(BRAIN!$E$28,AK5)),BRAIN!$E$28&", ",""),"") & IF(LEN(BRAIN!$E$29)>0,IF(ISNUMBER(SEARCH(BRAIN!$E$29,AK5)),BRAIN!$E$29&", ",""),"") & IF(LEN(BRAIN!$E$30)>0,IF(ISNUMBER(SEARCH(BRAIN!$E$30,AK5)),BRAIN!$E$30&", ",""),"") & IF(LEN(BRAIN!$E$31)>0,IF(ISNUMBER(SEARCH(BRAIN!$E$31,AK5)),BRAIN!$E$31&", ",""),"") & IF(LEN(BRAIN!$E$32)>0,IF(ISNUMBER(SEARCH(BRAIN!$E$32,AK5)),BRAIN!$E$32&", ",""),"") & IF(LEN(BRAIN!$E$33)>0,IF(ISNUMBER(SEARCH(BRAIN!$E$33,AK5)),BRAIN!$E$33&", ",""),"") & IF(LEN(BRAIN!$E$34)>0,IF(ISNUMBER(SEARCH(BRAIN!$E$34,AK5)),BRAIN!$E$34&", ",""),"") & IF(LEN(BRAIN!$E$35)>0,IF(ISNUMBER(SEARCH(BRAIN!$E$35,AK5)),BRAIN!$E$35&", ",""),"") & IF(LEN(BRAIN!$E$36)>0,IF(ISNUMBER(SEARCH(BRAIN!$E$36,AK5)),BRAIN!$E$36&", ",""),"") & IF(LEN(BRAIN!$E$37)>0,IF(ISNUMBER(SEARCH(BRAIN!$E$37,AK5)),BRAIN!$E$37&", ",""),"") & IF(LEN(BRAIN!$E$38)>0,IF(ISNUMBER(SEARCH(BRAIN!$E$38,AK5)),BRAIN!$E$38&", ",""),"") & IF(LEN(BRAIN!$E$39)>0,IF(ISNUMBER(SEARCH(BRAIN!$E$39,AK5)),BRAIN!$E$39&", ",""),"") & IF(LEN(BRAIN!$E$40)>0,IF(ISNUMBER(SEARCH(BRAIN!$E$40,AK5)),BRAIN!$E$40&", ",""),"") & IF(LEN(BRAIN!$E$41)>0,IF(ISNUMBER(SEARCH(BRAIN!$E$41,AK5)),BRAIN!$E$41&", ",""),"") & IF(LEN(BRAIN!$E$42)>0,IF(ISNUMBER(SEARCH(BRAIN!$E$42,AK5)),BRAIN!$E$42&", ",""),"") & IF(LEN(BRAIN!$E$43)>0,IF(ISNUMBER(SEARCH(BRAIN!$E$43,AK5)),BRAIN!$E$43&", ",""),"") & IF(LEN(BRAIN!$E$44)>0,IF(ISNUMBER(SEARCH(BRAIN!$E$44,AK5)),BRAIN!$E$44&", ",""),"") & IF(LEN(BRAIN!$E$45)>0,IF(ISNUMBER(SEARCH(BRAIN!$E$45,AK5)),BRAIN!$E$45&", ",""),"") & IF(LEN(BRAIN!$E$46)>0,IF(ISNUMBER(SEARCH(BRAIN!$E$46,AK5)),BRAIN!$E$46&", ",""),"") & IF(LEN(BRAIN!$E$47)>0,IF(ISNUMBER(SEARCH(BRAIN!$E$47,AK5)),BRAIN!$E$47&", ",""),"") & IF(LEN(BRAIN!$E$48)>0,IF(ISNUMBER(SEARCH(BRAIN!$E$48,AK5)),BRAIN!$E$48&", ",""),"") & IF(LEN(BRAIN!$E$49)>0,IF(ISNUMBER(SEARCH(BRAIN!$E$49,AK5)),BRAIN!$E$49&", ",""),"") & IF(LEN(BRAIN!$E$50)>0,IF(ISNUMBER(SEARCH(BRAIN!$E$50,AK5)),BRAIN!$E$50&", ",""),"") & IF(LEN(BRAIN!$E$51)>0,IF(ISNUMBER(SEARCH(BRAIN!$E$51,AK5)),BRAIN!$E$51&", ",""),"") & IF(LEN(BRAIN!$E$52)>0,IF(ISNUMBER(SEARCH(BRAIN!$E$52,AK5)),BRAIN!$E$52&", ",""),"") & IF(LEN(BRAIN!$E$53)>0,IF(ISNUMBER(SEARCH(BRAIN!$E$53,AK5)),BRAIN!$E$53&", ",""),"") & IF(LEN(BRAIN!$E$54)>0,IF(ISNUMBER(SEARCH(BRAIN!$E$54,AK5)),BRAIN!$E$54&", ",""),"") & IF(LEN(BRAIN!$E$55)>0,IF(ISNUMBER(SEARCH(BRAIN!$E$55,AK5)),BRAIN!$E$55&", ",""),"") & IF(LEN(BRAIN!$E$56)>0,IF(ISNUMBER(SEARCH(BRAIN!$E$56,AK5)),BRAIN!$E$56&", ",""),"") & IF(LEN(BRAIN!$E$57)>0,IF(ISNUMBER(SEARCH(BRAIN!$E$57,AK5)),BRAIN!$E$57&", ",""),"")),LEN((IF(LEN(BRAIN!$E$26)>0,IF(ISNUMBER(SEARCH(BRAIN!$E$26,AK5)),BRAIN!$E$26&", ",""),"") & IF(LEN(BRAIN!$E$27)>0,IF(ISNUMBER(SEARCH(BRAIN!$E$27,AK5)),BRAIN!$E$27&", ",""),"") & IF(LEN(BRAIN!$E$28)>0,IF(ISNUMBER(SEARCH(BRAIN!$E$28,AK5)),BRAIN!$E$28&", ",""),"") & IF(LEN(BRAIN!$E$29)>0,IF(ISNUMBER(SEARCH(BRAIN!$E$29,AK5)),BRAIN!$E$29&", ",""),"") & IF(LEN(BRAIN!$E$30)>0,IF(ISNUMBER(SEARCH(BRAIN!$E$30,AK5)),BRAIN!$E$30&", ",""),"") & IF(LEN(BRAIN!$E$31)>0,IF(ISNUMBER(SEARCH(BRAIN!$E$31,AK5)),BRAIN!$E$31&", ",""),"") & IF(LEN(BRAIN!$E$32)>0,IF(ISNUMBER(SEARCH(BRAIN!$E$32,AK5)),BRAIN!$E$32&", ",""),"") & IF(LEN(BRAIN!$E$33)>0,IF(ISNUMBER(SEARCH(BRAIN!$E$33,AK5)),BRAIN!$E$33&", ",""),"") & IF(LEN(BRAIN!$E$34)>0,IF(ISNUMBER(SEARCH(BRAIN!$E$34,AK5)),BRAIN!$E$34&", ",""),"") & IF(LEN(BRAIN!$E$35)>0,IF(ISNUMBER(SEARCH(BRAIN!$E$35,AK5)),BRAIN!$E$35&", ",""),"") & IF(LEN(BRAIN!$E$36)>0,IF(ISNUMBER(SEARCH(BRAIN!$E$36,AK5)),BRAIN!$E$36&", ",""),"") & IF(LEN(BRAIN!$E$37)>0,IF(ISNUMBER(SEARCH(BRAIN!$E$37,AK5)),BRAIN!$E$37&", ",""),"") & IF(LEN(BRAIN!$E$38)>0,IF(ISNUMBER(SEARCH(BRAIN!$E$38,AK5)),BRAIN!$E$38&", ",""),"") & IF(LEN(BRAIN!$E$39)>0,IF(ISNUMBER(SEARCH(BRAIN!$E$39,AK5)),BRAIN!$E$39&", ",""),"") & IF(LEN(BRAIN!$E$40)>0,IF(ISNUMBER(SEARCH(BRAIN!$E$40,AK5)),BRAIN!$E$40&", ",""),"") & IF(LEN(BRAIN!$E$41)>0,IF(ISNUMBER(SEARCH(BRAIN!$E$41,AK5)),BRAIN!$E$41&", ",""),"") & IF(LEN(BRAIN!$E$42)>0,IF(ISNUMBER(SEARCH(BRAIN!$E$42,AK5)),BRAIN!$E$42&", ",""),"") & IF(LEN(BRAIN!$E$43)>0,IF(ISNUMBER(SEARCH(BRAIN!$E$43,AK5)),BRAIN!$E$43&", ",""),"") & IF(LEN(BRAIN!$E$44)>0,IF(ISNUMBER(SEARCH(BRAIN!$E$44,AK5)),BRAIN!$E$44&", ",""),"") & IF(LEN(BRAIN!$E$45)>0,IF(ISNUMBER(SEARCH(BRAIN!$E$45,AK5)),BRAIN!$E$45&", ",""),"") & IF(LEN(BRAIN!$E$46)>0,IF(ISNUMBER(SEARCH(BRAIN!$E$46,AK5)),BRAIN!$E$46&", ",""),"") & IF(LEN(BRAIN!$E$47)>0,IF(ISNUMBER(SEARCH(BRAIN!$E$47,AK5)),BRAIN!$E$47&", ",""),"") & IF(LEN(BRAIN!$E$48)>0,IF(ISNUMBER(SEARCH(BRAIN!$E$48,AK5)),BRAIN!$E$48&", ",""),"") & IF(LEN(BRAIN!$E$49)>0,IF(ISNUMBER(SEARCH(BRAIN!$E$49,AK5)),BRAIN!$E$49&", ",""),"") & IF(LEN(BRAIN!$E$50)>0,IF(ISNUMBER(SEARCH(BRAIN!$E$50,AK5)),BRAIN!$E$50&", ",""),"") & IF(LEN(BRAIN!$E$51)>0,IF(ISNUMBER(SEARCH(BRAIN!$E$51,AK5)),BRAIN!$E$51&", ",""),"") & IF(LEN(BRAIN!$E$52)>0,IF(ISNUMBER(SEARCH(BRAIN!$E$52,AK5)),BRAIN!$E$52&", ",""),"") & IF(LEN(BRAIN!$E$53)>0,IF(ISNUMBER(SEARCH(BRAIN!$E$53,AK5)),BRAIN!$E$53&", ",""),"") & IF(LEN(BRAIN!$E$54)>0,IF(ISNUMBER(SEARCH(BRAIN!$E$54,AK5)),BRAIN!$E$54&", ",""),"") & IF(LEN(BRAIN!$E$55)>0,IF(ISNUMBER(SEARCH(BRAIN!$E$55,AK5)),BRAIN!$E$55&", ",""),"") & IF(LEN(BRAIN!$E$56)>0,IF(ISNUMBER(SEARCH(BRAIN!$E$56,AK5)),BRAIN!$E$56&", ",""),"") & IF(LEN(BRAIN!$E$57)>0,IF(ISNUMBER(SEARCH(BRAIN!$E$57,AK5)),BRAIN!$E$57&", ",""),"")))-2),(IF(LEN(BRAIN!$E$26)>0,IF(ISNUMBER(SEARCH(BRAIN!$E$26,AK5)),BRAIN!$E$26&", ",""),"") & IF(LEN(BRAIN!$E$27)>0,IF(ISNUMBER(SEARCH(BRAIN!$E$27,AK5)),BRAIN!$E$27&", ",""),"") & IF(LEN(BRAIN!$E$28)>0,IF(ISNUMBER(SEARCH(BRAIN!$E$28,AK5)),BRAIN!$E$28&", ",""),"") & IF(LEN(BRAIN!$E$29)>0,IF(ISNUMBER(SEARCH(BRAIN!$E$29,AK5)),BRAIN!$E$29&", ",""),"") & IF(LEN(BRAIN!$E$30)>0,IF(ISNUMBER(SEARCH(BRAIN!$E$30,AK5)),BRAIN!$E$30&", ",""),"") & IF(LEN(BRAIN!$E$31)>0,IF(ISNUMBER(SEARCH(BRAIN!$E$31,AK5)),BRAIN!$E$31&", ",""),"") & IF(LEN(BRAIN!$E$32)>0,IF(ISNUMBER(SEARCH(BRAIN!$E$32,AK5)),BRAIN!$E$32&", ",""),"") & IF(LEN(BRAIN!$E$33)>0,IF(ISNUMBER(SEARCH(BRAIN!$E$33,AK5)),BRAIN!$E$33&", ",""),"") & IF(LEN(BRAIN!$E$34)>0,IF(ISNUMBER(SEARCH(BRAIN!$E$34,AK5)),BRAIN!$E$34&", ",""),"") & IF(LEN(BRAIN!$E$35)>0,IF(ISNUMBER(SEARCH(BRAIN!$E$35,AK5)),BRAIN!$E$35&", ",""),"") & IF(LEN(BRAIN!$E$36)>0,IF(ISNUMBER(SEARCH(BRAIN!$E$36,AK5)),BRAIN!$E$36&", ",""),"") & IF(LEN(BRAIN!$E$37)>0,IF(ISNUMBER(SEARCH(BRAIN!$E$37,AK5)),BRAIN!$E$37&", ",""),"") & IF(LEN(BRAIN!$E$38)>0,IF(ISNUMBER(SEARCH(BRAIN!$E$38,AK5)),BRAIN!$E$38&", ",""),"") & IF(LEN(BRAIN!$E$39)>0,IF(ISNUMBER(SEARCH(BRAIN!$E$39,AK5)),BRAIN!$E$39&", ",""),"") & IF(LEN(BRAIN!$E$40)>0,IF(ISNUMBER(SEARCH(BRAIN!$E$40,AK5)),BRAIN!$E$40&", ",""),"") & IF(LEN(BRAIN!$E$41)>0,IF(ISNUMBER(SEARCH(BRAIN!$E$41,AK5)),BRAIN!$E$41&", ",""),"") & IF(LEN(BRAIN!$E$42)>0,IF(ISNUMBER(SEARCH(BRAIN!$E$42,AK5)),BRAIN!$E$42&", ",""),"") & IF(LEN(BRAIN!$E$43)>0,IF(ISNUMBER(SEARCH(BRAIN!$E$43,AK5)),BRAIN!$E$43&", ",""),"") & IF(LEN(BRAIN!$E$44)>0,IF(ISNUMBER(SEARCH(BRAIN!$E$44,AK5)),BRAIN!$E$44&", ",""),"") & IF(LEN(BRAIN!$E$45)>0,IF(ISNUMBER(SEARCH(BRAIN!$E$45,AK5)),BRAIN!$E$45&", ",""),"") & IF(LEN(BRAIN!$E$46)>0,IF(ISNUMBER(SEARCH(BRAIN!$E$46,AK5)),BRAIN!$E$46&", ",""),"") & IF(LEN(BRAIN!$E$47)>0,IF(ISNUMBER(SEARCH(BRAIN!$E$47,AK5)),BRAIN!$E$47&", ",""),"") & IF(LEN(BRAIN!$E$48)>0,IF(ISNUMBER(SEARCH(BRAIN!$E$48,AK5)),BRAIN!$E$48&", ",""),"") & IF(LEN(BRAIN!$E$49)>0,IF(ISNUMBER(SEARCH(BRAIN!$E$49,AK5)),BRAIN!$E$49&", ",""),"") & IF(LEN(BRAIN!$E$50)>0,IF(ISNUMBER(SEARCH(BRAIN!$E$50,AK5)),BRAIN!$E$50&", ",""),"") & IF(LEN(BRAIN!$E$51)>0,IF(ISNUMBER(SEARCH(BRAIN!$E$51,AK5)),BRAIN!$E$51&", ",""),"") & IF(LEN(BRAIN!$E$52)>0,IF(ISNUMBER(SEARCH(BRAIN!$E$52,AK5)),BRAIN!$E$52&", ",""),"") & IF(LEN(BRAIN!$E$53)>0,IF(ISNUMBER(SEARCH(BRAIN!$E$53,AK5)),BRAIN!$E$53&", ",""),"") & IF(LEN(BRAIN!$E$54)>0,IF(ISNUMBER(SEARCH(BRAIN!$E$54,AK5)),BRAIN!$E$54&", ",""),"") & IF(LEN(BRAIN!$E$55)>0,IF(ISNUMBER(SEARCH(BRAIN!$E$55,AK5)),BRAIN!$E$55&", ",""),"") & IF(LEN(BRAIN!$E$56)>0,IF(ISNUMBER(SEARCH(BRAIN!$E$56,AK5)),BRAIN!$E$56&", ",""),"") & IF(LEN(BRAIN!$E$57)>0,IF(ISNUMBER(SEARCH(BRAIN!$E$57,AK5)),BRAIN!$E$57&", ",""),""))),"") | AP5: =IFERROR(IF(RIGHT((IF(LEN(BRAIN!$F$26)>0,IF(ISNUMBER(SEARCH(BRAIN!$F$26,AK5)),BRAIN!$F$26&", ",""),"") & IF(LEN(BRAIN!$F$27)>0,IF(ISNUMBER(SEARCH(BRAIN!$F$27,AK5)),BRAIN!$F$27&", ",""),"") & IF(LEN(BRAIN!$F$28)>0,IF(ISNUMBER(SEARCH(BRAIN!$F$28,AK5)),BRAIN!$F$28&", ",""),"") & IF(LEN(BRAIN!$F$29)>0,IF(ISNUMBER(SEARCH(BRAIN!$F$29,AK5)),BRAIN!$F$29&", ",""),"") & IF(LEN(BRAIN!$F$30)>0,IF(ISNUMBER(SEARCH(BRAIN!$F$30,AK5)),BRAIN!$F$30&", ",""),"") & IF(LEN(BRAIN!$F$31)>0,IF(ISNUMBER(SEARCH(BRAIN!$F$31,AK5)),BRAIN!$F$31&", ",""),"") & IF(LEN(BRAIN!$F$32)>0,IF(ISNUMBER(SEARCH(BRAIN!$F$32,AK5)),BRAIN!$F$32&", ",""),"") & IF(LEN(BRAIN!$F$33)>0,IF(ISNUMBER(SEARCH(BRAIN!$F$33,AK5)),BRAIN!$F$33&", ",""),"") & IF(LEN(BRAIN!$F$34)>0,IF(ISNUMBER(SEARCH(BRAIN!$F$34,AK5)),BRAIN!$F$34&", ",""),"") & IF(LEN(BRAIN!$F$35)>0,IF(ISNUMBER(SEARCH(BRAIN!$F$35,AK5)),BRAIN!$F$35&", ",""),"") & IF(LEN(BRAIN!$F$36)>0,IF(ISNUMBER(SEARCH(BRAIN!$F$36,AK5)),BRAIN!$F$36&", ",""),"") & IF(LEN(BRAIN!$F$37)>0,IF(ISNUMBER(SEARCH(BRAIN!$F$37,AK5)),BRAIN!$F$37&", ",""),"") & IF(LEN(BRAIN!$F$38)>0,IF(ISNUMBER(SEARCH(BRAIN!$F$38,AK5)),BRAIN!$F$38&", ",""),"") & IF(LEN(BRAIN!$F$39)>0,IF(ISNUMBER(SEARCH(BRAIN!$F$39,AK5)),BRAIN!$F$39&", ",""),"") & IF(LEN(BRAIN!$F$40)>0,IF(ISNUMBER(SEARCH(BRAIN!$F$40,AK5)),BRAIN!$F$40&", ",""),"") & IF(LEN(BRAIN!$F$41)>0,IF(ISNUMBER(SEARCH(BRAIN!$F$41,AK5)),BRAIN!$F$41&", ",""),"") & IF(LEN(BRAIN!$F$42)>0,IF(ISNUMBER(SEARCH(BRAIN!$F$42,AK5)),BRAIN!$F$42&", ",""),"") & IF(LEN(BRAIN!$F$43)>0,IF(ISNUMBER(SEARCH(BRAIN!$F$43,AK5)),BRAIN!$F$43&", ",""),"") & IF(LEN(BRAIN!$F$44)>0,IF(ISNUMBER(SEARCH(BRAIN!$F$44,AK5)),BRAIN!$F$44&", ",""),"") & IF(LEN(BRAIN!$F$45)>0,IF(ISNUMBER(SEARCH(BRAIN!$F$45,AK5)),BRAIN!$F$45&", ",""),"") & IF(LEN(BRAIN!$F$46)>0,IF(ISNUMBER(SEARCH(BRAIN!$F$46,AK5)),BRAIN!$F$46&", ",""),"") & IF(LEN(BRAIN!$F$47)>0,IF(ISNUMBER(SEARCH(BRAIN!$F$47,AK5)),BRAIN!$F$47&", ",""),"") & IF(LEN(BRAIN!$F$48)>0,IF(ISNUMBER(SEARCH(BRAIN!$F$48,AK5)),BRAIN!$F$48&", ",""),"") & IF(LEN(BRAIN!$F$49)>0,IF(ISNUMBER(SEARCH(BRAIN!$F$49,AK5)),BRAIN!$F$49&", ",""),"") & IF(LEN(BRAIN!$F$50)>0,IF(ISNUMBER(SEARCH(BRAIN!$F$50,AK5)),BRAIN!$F$50&", ",""),"") & IF(LEN(BRAIN!$F$51)>0,IF(ISNUMBER(SEARCH(BRAIN!$F$51,AK5)),BRAIN!$F$51&", ",""),"") & IF(LEN(BRAIN!$F$52)>0,IF(ISNUMBER(SEARCH(BRAIN!$F$52,AK5)),BRAIN!$F$52&", ",""),"") & IF(LEN(BRAIN!$F$53)>0,IF(ISNUMBER(SEARCH(BRAIN!$F$53,AK5)),BRAIN!$F$53&", ",""),"") & IF(LEN(BRAIN!$F$54)>0,IF(ISNUMBER(SEARCH(BRAIN!$F$54,AK5)),BRAIN!$F$54&", ",""),"") & IF(LEN(BRAIN!$F$55)>0,IF(ISNUMBER(SEARCH(BRAIN!$F$55,AK5)),BRAIN!$F$55&", ",""),"") & IF(LEN(BRAIN!$F$56)>0,IF(ISNUMBER(SEARCH(BRAIN!$F$56,AK5)),BRAIN!$F$56&", ",""),"") & IF(LEN(BRAIN!$F$57)>0,IF(ISNUMBER(SEARCH(BRAIN!$F$57,AK5)),BRAIN!$F$57&", ",""),"")),2)=", ",LEFT((IF(LEN(BRAIN!$F$26)>0,IF(ISNUMBER(SEARCH(BRAIN!$F$26,AK5)),BRAIN!$F$26&", ",""),"") & IF(LEN(BRAIN!$F$27)>0,IF(ISNUMBER(SEARCH(BRAIN!$F$27,AK5)),BRAIN!$F$27&", ",""),"") & IF(LEN(BRAIN!$F$28)>0,IF(ISNUMBER(SEARCH(BRAIN!$F$28,AK5)),BRAIN!$F$28&", ",""),"") & IF(LEN(BRAIN!$F$29)>0,IF(ISNUMBER(SEARCH(BRAIN!$F$29,AK5)),BRAIN!$F$29&", ",""),"") & IF(LEN(BRAIN!$F$30)>0,IF(ISNUMBER(SEARCH(BRAIN!$F$30,AK5)),BRAIN!$F$30&", ",""),"") & IF(LEN(BRAIN!$F$31)>0,IF(ISNUMBER(SEARCH(BRAIN!$F$31,AK5)),BRAIN!$F$31&", ",""),"") & IF(LEN(BRAIN!$F$32)>0,IF(ISNUMBER(SEARCH(BRAIN!$F$32,AK5)),BRAIN!$F$32&", ",""),"") & IF(LEN(BRAIN!$F$33)>0,IF(ISNUMBER(SEARCH(BRAIN!$F$33,AK5)),BRAIN!$F$33&", ",""),"") & IF(LEN(BRAIN!$F$34)>0,IF(ISNUMBER(SEARCH(BRAIN!$F$34,AK5)),BRAIN!$F$34&", ",""),"") & IF(LEN(BRAIN!$F$35)>0,IF(ISNUMBER(SEARCH(BRAIN!$F$35,AK5)),BRAIN!$F$35&", ",""),"") & IF(LEN(BRAIN!$F$36)>0,IF(ISNUMBER(SEARCH(BRAIN!$F$36,AK5)),BRAIN!$F$36&", ",""),"") & IF(LEN(BRAIN!$F$37)>0,IF(ISNUMBER(SEARCH(BRAIN!$F$37,AK5)),BRAIN!$F$37&", ",""),"") & IF(LEN(BRAIN!$F$38)>0,IF(ISNUMBER(SEARCH(BRAIN!$F$38,AK5)),BRAIN!$F$38&", ",""),"") & IF(LEN(BRAIN!$F$39)>0,IF(ISNUMBER(SEARCH(BRAIN!$F$39,AK5)),BRAIN!$F$39&", ",""),"") & IF(LEN(BRAIN!$F$40)>0,IF(ISNUMBER(SEARCH(BRAIN!$F$40,AK5)),BRAIN!$F$40&", ",""),"") & IF(LEN(BRAIN!$F$41)>0,IF(ISNUMBER(SEARCH(BRAIN!$F$41,AK5)),BRAIN!$F$41&", ",""),"") & IF(LEN(BRAIN!$F$42)>0,IF(ISNUMBER(SEARCH(BRAIN!$F$42,AK5)),BRAIN!$F$42&", ",""),"") & IF(LEN(BRAIN!$F$43)>0,IF(ISNUMBER(SEARCH(BRAIN!$F$43,AK5)),BRAIN!$F$43&", ",""),"") & IF(LEN(BRAIN!$F$44)>0,IF(ISNUMBER(SEARCH(BRAIN!$F$44,AK5)),BRAIN!$F$44&", ",""),"") & IF(LEN(BRAIN!$F$45)>0,IF(ISNUMBER(SEARCH(BRAIN!$F$45,AK5)),BRAIN!$F$45&", ",""),"") & IF(LEN(BRAIN!$F$46)>0,IF(ISNUMBER(SEARCH(BRAIN!$F$46,AK5)),BRAIN!$F$46&", ",""),"") & IF(LEN(BRAIN!$F$47)>0,IF(ISNUMBER(SEARCH(BRAIN!$F$47,AK5)),BRAIN!$F$47&", ",""),"") & IF(LEN(BRAIN!$F$48)>0,IF(ISNUMBER(SEARCH(BRAIN!$F$48,AK5)),BRAIN!$F$48&", ",""),"") & IF(LEN(BRAIN!$F$49)>0,IF(ISNUMBER(SEARCH(BRAIN!$F$49,AK5)),BRAIN!$F$49&", ",""),"") & IF(LEN(BRAIN!$F$50)>0,IF(ISNUMBER(SEARCH(BRAIN!$F$50,AK5)),BRAIN!$F$50&", ",""),"") & IF(LEN(BRAIN!$F$51)>0,IF(ISNUMBER(SEARCH(BRAIN!$F$51,AK5)),BRAIN!$F$51&", ",""),"") & IF(LEN(BRAIN!$F$52)>0,IF(ISNUMBER(SEARCH(BRAIN!$F$52,AK5)),BRAIN!$F$52&", ",""),"") & IF(LEN(BRAIN!$F$53)>0,IF(ISNUMBER(SEARCH(BRAIN!$F$53,AK5)),BRAIN!$F$53&", ",""),"") & IF(LEN(BRAIN!$F$54)>0,IF(ISNUMBER(SEARCH(BRAIN!$F$54,AK5)),BRAIN!$F$54&", ",""),"") & IF(LEN(BRAIN!$F$55)>0,IF(ISNUMBER(SEARCH(BRAIN!$F$55,AK5)),BRAIN!$F$55&", ",""),"") & IF(LEN(BRAIN!$F$56)>0,IF(ISNUMBER(SEARCH(BRAIN!$F$56,AK5)),BRAIN!$F$56&", ",""),"") & IF(LEN(BRAIN!$F$57)>0,IF(ISNUMBER(SEARCH(BRAIN!$F$57,AK5)),BRAIN!$F$57&", ",""),"")),LEN((IF(LEN(BRAIN!$F$26)>0,IF(ISNUMBER(SEARCH(BRAIN!$F$26,AK5)),BRAIN!$F$26&", ",""),"") & IF(LEN(BRAIN!$F$27)>0,IF(ISNUMBER(SEARCH(BRAIN!$F$27,AK5)),BRAIN!$F$27&", ",""),"") & IF(LEN(BRAIN!$F$28)>0,IF(ISNUMBER(SEARCH(BRAIN!$F$28,AK5)),BRAIN!$F$28&", ",""),"") & IF(LEN(BRAIN!$F$29)>0,IF(ISNUMBER(SEARCH(BRAIN!$F$29,AK5)),BRAIN!$F$29&", ",""),"") & IF(LEN(BRAIN!$F$30)>0,IF(ISNUMBER(SEARCH(BRAIN!$F$30,AK5)),BRAIN!$F$30&", ",""),"") & IF(LEN(BRAIN!$F$31)>0,IF(ISNUMBER(SEARCH(BRAIN!$F$31,AK5)),BRAIN!$F$31&", ",""),"") & IF(LEN(BRAIN!$F$32)>0,IF(ISNUMBER(SEARCH(BRAIN!$F$32,AK5)),BRAIN!$F$32&", ",""),"") & IF(LEN(BRAIN!$F$33)>0,IF(ISNUMBER(SEARCH(BRAIN!$F$33,AK5)),BRAIN!$F$33&", ",""),"") & IF(LEN(BRAIN!$F$34)>0,IF(ISNUMBER(SEARCH(BRAIN!$F$34,AK5)),BRAIN!$F$34&", ",""),"") & IF(LEN(BRAIN!$F$35)>0,IF(ISNUMBER(SEARCH(BRAIN!$F$35,AK5)),BRAIN!$F$35&", ",""),"") & IF(LEN(BRAIN!$F$36)>0,IF(ISNUMBER(SEARCH(BRAIN!$F$36,AK5)),BRAIN!$F$36&", ",""),"") & IF(LEN(BRAIN!$F$37)>0,IF(ISNUMBER(SEARCH(BRAIN!$F$37,AK5)),BRAIN!$F$37&", ",""),"") & IF(LEN(BRAIN!$F$38)>0,IF(ISNUMBER(SEARCH(BRAIN!$F$38,AK5)),BRAIN!$F$38&", ",""),"") & IF(LEN(BRAIN!$F$39)>0,IF(ISNUMBER(SEARCH(BRAIN!$F$39,AK5)),BRAIN!$F$39&", ",""),"") & IF(LEN(BRAIN!$F$40)>0,IF(ISNUMBER(SEARCH(BRAIN!$F$40,AK5)),BRAIN!$F$40&", ",""),"") & IF(LEN(BRAIN!$F$41)>0,IF(ISNUMBER(SEARCH(BRAIN!$F$41,AK5)),BRAIN!$F$41&", ",""),"") & IF(LEN(BRAIN!$F$42)>0,IF(ISNUMBER(SEARCH(BRAIN!$F$42,AK5)),BRAIN!$F$42&", ",""),"") & IF(LEN(BRAIN!$F$43)>0,IF(ISNUMBER(SEARCH(BRAIN!$F$43,AK5)),BRAIN!$F$43&", ",""),"") & IF(LEN(BRAIN!$F$44)>0,IF(ISNUMBER(SEARCH(BRAIN!$F$44,AK5)),BRAIN!$F$44&", ",""),"") & IF(LEN(BRAIN!$F$45)>0,IF(ISNUMBER(SEARCH(BRAIN!$F$45,AK5)),BRAIN!$F$45&", ",""),"") & IF(LEN(BRAIN!$F$46)>0,IF(ISNUMBER(SEARCH(BRAIN!$F$46,AK5)),BRAIN!$F$46&", ",""),"") & IF(LEN(BRAIN!$F$47)>0,IF(ISNUMBER(SEARCH(BRAIN!$F$47,AK5)),BRAIN!$F$47&", ",""),"") & IF(LEN(BRAIN!$F$48)>0,IF(ISNUMBER(SEARCH(BRAIN!$F$48,AK5)),BRAIN!$F$48&", ",""),"") & IF(LEN(BRAIN!$F$49)>0,IF(ISNUMBER(SEARCH(BRAIN!$F$49,AK5)),BRAIN!$F$49&", ",""),"") & IF(LEN(BRAIN!$F$50)>0,IF(ISNUMBER(SEARCH(BRAIN!$F$50,AK5)),BRAIN!$F$50&", ",""),"") & IF(LEN(BRAIN!$F$51)>0,IF(ISNUMBER(SEARCH(BRAIN!$F$51,AK5)),BRAIN!$F$51&", ",""),"") & IF(LEN(BRAIN!$F$52)>0,IF(ISNUMBER(SEARCH(BRAIN!$F$52,AK5)),BRAIN!$F$52&", ",""),"") & IF(LEN(BRAIN!$F$53)>0,IF(ISNUMBER(SEARCH(BRAIN!$F$53,AK5)),BRAIN!$F$53&", ",""),"") & IF(LEN(BRAIN!$F$54)>0,IF(ISNUMBER(SEARCH(BRAIN!$F$54,AK5)),BRAIN!$F$54&", ",""),"") & IF(LEN(BRAIN!$F$55)>0,IF(ISNUMBER(SEARCH(BRAIN!$F$55,AK5)),BRAIN!$F$55&", ",""),"") & IF(LEN(BRAIN!$F$56)>0,IF(ISNUMBER(SEARCH(BRAIN!$F$56,AK5)),BRAIN!$F$56&", ",""),"") & IF(LEN(BRAIN!$F$57)>0,IF(ISNUMBER(SEARCH(BRAIN!$F$57,AK5)),BRAIN!$F$57&", ",""),"")))-2),(IF(LEN(BRAIN!$F$26)>0,IF(ISNUMBER(SEARCH(BRAIN!$F$26,AK5)),BRAIN!$F$26&", ",""),"") & IF(LEN(BRAIN!$F$27)>0,IF(ISNUMBER(SEARCH(BRAIN!$F$27,AK5)),BRAIN!$F$27&", ",""),"") & IF(LEN(BRAIN!$F$28)>0,IF(ISNUMBER(SEARCH(BRAIN!$F$28,AK5)),BRAIN!$F$28&", ",""),"") & IF(LEN(BRAIN!$F$29)>0,IF(ISNUMBER(SEARCH(BRAIN!$F$29,AK5)),BRAIN!$F$29&", ",""),"") & IF(LEN(BRAIN!$F$30)>0,IF(ISNUMBER(SEARCH(BRAIN!$F$30,AK5)),BRAIN!$F$30&", ",""),"") & IF(LEN(BRAIN!$F$31)>0,IF(ISNUMBER(SEARCH(BRAIN!$F$31,AK5)),BRAIN!$F$31&", ",""),"") & IF(LEN(BRAIN!$F$32)>0,IF(ISNUMBER(SEARCH(BRAIN!$F$32,AK5)),BRAIN!$F$32&", ",""),"") & IF(LEN(BRAIN!$F$33)>0,IF(ISNUMBER(SEARCH(BRAIN!$F$33,AK5)),BRAIN!$F$33&", ",""),"") & IF(LEN(BRAIN!$F$34)>0,IF(ISNUMBER(SEARCH(BRAIN!$F$34,AK5)),BRAIN!$F$34&", ",""),"") & IF(LEN(BRAIN!$F$35)>0,IF(ISNUMBER(SEARCH(BRAIN!$F$35,AK5)),BRAIN!$F$35&", ",""),"") & IF(LEN(BRAIN!$F$36)>0,IF(ISNUMBER(SEARCH(BRAIN!$F$36,AK5)),BRAIN!$F$36&", ",""),"") & IF(LEN(BRAIN!$F$37)>0,IF(ISNUMBER(SEARCH(BRAIN!$F$37,AK5)),BRAIN!$F$37&", ",""),"") & IF(LEN(BRAIN!$F$38)>0,IF(ISNUMBER(SEARCH(BRAIN!$F$38,AK5)),BRAIN!$F$38&", ",""),"") & IF(LEN(BRAIN!$F$39)>0,IF(ISNUMBER(SEARCH(BRAIN!$F$39,AK5)),BRAIN!$F$39&", ",""),"") & IF(LEN(BRAIN!$F$40)>0,IF(ISNUMBER(SEARCH(BRAIN!$F$40,AK5)),BRAIN!$F$40&", ",""),"") & IF(LEN(BRAIN!$F$41)>0,IF(ISNUMBER(SEARCH(BRAIN!$F$41,AK5)),BRAIN!$F$41&", ",""),"") & IF(LEN(BRAIN!$F$42)>0,IF(ISNUMBER(SEARCH(BRAIN!$F$42,AK5)),BRAIN!$F$42&", ",""),"") & IF(LEN(BRAIN!$F$43)>0,IF(ISNUMBER(SEARCH(BRAIN!$F$43,AK5)),BRAIN!$F$43&", ",""),"") & IF(LEN(BRAIN!$F$44)>0,IF(ISNUMBER(SEARCH(BRAIN!$F$44,AK5)),BRAIN!$F$44&", ",""),"") & IF(LEN(BRAIN!$F$45)>0,IF(ISNUMBER(SEARCH(BRAIN!$F$45,AK5)),BRAIN!$F$45&", ",""),"") & IF(LEN(BRAIN!$F$46)>0,IF(ISNUMBER(SEARCH(BRAIN!$F$46,AK5)),BRAIN!$F$46&", ",""),"") & IF(LEN(BRAIN!$F$47)>0,IF(ISNUMBER(SEARCH(BRAIN!$F$47,AK5)),BRAIN!$F$47&", ",""),"") & IF(LEN(BRAIN!$F$48)>0,IF(ISNUMBER(SEARCH(BRAIN!$F$48,AK5)),BRAIN!$F$48&", ",""),"") & IF(LEN(BRAIN!$F$49)>0,IF(ISNUMBER(SEARCH(BRAIN!$F$49,AK5)),BRAIN!$F$49&", ",""),"") & IF(LEN(BRAIN!$F$50)>0,IF(ISNUMBER(SEARCH(BRAIN!$F$50,AK5)),BRAIN!$F$50&", ",""),"") & IF(LEN(BRAIN!$F$51)>0,IF(ISNUMBER(SEARCH(BRAIN!$F$51,AK5)),BRAIN!$F$51&", ",""),"") & IF(LEN(BRAIN!$F$52)>0,IF(ISNUMBER(SEARCH(BRAIN!$F$52,AK5)),BRAIN!$F$52&", ",""),"") & IF(LEN(BRAIN!$F$53)>0,IF(ISNUMBER(SEARCH(BRAIN!$F$53,AK5)),BRAIN!$F$53&", ",""),"") & IF(LEN(BRAIN!$F$54)>0,IF(ISNUMBER(SEARCH(BRAIN!$F$54,AK5)),BRAIN!$F$54&", ",""),"") & IF(LEN(BRAIN!$F$55)>0,IF(ISNUMBER(SEARCH(BRAIN!$F$55,AK5)),BRAIN!$F$55&", ",""),"") & IF(LEN(BRAIN!$F$56)>0,IF(ISNUMBER(SEARCH(BRAIN!$F$56,AK5)),BRAIN!$F$56&", ",""),"") & IF(LEN(BRAIN!$F$57)>0,IF(ISNUMBER(SEARCH(BRAIN!$F$57,AK5)),BRAIN!$F$57&", ",""),""))),"") | AQ5: =IFERROR(IF(RIGHT((IF(LEN(BRAIN!$G$26)>0,IF(ISNUMBER(SEARCH(BRAIN!$G$26,AK5)),BRAIN!$G$26&", ",""),"") & IF(LEN(BRAIN!$G$27)>0,IF(ISNUMBER(SEARCH(BRAIN!$G$27,AK5)),BRAIN!$G$27&", ",""),"") & IF(LEN(BRAIN!$G$28)>0,IF(ISNUMBER(SEARCH(BRAIN!$G$28,AK5)),BRAIN!$G$28&", ",""),"") & IF(LEN(BRAIN!$G$29)>0,IF(ISNUMBER(SEARCH(BRAIN!$G$29,AK5)),BRAIN!$G$29&", ",""),"") & IF(LEN(BRAIN!$G$30)>0,IF(ISNUMBER(SEARCH(BRAIN!$G$30,AK5)),BRAIN!$G$30&", ",""),"") & IF(LEN(BRAIN!$G$31)>0,IF(ISNUMBER(SEARCH(BRAIN!$G$31,AK5)),BRAIN!$G$31&", ",""),"") & IF(LEN(BRAIN!$G$32)>0,IF(ISNUMBER(SEARCH(BRAIN!$G$32,AK5)),BRAIN!$G$32&", ",""),"") & IF(LEN(BRAIN!$G$33)>0,IF(ISNUMBER(SEARCH(BRAIN!$G$33,AK5)),BRAIN!$G$33&", ",""),"") & IF(LEN(BRAIN!$G$34)>0,IF(ISNUMBER(SEARCH(BRAIN!$G$34,AK5)),BRAIN!$G$34&", ",""),"") & IF(LEN(BRAIN!$G$35)>0,IF(ISNUMBER(SEARCH(BRAIN!$G$35,AK5)),BRAIN!$G$35&", ",""),"") & IF(LEN(BRAIN!$G$36)>0,IF(ISNUMBER(SEARCH(BRAIN!$G$36,AK5)),BRAIN!$G$36&", ",""),"") & IF(LEN(BRAIN!$G$37)>0,IF(ISNUMBER(SEARCH(BRAIN!$G$37,AK5)),BRAIN!$G$37&", ",""),"") & IF(LEN(BRAIN!$G$38)>0,IF(ISNUMBER(SEARCH(BRAIN!$G$38,AK5)),BRAIN!$G$38&", ",""),"") & IF(LEN(BRAIN!$G$39)>0,IF(ISNUMBER(SEARCH(BRAIN!$G$39,AK5)),BRAIN!$G$39&", ",""),"") & IF(LEN(BRAIN!$G$40)>0,IF(ISNUMBER(SEARCH(BRAIN!$G$40,AK5)),BRAIN!$G$40&", ",""),"") & IF(LEN(BRAIN!$G$41)>0,IF(ISNUMBER(SEARCH(BRAIN!$G$41,AK5)),BRAIN!$G$41&", ",""),"") & IF(LEN(BRAIN!$G$42)>0,IF(ISNUMBER(SEARCH(BRAIN!$G$42,AK5)),BRAIN!$G$42&", ",""),"") & IF(LEN(BRAIN!$G$43)>0,IF(ISNUMBER(SEARCH(BRAIN!$G$43,AK5)),BRAIN!$G$43&", ",""),"") & IF(LEN(BRAIN!$G$44)>0,IF(ISNUMBER(SEARCH(BRAIN!$G$44,AK5)),BRAIN!$G$44&", ",""),"") & IF(LEN(BRAIN!$G$45)>0,IF(ISNUMBER(SEARCH(BRAIN!$G$45,AK5)),BRAIN!$G$45&", ",""),"") & IF(LEN(BRAIN!$G$46)>0,IF(ISNUMBER(SEARCH(BRAIN!$G$46,AK5)),BRAIN!$G$46&", ",""),"") & IF(LEN(BRAIN!$G$47)>0,IF(ISNUMBER(SEARCH(BRAIN!$G$47,AK5)),BRAIN!$G$47&", ",""),"") & IF(LEN(BRAIN!$G$48)>0,IF(ISNUMBER(SEARCH(BRAIN!$G$48,AK5)),BRAIN!$G$48&", ",""),"") & IF(LEN(BRAIN!$G$49)>0,IF(ISNUMBER(SEARCH(BRAIN!$G$49,AK5)),BRAIN!$G$49&", ",""),"") & IF(LEN(BRAIN!$G$50)>0,IF(ISNUMBER(SEARCH(BRAIN!$G$50,AK5)),BRAIN!$G$50&", ",""),"") & IF(LEN(BRAIN!$G$51)>0,IF(ISNUMBER(SEARCH(BRAIN!$G$51,AK5)),BRAIN!$G$51&", ",""),"") & IF(LEN(BRAIN!$G$52)>0,IF(ISNUMBER(SEARCH(BRAIN!$G$52,AK5)),BRAIN!$G$52&", ",""),"") & IF(LEN(BRAIN!$G$53)>0,IF(ISNUMBER(SEARCH(BRAIN!$G$53,AK5)),BRAIN!$G$53&", ",""),"") & IF(LEN(BRAIN!$G$54)>0,IF(ISNUMBER(SEARCH(BRAIN!$G$54,AK5)),BRAIN!$G$54&", ",""),"") & IF(LEN(BRAIN!$G$55)>0,IF(ISNUMBER(SEARCH(BRAIN!$G$55,AK5)),BRAIN!$G$55&", ",""),"") & IF(LEN(BRAIN!$G$56)>0,IF(ISNUMBER(SEARCH(BRAIN!$G$56,AK5)),BRAIN!$G$56&", ",""),"") & IF(LEN(BRAIN!$G$57)>0,IF(ISNUMBER(SEARCH(BRAIN!$G$57,AK5)),BRAIN!$G$57&", ",""),"")),2)=", ",LEFT((IF(LEN(BRAIN!$G$26)>0,IF(ISNUMBER(SEARCH(BRAIN!$G$26,AK5)),BRAIN!$G$26&", ",""),"") & IF(LEN(BRAIN!$G$27)>0,IF(ISNUMBER(SEARCH(BRAIN!$G$27,AK5)),BRAIN!$G$27&", ",""),"") & IF(LEN(BRAIN!$G$28)>0,IF(ISNUMBER(SEARCH(BRAIN!$G$28,AK5)),BRAIN!$G$28&", ",""),"") & IF(LEN(BRAIN!$G$29)>0,IF(ISNUMBER(SEARCH(BRAIN!$G$29,AK5)),BRAIN!$G$29&", ",""),"") & IF(LEN(BRAIN!$G$30)>0,IF(ISNUMBER(SEARCH(BRAIN!$G$30,AK5)),BRAIN!$G$30&", ",""),"") & IF(LEN(BRAIN!$G$31)>0,IF(ISNUMBER(SEARCH(BRAIN!$G$31,AK5)),BRAIN!$G$31&", ",""),"") & IF(LEN(BRAIN!$G$32)>0,IF(ISNUMBER(SEARCH(BRAIN!$G$32,AK5)),BRAIN!$G$32&", ",""),"") & IF(LEN(BRAIN!$G$33)>0,IF(ISNUMBER(SEARCH(BRAIN!$G$33,AK5)),BRAIN!$G$33&", ",""),"") & IF(LEN(BRAIN!$G$34)>0,IF(ISNUMBER(SEARCH(BRAIN!$G$34,AK5)),BRAIN!$G$34&", ",""),"") & IF(LEN(BRAIN!$G$35)>0,IF(ISNUMBER(SEARCH(BRAIN!$G$35,AK5)),BRAIN!$G$35&", ",""),"") & IF(LEN(BRAIN!$G$36)>0,IF(ISNUMBER(SEARCH(BRAIN!$G$36,AK5)),BRAIN!$G$36&", ",""),"") & IF(LEN(BRAIN!$G$37)>0,IF(ISNUMBER(SEARCH(BRAIN!$G$37,AK5)),BRAIN!$G$37&", ",""),"") & IF(LEN(BRAIN!$G$38)>0,IF(ISNUMBER(SEARCH(BRAIN!$G$38,AK5)),BRAIN!$G$38&", ",""),"") & IF(LEN(BRAIN!$G$39)>0,IF(ISNUMBER(SEARCH(BRAIN!$G$39,AK5)),BRAIN!$G$39&", ",""),"") & IF(LEN(BRAIN!$G$40)>0,IF(ISNUMBER(SEARCH(BRAIN!$G$40,AK5)),BRAIN!$G$40&", ",""),"") & IF(LEN(BRAIN!$G$41)>0,IF(ISNUMBER(SEARCH(BRAIN!$G$41,AK5)),BRAIN!$G$41&", ",""),"") & IF(LEN(BRAIN!$G$42)>0,IF(ISNUMBER(SEARCH(BRAIN!$G$42,AK5)),BRAIN!$G$42&", ",""),"") & IF(LEN(BRAIN!$G$43)>0,IF(ISNUMBER(SEARCH(BRAIN!$G$43,AK5)),BRAIN!$G$43&", ",""),"") & IF(LEN(BRAIN!$G$44)>0,IF(ISNUMBER(SEARCH(BRAIN!$G$44,AK5)),BRAIN!$G$44&", ",""),"") & IF(LEN(BRAIN!$G$45)>0,IF(ISNUMBER(SEARCH(BRAIN!$G$45,AK5)),BRAIN!$G$45&", ",""),"") & IF(LEN(BRAIN!$G$46)>0,IF(ISNUMBER(SEARCH(BRAIN!$G$46,AK5)),BRAIN!$G$46&", ",""),"") & IF(LEN(BRAIN!$G$47)>0,IF(ISNUMBER(SEARCH(BRAIN!$G$47,AK5)),BRAIN!$G$47&", ",""),"") & IF(LEN(BRAIN!$G$48)>0,IF(ISNUMBER(SEARCH(BRAIN!$G$48,AK5)),BRAIN!$G$48&", ",""),"") & IF(LEN(BRAIN!$G$49)>0,IF(ISNUMBER(SEARCH(BRAIN!$G$49,AK5)),BRAIN!$G$49&", ",""),"") & IF(LEN(BRAIN!$G$50)>0,IF(ISNUMBER(SEARCH(BRAIN!$G$50,AK5)),BRAIN!$G$50&", ",""),"") & IF(LEN(BRAIN!$G$51)>0,IF(ISNUMBER(SEARCH(BRAIN!$G$51,AK5)),BRAIN!$G$51&", ",""),"") & IF(LEN(BRAIN!$G$52)>0,IF(ISNUMBER(SEARCH(BRAIN!$G$52,AK5)),BRAIN!$G$52&", ",""),"") & IF(LEN(BRAIN!$G$53)>0,IF(ISNUMBER(SEARCH(BRAIN!$G$53,AK5)),BRAIN!$G$53&", ",""),"") & IF(LEN(BRAIN!$G$54)>0,IF(ISNUMBER(SEARCH(BRAIN!$G$54,AK5)),BRAIN!$G$54&", ",""),"") & IF(LEN(BRAIN!$G$55)>0,IF(ISNUMBER(SEARCH(BRAIN!$G$55,AK5)),BRAIN!$G$55&", ",""),"") & IF(LEN(BRAIN!$G$56)>0,IF(ISNUMBER(SEARCH(BRAIN!$G$56,AK5)),BRAIN!$G$56&", ",""),"") & IF(LEN(BRAIN!$G$57)>0,IF(ISNUMBER(SEARCH(BRAIN!$G$57,AK5)),BRAIN!$G$57&", ",""),"")),LEN((IF(LEN(BRAIN!$G$26)>0,IF(ISNUMBER(SEARCH(BRAIN!$G$26,AK5)),BRAIN!$G$26&", ",""),"") & IF(LEN(BRAIN!$G$27)>0,IF(ISNUMBER(SEARCH(BRAIN!$G$27,AK5)),BRAIN!$G$27&", ",""),"") & IF(LEN(BRAIN!$G$28)>0,IF(ISNUMBER(SEARCH(BRAIN!$G$28,AK5)),BRAIN!$G$28&", ",""),"") & IF(LEN(BRAIN!$G$29)>0,IF(ISNUMBER(SEARCH(BRAIN!$G$29,AK5)),BRAIN!$G$29&", ",""),"") & IF(LEN(BRAIN!$G$30)>0,IF(ISNUMBER(SEARCH(BRAIN!$G$30,AK5)),BRAIN!$G$30&", ",""),"") & IF(LEN(BRAIN!$G$31)>0,IF(ISNUMBER(SEARCH(BRAIN!$G$31,AK5)),BRAIN!$G$31&", ",""),"") & IF(LEN(BRAIN!$G$32)>0,IF(ISNUMBER(SEARCH(BRAIN!$G$32,AK5)),BRAIN!$G$32&", ",""),"") & IF(LEN(BRAIN!$G$33)>0,IF(ISNUMBER(SEARCH(BRAIN!$G$33,AK5)),BRAIN!$G$33&", ",""),"") & IF(LEN(BRAIN!$G$34)>0,IF(ISNUMBER(SEARCH(BRAIN!$G$34,AK5)),BRAIN!$G$34&", ",""),"") & IF(LEN(BRAIN!$G$35)>0,IF(ISNUMBER(SEARCH(BRAIN!$G$35,AK5)),BRAIN!$G$35&", ",""),"") & IF(LEN(BRAIN!$G$36)>0,IF(ISNUMBER(SEARCH(BRAIN!$G$36,AK5)),BRAIN!$G$36&", ",""),"") & IF(LEN(BRAIN!$G$37)>0,IF(ISNUMBER(SEARCH(BRAIN!$G$37,AK5)),BRAIN!$G$37&", ",""),"") & IF(LEN(BRAIN!$G$38)>0,IF(ISNUMBER(SEARCH(BRAIN!$G$38,AK5)),BRAIN!$G$38&", ",""),"") & IF(LEN(BRAIN!$G$39)>0,IF(ISNUMBER(SEARCH(BRAIN!$G$39,AK5)),BRAIN!$G$39&", ",""),"") & IF(LEN(BRAIN!$G$40)>0,IF(ISNUMBER(SEARCH(BRAIN!$G$40,AK5)),BRAIN!$G$40&", ",""),"") & IF(LEN(BRAIN!$G$41)>0,IF(ISNUMBER(SEARCH(BRAIN!$G$41,AK5)),BRAIN!$G$41&", ",""),"") & IF(LEN(BRAIN!$G$42)>0,IF(ISNUMBER(SEARCH(BRAIN!$G$42,AK5)),BRAIN!$G$42&", ",""),"") & IF(LEN(BRAIN!$G$43)>0,IF(ISNUMBER(SEARCH(BRAIN!$G$43,AK5)),BRAIN!$G$43&", ",""),"") & IF(LEN(BRAIN!$G$44)>0,IF(ISNUMBER(SEARCH(BRAIN!$G$44,AK5)),BRAIN!$G$44&", ",""),"") & IF(LEN(BRAIN!$G$45)>0,IF(ISNUMBER(SEARCH(BRAIN!$G$45,AK5)),BRAIN!$G$45&", ",""),"") & IF(LEN(BRAIN!$G$46)>0,IF(ISNUMBER(SEARCH(BRAIN!$G$46,AK5)),BRAIN!$G$46&", ",""),"") & IF(LEN(BRAIN!$G$47)>0,IF(ISNUMBER(SEARCH(BRAIN!$G$47,AK5)),BRAIN!$G$47&", ",""),"") & IF(LEN(BRAIN!$G$48)>0,IF(ISNUMBER(SEARCH(BRAIN!$G$48,AK5)),BRAIN!$G$48&", ",""),"") & IF(LEN(BRAIN!$G$49)>0,IF(ISNUMBER(SEARCH(BRAIN!$G$49,AK5)),BRAIN!$G$49&", ",""),"") & IF(LEN(BRAIN!$G$50)>0,IF(ISNUMBER(SEARCH(BRAIN!$G$50,AK5)),BRAIN!$G$50&", ",""),"") & IF(LEN(BRAIN!$G$51)>0,IF(ISNUMBER(SEARCH(BRAIN!$G$51,AK5)),BRAIN!$G$51&", ",""),"") & IF(LEN(BRAIN!$G$52)>0,IF(ISNUMBER(SEARCH(BRAIN!$G$52,AK5)),BRAIN!$G$52&", ",""),"") & IF(LEN(BRAIN!$G$53)>0,IF(ISNUMBER(SEARCH(BRAIN!$G$53,AK5)),BRAIN!$G$53&", ",""),"") & IF(LEN(BRAIN!$G$54)>0,IF(ISNUMBER(SEARCH(BRAIN!$G$54,AK5)),BRAIN!$G$54&", ",""),"") & IF(LEN(BRAIN!$G$55)>0,IF(ISNUMBER(SEARCH(BRAIN!$G$55,AK5)),BRAIN!$G$55&", ",""),"") & IF(LEN(BRAIN!$G$56)>0,IF(ISNUMBER(SEARCH(BRAIN!$G$56,AK5)),BRAIN!$G$56&", ",""),"") & IF(LEN(BRAIN!$G$57)>0,IF(ISNUMBER(SEARCH(BRAIN!$G$57,AK5)),BRAIN!$G$57&", ",""),"")))-2),(IF(LEN(BRAIN!$G$26)>0,IF(ISNUMBER(SEARCH(BRAIN!$G$26,AK5)),BRAIN!$G$26&", ",""),"") & IF(LEN(BRAIN!$G$27)>0,IF(ISNUMBER(SEARCH(BRAIN!$G$27,AK5)),BRAIN!$G$27&", ",""),"") & IF(LEN(BRAIN!$G$28)>0,IF(ISNUMBER(SEARCH(BRAIN!$G$28,AK5)),BRAIN!$G$28&", ",""),"") & IF(LEN(BRAIN!$G$29)>0,IF(ISNUMBER(SEARCH(BRAIN!$G$29,AK5)),BRAIN!$G$29&", ",""),"") & IF(LEN(BRAIN!$G$30)>0,IF(ISNUMBER(SEARCH(BRAIN!$G$30,AK5)),BRAIN!$G$30&", ",""),"") & IF(LEN(BRAIN!$G$31)>0,IF(ISNUMBER(SEARCH(BRAIN!$G$31,AK5)),BRAIN!$G$31&", ",""),"") & IF(LEN(BRAIN!$G$32)>0,IF(ISNUMBER(SEARCH(BRAIN!$G$32,AK5)),BRAIN!$G$32&", ",""),"") & IF(LEN(BRAIN!$G$33)>0,IF(ISNUMBER(SEARCH(BRAIN!$G$33,AK5)),BRAIN!$G$33&", ",""),"") & IF(LEN(BRAIN!$G$34)>0,IF(ISNUMBER(SEARCH(BRAIN!$G$34,AK5)),BRAIN!$G$34&", ",""),"") & IF(LEN(BRAIN!$G$35)>0,IF(ISNUMBER(SEARCH(BRAIN!$G$35,AK5)),BRAIN!$G$35&", ",""),"") & IF(LEN(BRAIN!$G$36)>0,IF(ISNUMBER(SEARCH(BRAIN!$G$36,AK5)),BRAIN!$G$36&", ",""),"") & IF(LEN(BRAIN!$G$37)>0,IF(ISNUMBER(SEARCH(BRAIN!$G$37,AK5)),BRAIN!$G$37&", ",""),"") & IF(LEN(BRAIN!$G$38)>0,IF(ISNUMBER(SEARCH(BRAIN!$G$38,AK5)),BRAIN!$G$38&", ",""),"") & IF(LEN(BRAIN!$G$39)>0,IF(ISNUMBER(SEARCH(BRAIN!$G$39,AK5)),BRAIN!$G$39&", ",""),"") & IF(LEN(BRAIN!$G$40)>0,IF(ISNUMBER(SEARCH(BRAIN!$G$40,AK5)),BRAIN!$G$40&", ",""),"") & IF(LEN(BRAIN!$G$41)>0,IF(ISNUMBER(SEARCH(BRAIN!$G$41,AK5)),BRAIN!$G$41&", ",""),"") & IF(LEN(BRAIN!$G$42)>0,IF(ISNUMBER(SEARCH(BRAIN!$G$42,AK5)),BRAIN!$G$42&", ",""),"") & IF(LEN(BRAIN!$G$43)>0,IF(ISNUMBER(SEARCH(BRAIN!$G$43,AK5)),BRAIN!$G$43&", ",""),"") & IF(LEN(BRAIN!$G$44)>0,IF(ISNUMBER(SEARCH(BRAIN!$G$44,AK5)),BRAIN!$G$44&", ",""),"") & IF(LEN(BRAIN!$G$45)>0,IF(ISNUMBER(SEARCH(BRAIN!$G$45,AK5)),BRAIN!$G$45&", ",""),"") & IF(LEN(BRAIN!$G$46)>0,IF(ISNUMBER(SEARCH(BRAIN!$G$46,AK5)),BRAIN!$G$46&", ",""),"") & IF(LEN(BRAIN!$G$47)>0,IF(ISNUMBER(SEARCH(BRAIN!$G$47,AK5)),BRAIN!$G$47&", ",""),"") & IF(LEN(BRAIN!$G$48)>0,IF(ISNUMBER(SEARCH(BRAIN!$G$48,AK5)),BRAIN!$G$48&", ",""),"") & IF(LEN(BRAIN!$G$49)>0,IF(ISNUMBER(SEARCH(BRAIN!$G$49,AK5)),BRAIN!$G$49&", ",""),"") & IF(LEN(BRAIN!$G$50)>0,IF(ISNUMBER(SEARCH(BRAIN!$G$50,AK5)),BRAIN!$G$50&", ",""),"") & IF(LEN(BRAIN!$G$51)>0,IF(ISNUMBER(SEARCH(BRAIN!$G$51,AK5)),BRAIN!$G$51&", ",""),"") & IF(LEN(BRAIN!$G$52)>0,IF(ISNUMBER(SEARCH(BRAIN!$G$52,AK5)),BRAIN!$G$52&", ",""),"") & IF(LEN(BRAIN!$G$53)>0,IF(ISNUMBER(SEARCH(BRAIN!$G$53,AK5)),BRAIN!$G$53&", ",""),"") & IF(LEN(BRAIN!$G$54)>0,IF(ISNUMBER(SEARCH(BRAIN!$G$54,AK5)),BRAIN!$G$54&", ",""),"") & IF(LEN(BRAIN!$G$55)>0,IF(ISNUMBER(SEARCH(BRAIN!$G$55,AK5)),BRAIN!$G$55&", ",""),"") & IF(LEN(BRAIN!$G$56)>0,IF(ISNUMBER(SEARCH(BRAIN!$G$56,AK5)),BRAIN!$G$56&", ",""),"") & IF(LEN(BRAIN!$G$57)>0,IF(ISNUMBER(SEARCH(BRAIN!$G$57,AK5)),BRAIN!$G$57&", ",""),""))),"") -> chatbot, manual | AR5: =IFERROR(IF(RIGHT((IF(LEN(BRAIN!$H$26)>0,IF(ISNUMBER(SEARCH(BRAIN!$H$26,AK5)),BRAIN!$H$26&", ",""),"") & IF(LEN(BRAIN!$H$27)>0,IF(ISNUMBER(SEARCH(BRAIN!$H$27,AK5)),BRAIN!$H$27&", ",""),"") & IF(LEN(BRAIN!$H$28)>0,IF(ISNUMBER(SEARCH(BRAIN!$H$28,AK5)),BRAIN!$H$28&", ",""),"") & IF(LEN(BRAIN!$H$29)>0,IF(ISNUMBER(SEARCH(BRAIN!$H$29,AK5)),BRAIN!$H$29&", ",""),"") & IF(LEN(BRAIN!$H$30)>0,IF(ISNUMBER(SEARCH(BRAIN!$H$30,AK5)),BRAIN!$H$30&", ",""),"") & IF(LEN(BRAIN!$H$31)>0,IF(ISNUMBER(SEARCH(BRAIN!$H$31,AK5)),BRAIN!$H$31&", ",""),"") & IF(LEN(BRAIN!$H$32)>0,IF(ISNUMBER(SEARCH(BRAIN!$H$32,AK5)),BRAIN!$H$32&", ",""),"") & IF(LEN(BRAIN!$H$33)>0,IF(ISNUMBER(SEARCH(BRAIN!$H$33,AK5)),BRAIN!$H$33&", ",""),"") & IF(LEN(BRAIN!$H$34)>0,IF(ISNUMBER(SEARCH(BRAIN!$H$34,AK5)),BRAIN!$H$34&", ",""),"") & IF(LEN(BRAIN!$H$35)>0,IF(ISNUMBER(SEARCH(BRAIN!$H$35,AK5)),BRAIN!$H$35&", ",""),"") & IF(LEN(BRAIN!$H$36)>0,IF(ISNUMBER(SEARCH(BRAIN!$H$36,AK5)),BRAIN!$H$36&", ",""),"") & IF(LEN(BRAIN!$H$37)>0,IF(ISNUMBER(SEARCH(BRAIN!$H$37,AK5)),BRAIN!$H$37&", ",""),"") & IF(LEN(BRAIN!$H$38)>0,IF(ISNUMBER(SEARCH(BRAIN!$H$38,AK5)),BRAIN!$H$38&", ",""),"") & IF(LEN(BRAIN!$H$39)>0,IF(ISNUMBER(SEARCH(BRAIN!$H$39,AK5)),BRAIN!$H$39&", ",""),"") & IF(LEN(BRAIN!$H$40)>0,IF(ISNUMBER(SEARCH(BRAIN!$H$40,AK5)),BRAIN!$H$40&", ",""),"") & IF(LEN(BRAIN!$H$41)>0,IF(ISNUMBER(SEARCH(BRAIN!$H$41,AK5)),BRAIN!$H$41&", ",""),"") & IF(LEN(BRAIN!$H$42)>0,IF(ISNUMBER(SEARCH(BRAIN!$H$42,AK5)),BRAIN!$H$42&", ",""),"") & IF(LEN(BRAIN!$H$43)>0,IF(ISNUMBER(SEARCH(BRAIN!$H$43,AK5)),BRAIN!$H$43&", ",""),"") & IF(LEN(BRAIN!$H$44)>0,IF(ISNUMBER(SEARCH(BRAIN!$H$44,AK5)),BRAIN!$H$44&", ",""),"") & IF(LEN(BRAIN!$H$45)>0,IF(ISNUMBER(SEARCH(BRAIN!$H$45,AK5)),BRAIN!$H$45&", ",""),"") & IF(LEN(BRAIN!$H$46)>0,IF(ISNUMBER(SEARCH(BRAIN!$H$46,AK5)),BRAIN!$H$46&", ",""),"") & IF(LEN(BRAIN!$H$47)>0,IF(ISNUMBER(SEARCH(BRAIN!$H$47,AK5)),BRAIN!$H$47&", ",""),"") & IF(LEN(BRAIN!$H$48)>0,IF(ISNUMBER(SEARCH(BRAIN!$H$48,AK5)),BRAIN!$H$48&", ",""),"") & IF(LEN(BRAIN!$H$49)>0,IF(ISNUMBER(SEARCH(BRAIN!$H$49,AK5)),BRAIN!$H$49&", ",""),"") & IF(LEN(BRAIN!$H$50)>0,IF(ISNUMBER(SEARCH(BRAIN!$H$50,AK5)),BRAIN!$H$50&", ",""),"") & IF(LEN(BRAIN!$H$51)>0,IF(ISNUMBER(SEARCH(BRAIN!$H$51,AK5)),BRAIN!$H$51&", ",""),"") & IF(LEN(BRAIN!$H$52)>0,IF(ISNUMBER(SEARCH(BRAIN!$H$52,AK5)),BRAIN!$H$52&", ",""),"") & IF(LEN(BRAIN!$H$53)>0,IF(ISNUMBER(SEARCH(BRAIN!$H$53,AK5)),BRAIN!$H$53&", ",""),"") & IF(LEN(BRAIN!$H$54)>0,IF(ISNUMBER(SEARCH(BRAIN!$H$54,AK5)),BRAIN!$H$54&", ",""),"") & IF(LEN(BRAIN!$H$55)>0,IF(ISNUMBER(SEARCH(BRAIN!$H$55,AK5)),BRAIN!$H$55&", ",""),"") & IF(LEN(BRAIN!$H$56)>0,IF(ISNUMBER(SEARCH(BRAIN!$H$56,AK5)),BRAIN!$H$56&", ",""),"") & IF(LEN(BRAIN!$H$57)>0,IF(ISNUMBER(SEARCH(BRAIN!$H$57,AK5)),BRAIN!$H$57&", ",""),"")),2)=", ",LEFT((IF(LEN(BRAIN!$H$26)>0,IF(ISNUMBER(SEARCH(BRAIN!$H$26,AK5)),BRAIN!$H$26&", ",""),"") & IF(LEN(BRAIN!$H$27)>0,IF(ISNUMBER(SEARCH(BRAIN!$H$27,AK5)),BRAIN!$H$27&", ",""),"") & IF(LEN(BRAIN!$H$28)>0,IF(ISNUMBER(SEARCH(BRAIN!$H$28,AK5)),BRAIN!$H$28&", ",""),"") & IF(LEN(BRAIN!$H$29)>0,IF(ISNUMBER(SEARCH(BRAIN!$H$29,AK5)),BRAIN!$H$29&", ",""),"") & IF(LEN(BRAIN!$H$30)>0,IF(ISNUMBER(SEARCH(BRAIN!$H$30,AK5)),BRAIN!$H$30&", ",""),"") & IF(LEN(BRAIN!$H$31)>0,IF(ISNUMBER(SEARCH(BRAIN!$H$31,AK5)),BRAIN!$H$31&", ",""),"") & IF(LEN(BRAIN!$H$32)>0,IF(ISNUMBER(SEARCH(BRAIN!$H$32,AK5)),BRAIN!$H$32&", ",""),"") & IF(LEN(BRAIN!$H$33)>0,IF(ISNUMBER(SEARCH(BRAIN!$H$33,AK5)),BRAIN!$H$33&", ",""),"") & IF(LEN(BRAIN!$H$34)>0,IF(ISNUMBER(SEARCH(BRAIN!$H$34,AK5)),BRAIN!$H$34&", ",""),"") & IF(LEN(BRAIN!$H$35)>0,IF(ISNUMBER(SEARCH(BRAIN!$H$35,AK5)),BRAIN!$H$35&", ",""),"") & IF(LEN(BRAIN!$H$36)>0,IF(ISNUMBER(SEARCH(BRAIN!$H$36,AK5)),BRAIN!$H$36&", ",""),"") & IF(LEN(BRAIN!$H$37)>0,IF(ISNUMBER(SEARCH(BRAIN!$H$37,AK5)),BRAIN!$H$37&", ",""),"") & IF(LEN(BRAIN!$H$38)>0,IF(ISNUMBER(SEARCH(BRAIN!$H$38,AK5)),BRAIN!$H$38&", ",""),"") & IF(LEN(BRAIN!$H$39)>0,IF(ISNUMBER(SEARCH(BRAIN!$H$39,AK5)),BRAIN!$H$39&", ",""),"") & IF(LEN(BRAIN!$H$40)>0,IF(ISNUMBER(SEARCH(BRAIN!$H$40,AK5)),BRAIN!$H$40&", ",""),"") & IF(LEN(BRAIN!$H$41)>0,IF(ISNUMBER(SEARCH(BRAIN!$H$41,AK5)),BRAIN!$H$41&", ",""),"") & IF(LEN(BRAIN!$H$42)>0,IF(ISNUMBER(SEARCH(BRAIN!$H$42,AK5)),BRAIN!$H$42&", ",""),"") & IF(LEN(BRAIN!$H$43)>0,IF(ISNUMBER(SEARCH(BRAIN!$H$43,AK5)),BRAIN!$H$43&", ",""),"") & IF(LEN(BRAIN!$H$44)>0,IF(ISNUMBER(SEARCH(BRAIN!$H$44,AK5)),BRAIN!$H$44&", ",""),"") & IF(LEN(BRAIN!$H$45)>0,IF(ISNUMBER(SEARCH(BRAIN!$H$45,AK5)),BRAIN!$H$45&", ",""),"") & IF(LEN(BRAIN!$H$46)>0,IF(ISNUMBER(SEARCH(BRAIN!$H$46,AK5)),BRAIN!$H$46&", ",""),"") & IF(LEN(BRAIN!$H$47)>0,IF(ISNUMBER(SEARCH(BRAIN!$H$47,AK5)),BRAIN!$H$47&", ",""),"") & IF(LEN(BRAIN!$H$48)>0,IF(ISNUMBER(SEARCH(BRAIN!$H$48,AK5)),BRAIN!$H$48&", ",""),"") & IF(LEN(BRAIN!$H$49)>0,IF(ISNUMBER(SEARCH(BRAIN!$H$49,AK5)),BRAIN!$H$49&", ",""),"") & IF(LEN(BRAIN!$H$50)>0,IF(ISNUMBER(SEARCH(BRAIN!$H$50,AK5)),BRAIN!$H$50&", ",""),"") & IF(LEN(BRAIN!$H$51)>0,IF(ISNUMBER(SEARCH(BRAIN!$H$51,AK5)),BRAIN!$H$51&", ",""),"") & IF(LEN(BRAIN!$H$52)>0,IF(ISNUMBER(SEARCH(BRAIN!$H$52,AK5)),BRAIN!$H$52&", ",""),"") & IF(LEN(BRAIN!$H$53)>0,IF(ISNUMBER(SEARCH(BRAIN!$H$53,AK5)),BRAIN!$H$53&", ",""),"") & IF(LEN(BRAIN!$H$54)>0,IF(ISNUMBER(SEARCH(BRAIN!$H$54,AK5)),BRAIN!$H$54&", ",""),"") & IF(LEN(BRAIN!$H$55)>0,IF(ISNUMBER(SEARCH(BRAIN!$H$55,AK5)),BRAIN!$H$55&", ",""),"") & IF(LEN(BRAIN!$H$56)>0,IF(ISNUMBER(SEARCH(BRAIN!$H$56,AK5)),BRAIN!$H$56&", ",""),"") & IF(LEN(BRAIN!$H$57)>0,IF(ISNUMBER(SEARCH(BRAIN!$H$57,AK5)),BRAIN!$H$57&", ",""),"")),LEN((IF(LEN(BRAIN!$H$26)>0,IF(ISNUMBER(SEARCH(BRAIN!$H$26,AK5)),BRAIN!$H$26&", ",""),"") & IF(LEN(BRAIN!$H$27)>0,IF(ISNUMBER(SEARCH(BRAIN!$H$27,AK5)),BRAIN!$H$27&", ",""),"") & IF(LEN(BRAIN!$H$28)>0,IF(ISNUMBER(SEARCH(BRAIN!$H$28,AK5)),BRAIN!$H$28&", ",""),"") & IF(LEN(BRAIN!$H$29)>0,IF(ISNUMBER(SEARCH(BRAIN!$H$29,AK5)),BRAIN!$H$29&", ",""),"") & IF(LEN(BRAIN!$H$30)>0,IF(ISNUMBER(SEARCH(BRAIN!$H$30,AK5)),BRAIN!$H$30&", ",""),"") & IF(LEN(BRAIN!$H$31)>0,IF(ISNUMBER(SEARCH(BRAIN!$H$31,AK5)),BRAIN!$H$31&", ",""),"") & IF(LEN(BRAIN!$H$32)>0,IF(ISNUMBER(SEARCH(BRAIN!$H$32,AK5)),BRAIN!$H$32&", ",""),"") & IF(LEN(BRAIN!$H$33)>0,IF(ISNUMBER(SEARCH(BRAIN!$H$33,AK5)),BRAIN!$H$33&", ",""),"") & IF(LEN(BRAIN!$H$34)>0,IF(ISNUMBER(SEARCH(BRAIN!$H$34,AK5)),BRAIN!$H$34&", ",""),"") & IF(LEN(BRAIN!$H$35)>0,IF(ISNUMBER(SEARCH(BRAIN!$H$35,AK5)),BRAIN!$H$35&", ",""),"") & IF(LEN(BRAIN!$H$36)>0,IF(ISNUMBER(SEARCH(BRAIN!$H$36,AK5)),BRAIN!$H$36&", ",""),"") & IF(LEN(BRAIN!$H$37)>0,IF(ISNUMBER(SEARCH(BRAIN!$H$37,AK5)),BRAIN!$H$37&", ",""),"") & IF(LEN(BRAIN!$H$38)>0,IF(ISNUMBER(SEARCH(BRAIN!$H$38,AK5)),BRAIN!$H$38&", ",""),"") & IF(LEN(BRAIN!$H$39)>0,IF(ISNUMBER(SEARCH(BRAIN!$H$39,AK5)),BRAIN!$H$39&", ",""),"") & IF(LEN(BRAIN!$H$40)>0,IF(ISNUMBER(SEARCH(BRAIN!$H$40,AK5)),BRAIN!$H$40&", ",""),"") & IF(LEN(BRAIN!$H$41)>0,IF(ISNUMBER(SEARCH(BRAIN!$H$41,AK5)),BRAIN!$H$41&", ",""),"") & IF(LEN(BRAIN!$H$42)>0,IF(ISNUMBER(SEARCH(BRAIN!$H$42,AK5)),BRAIN!$H$42&", ",""),"") & IF(LEN(BRAIN!$H$43)>0,IF(ISNUMBER(SEARCH(BRAIN!$H$43,AK5)),BRAIN!$H$43&", ",""),"") & IF(LEN(BRAIN!$H$44)>0,IF(ISNUMBER(SEARCH(BRAIN!$H$44,AK5)),BRAIN!$H$44&", ",""),"") & IF(LEN(BRAIN!$H$45)>0,IF(ISNUMBER(SEARCH(BRAIN!$H$45,AK5)),BRAIN!$H$45&", ",""),"") & IF(LEN(BRAIN!$H$46)>0,IF(ISNUMBER(SEARCH(BRAIN!$H$46,AK5)),BRAIN!$H$46&", ",""),"") & IF(LEN(BRAIN!$H$47)>0,IF(ISNUMBER(SEARCH(BRAIN!$H$47,AK5)),BRAIN!$H$47&", ",""),"") & IF(LEN(BRAIN!$H$48)>0,IF(ISNUMBER(SEARCH(BRAIN!$H$48,AK5)),BRAIN!$H$48&", ",""),"") & IF(LEN(BRAIN!$H$49)>0,IF(ISNUMBER(SEARCH(BRAIN!$H$49,AK5)),BRAIN!$H$49&", ",""),"") & IF(LEN(BRAIN!$H$50)>0,IF(ISNUMBER(SEARCH(BRAIN!$H$50,AK5)),BRAIN!$H$50&", ",""),"") & IF(LEN(BRAIN!$H$51)>0,IF(ISNUMBER(SEARCH(BRAIN!$H$51,AK5)),BRAIN!$H$51&", ",""),"") & IF(LEN(BRAIN!$H$52)>0,IF(ISNUMBER(SEARCH(BRAIN!$H$52,AK5)),BRAIN!$H$52&", ",""),"") & IF(LEN(BRAIN!$H$53)>0,IF(ISNUMBER(SEARCH(BRAIN!$H$53,AK5)),BRAIN!$H$53&", ",""),"") & IF(LEN(BRAIN!$H$54)>0,IF(ISNUMBER(SEARCH(BRAIN!$H$54,AK5)),BRAIN!$H$54&", ",""),"") & IF(LEN(BRAIN!$H$55)>0,IF(ISNUMBER(SEARCH(BRAIN!$H$55,AK5)),BRAIN!$H$55&", ",""),"") & IF(LEN(BRAIN!$H$56)>0,IF(ISNUMBER(SEARCH(BRAIN!$H$56,AK5)),BRAIN!$H$56&", ",""),"") & IF(LEN(BRAIN!$H$57)>0,IF(ISNUMBER(SEARCH(BRAIN!$H$57,AK5)),BRAIN!$H$57&", ",""),"")))-2),(IF(LEN(BRAIN!$H$26)>0,IF(ISNUMBER(SEARCH(BRAIN!$H$26,AK5)),BRAIN!$H$26&", ",""),"") & IF(LEN(BRAIN!$H$27)>0,IF(ISNUMBER(SEARCH(BRAIN!$H$27,AK5)),BRAIN!$H$27&", ",""),"") & IF(LEN(BRAIN!$H$28)>0,IF(ISNUMBER(SEARCH(BRAIN!$H$28,AK5)),BRAIN!$H$28&", ",""),"") & IF(LEN(BRAIN!$H$29)>0,IF(ISNUMBER(SEARCH(BRAIN!$H$29,AK5)),BRAIN!$H$29&", ",""),"") & IF(LEN(BRAIN!$H$30)>0,IF(ISNUMBER(SEARCH(BRAIN!$H$30,AK5)),BRAIN!$H$30&", ",""),"") & IF(LEN(BRAIN!$H$31)>0,IF(ISNUMBER(SEARCH(BRAIN!$H$31,AK5)),BRAIN!$H$31&", ",""),"") & IF(LEN(BRAIN!$H$32)>0,IF(ISNUMBER(SEARCH(BRAIN!$H$32,AK5)),BRAIN!$H$32&", ",""),"") & IF(LEN(BRAIN!$H$33)>0,IF(ISNUMBER(SEARCH(BRAIN!$H$33,AK5)),BRAIN!$H$33&", ",""),"") & IF(LEN(BRAIN!$H$34)>0,IF(ISNUMBER(SEARCH(BRAIN!$H$34,AK5)),BRAIN!$H$34&", ",""),"") & IF(LEN(BRAIN!$H$35)>0,IF(ISNUMBER(SEARCH(BRAIN!$H$35,AK5)),BRAIN!$H$35&", ",""),"") & IF(LEN(BRAIN!$H$36)>0,IF(ISNUMBER(SEARCH(BRAIN!$H$36,AK5)),BRAIN!$H$36&", ",""),"") & IF(LEN(BRAIN!$H$37)>0,IF(ISNUMBER(SEARCH(BRAIN!$H$37,AK5)),BRAIN!$H$37&", ",""),"") & IF(LEN(BRAIN!$H$38)>0,IF(ISNUMBER(SEARCH(BRAIN!$H$38,AK5)),BRAIN!$H$38&", ",""),"") & IF(LEN(BRAIN!$H$39)>0,IF(ISNUMBER(SEARCH(BRAIN!$H$39,AK5)),BRAIN!$H$39&", ",""),"") & IF(LEN(BRAIN!$H$40)>0,IF(ISNUMBER(SEARCH(BRAIN!$H$40,AK5)),BRAIN!$H$40&", ",""),"") & IF(LEN(BRAIN!$H$41)>0,IF(ISNUMBER(SEARCH(BRAIN!$H$41,AK5)),BRAIN!$H$41&", ",""),"") & IF(LEN(BRAIN!$H$42)>0,IF(ISNUMBER(SEARCH(BRAIN!$H$42,AK5)),BRAIN!$H$42&", ",""),"") & IF(LEN(BRAIN!$H$43)>0,IF(ISNUMBER(SEARCH(BRAIN!$H$43,AK5)),BRAIN!$H$43&", ",""),"") & IF(LEN(BRAIN!$H$44)>0,IF(ISNUMBER(SEARCH(BRAIN!$H$44,AK5)),BRAIN!$H$44&", ",""),"") & IF(LEN(BRAIN!$H$45)>0,IF(ISNUMBER(SEARCH(BRAIN!$H$45,AK5)),BRAIN!$H$45&", ",""),"") & IF(LEN(BRAIN!$H$46)>0,IF(ISNUMBER(SEARCH(BRAIN!$H$46,AK5)),BRAIN!$H$46&", ",""),"") & IF(LEN(BRAIN!$H$47)>0,IF(ISNUMBER(SEARCH(BRAIN!$H$47,AK5)),BRAIN!$H$47&", ",""),"") & IF(LEN(BRAIN!$H$48)>0,IF(ISNUMBER(SEARCH(BRAIN!$H$48,AK5)),BRAIN!$H$48&", ",""),"") & IF(LEN(BRAIN!$H$49)>0,IF(ISNUMBER(SEARCH(BRAIN!$H$49,AK5)),BRAIN!$H$49&", ",""),"") & IF(LEN(BRAIN!$H$50)>0,IF(ISNUMBER(SEARCH(BRAIN!$H$50,AK5)),BRAIN!$H$50&", ",""),"") & IF(LEN(BRAIN!$H$51)>0,IF(ISNUMBER(SEARCH(BRAIN!$H$51,AK5)),BRAIN!$H$51&", ",""),"") & IF(LEN(BRAIN!$H$52)>0,IF(ISNUMBER(SEARCH(BRAIN!$H$52,AK5)),BRAIN!$H$52&", ",""),"") & IF(LEN(BRAIN!$H$53)>0,IF(ISNUMBER(SEARCH(BRAIN!$H$53,AK5)),BRAIN!$H$53&", ",""),"") & IF(LEN(BRAIN!$H$54)>0,IF(ISNUMBER(SEARCH(BRAIN!$H$54,AK5)),BRAIN!$H$54&", ",""),"") & IF(LEN(BRAIN!$H$55)>0,IF(ISNUMBER(SEARCH(BRAIN!$H$55,AK5)),BRAIN!$H$55&", ",""),"") & IF(LEN(BRAIN!$H$56)>0,IF(ISNUMBER(SEARCH(BRAIN!$H$56,AK5)),BRAIN!$H$56&", ",""),"") & IF(LEN(BRAIN!$H$57)>0,IF(ISNUMBER(SEARCH(BRAIN!$H$57,AK5)),BRAIN!$H$57&", ",""),""))),"")
A6: REQ-002 | B6: 46153 | C6: U Win Aung | D6: win.aung@city.com | E6: Customs / Logistics | F6: Yangon clearance | G6: Logistics & Distribution | H6: Digitize handwritten customs declarations | I6: Brokers hand us scanned + handwritten declaration forms in Burmese and English. Re-typing into the system takes 30 minutes per shipment and clerks misread HS codes. | J6: Manual data entry of each handwritten form, photocopy filed, errors caught at audit. | K6: OCR + extract HS code, duty, invoice price from each handwritten PDF, side-by-side review UI, approve to push into ERP. | L6: Scanned / handwritten | M6: Customs / shipping docs | N6: Daily | O6: 100-1k | P6: Critical | Q6: L — 2-3 months | R6: 320000 | S6: Head of Customs, COO | T6: Customs audit trail | U6: 46188 | V6: =IF(SUM(AE6:AJ6)=0,"",INDEX(AL$5:AL$10,MATCH(MAX(AE6:AJ6),AE6:AJ6,0))) -> RO-ED-Lang — Customs PDF Extractor | W6: =IF(SUM(AE6:AJ6)=0,"",ROUND(MAX(AE6:AJ6)/SUM(AE6:AJ6)*100,0)/100) -> 0.78 | X6: =IF(SUM(AE6:AJ6)=0,"",IFERROR(INDEX(AM6:AR6,MATCH(MAX(AE6:AJ6),AE6:AJ6,0)),"—")) -> customs, declaration, duty, hs code, handwritten, shipment, invoice, ocr, broker | Y6: =IF(COUNTIF(AE6:AJ6,">0")<2,"",INDEX(AL$5:AL$10,MATCH(LARGE(AE6:AJ6,2),AE6:AJ6,0))) -> CHL Scout — Agentic RAG / Doc Q&A | Z6: Approved | AE6: =IF(LEN(AK6)=0,0,2*SUMPRODUCT((LEN(KW_PULSE)>0)*--ISNUMBER(SEARCH(KW_PULSE,AK6))) + 1*IFERROR(INDEX(Affinity_PULSE,MATCH(E6,AffinityFunctions,0)),0)) -> 0 | AF6: =IF(LEN(AK6)=0,0,2*SUMPRODUCT((LEN(KW_RTM)>0)*--ISNUMBER(SEARCH(KW_RTM,AK6))) + 1*IFERROR(INDEX(Affinity_RTM,MATCH(E6,AffinityFunctions,0)),0)) -> 0 | AG6: =IF(LEN(AK6)=0,0,2*SUMPRODUCT((LEN(KW_ROED)>0)*--ISNUMBER(SEARCH(KW_ROED,AK6))) + 1*IFERROR(INDEX(Affinity_ROED,MATCH(E6,AffinityFunctions,0)),0)) -> 21 | AH6: =IF(LEN(AK6)=0,0,2*SUMPRODUCT((LEN(KW_KONTACT)>0)*--ISNUMBER(SEARCH(KW_KONTACT,AK6))) + 1*IFERROR(INDEX(Affinity_KONTACT,MATCH(E6,AffinityFunctions,0)),0)) -> 0 | AI6: =IF(LEN(AK6)=0,0,2*SUMPRODUCT((LEN(KW_SCOUT)>0)*--ISNUMBER(SEARCH(KW_SCOUT,AK6))) + 1*IFERROR(INDEX(Affinity_SCOUT,MATCH(E6,AffinityFunctions,0)),0)) -> 5 | AJ6: =IF(LEN(AK6)=0,0,2*SUMPRODUCT((LEN(KW_DASH)>0)*--ISNUMBER(SEARCH(KW_DASH,AK6))) + 1*IFERROR(INDEX(Affinity_DASH,MATCH(E6,AffinityFunctions,0)),0)) -> 1 | AK6: =LOWER(IFERROR(_xlfn.TEXTJOIN(" ",1,H6,I6,J6,K6,L6,M6),"")) -> digitize handwritten customs declarations brokers hand us scanned + handwritten declaration forms in burmese and english. re-typing into the system takes 30 minutes per shipment and clerks misread hs codes. manual data entry of each handwritten form, photocopy filed, errors caught at audit. ocr + extract hs code, duty, invoice price from each handwritten pdf, side-by-side review ui, approve to push into erp. scanned / handwritten customs / shipping docs | AL6: PG-MCP-RTM — Route-to-Market Classifier | AM6: =IFERROR(IF(RIGHT((IF(LEN(BRAIN!$C$26)>0,IF(ISNUMBER(SEARCH(BRAIN!$C$26,AK6)),BRAIN!$C$26&", ",""),"") & IF(LEN(BRAIN!$C$27)>0,IF(ISNUMBER(SEARCH(BRAIN!$C$27,AK6)),BRAIN!$C$27&", ",""),"") & IF(LEN(BRAIN!$C$28)>0,IF(ISNUMBER(SEARCH(BRAIN!$C$28,AK6)),BRAIN!$C$28&", ",""),"") & IF(LEN(BRAIN!$C$29)>0,IF(ISNUMBER(SEARCH(BRAIN!$C$29,AK6)),BRAIN!$C$29&", ",""),"") & IF(LEN(BRAIN!$C$30)>0,IF(ISNUMBER(SEARCH(BRAIN!$C$30,AK6)),BRAIN!$C$30&", ",""),"") & IF(LEN(BRAIN!$C$31)>0,IF(ISNUMBER(SEARCH(BRAIN!$C$31,AK6)),BRAIN!$C$31&", ",""),"") & IF(LEN(BRAIN!$C$32)>0,IF(ISNUMBER(SEARCH(BRAIN!$C$32,AK6)),BRAIN!$C$32&", ",""),"") & IF(LEN(BRAIN!$C$33)>0,IF(ISNUMBER(SEARCH(BRAIN!$C$33,AK6)),BRAIN!$C$33&", ",""),"") & IF(LEN(BRAIN!$C$34)>0,IF(ISNUMBER(SEARCH(BRAIN!$C$34,AK6)),BRAIN!$C$34&", ",""),"") & IF(LEN(BRAIN!$C$35)>0,IF(ISNUMBER(SEARCH(BRAIN!$C$35,AK6)),BRAIN!$C$35&", ",""),"") & IF(LEN(BRAIN!$C$36)>0,IF(ISNUMBER(SEARCH(BRAIN!$C$36,AK6)),BRAIN!$C$36&", ",""),"") & IF(LEN(BRAIN!$C$37)>0,IF(ISNUMBER(SEARCH(BRAIN!$C$37,AK6)),BRAIN!$C$37&", ",""),"") & IF(LEN(BRAIN!$C$38)>0,IF(ISNUMBER(SEARCH(BRAIN!$C$38,AK6)),BRAIN!$C$38&", ",""),"") & IF(LEN(BRAIN!$C$39)>0,IF(ISNUMBER(SEARCH(BRAIN!$C$39,AK6)),BRAIN!$C$39&", ",""),"") & IF(LEN(BRAIN!$C$40)>0,IF(ISNUMBER(SEARCH(BRAIN!$C$40,AK6)),BRAIN!$C$40&", ",""),"") & IF(LEN(BRAIN!$C$41)>0,IF(ISNUMBER(SEARCH(BRAIN!$C$41,AK6)),BRAIN!$C$41&", ",""),"") & IF(LEN(BRAIN!$C$42)>0,IF(ISNUMBER(SEARCH(BRAIN!$C$42,AK6)),BRAIN!$C$42&", ",""),"") & IF(LEN(BRAIN!$C$43)>0,IF(ISNUMBER(SEARCH(BRAIN!$C$43,AK6)),BRAIN!$C$43&", ",""),"") & IF(LEN(BRAIN!$C$44)>0,IF(ISNUMBER(SEARCH(BRAIN!$C$44,AK6)),BRAIN!$C$44&", ",""),"") & IF(LEN(BRAIN!$C$45)>0,IF(ISNUMBER(SEARCH(BRAIN!$C$45,AK6)),BRAIN!$C$45&", ",""),"") & IF(LEN(BRAIN!$C$46)>0,IF(ISNUMBER(SEARCH(BRAIN!$C$46,AK6)),BRAIN!$C$46&", ",""),"") & IF(LEN(BRAIN!$C$47)>0,IF(ISNUMBER(SEARCH(BRAIN!$C$47,AK6)),BRAIN!$C$47&", ",""),"") & IF(LEN(BRAIN!$C$48)>0,IF(ISNUMBER(SEARCH(BRAIN!$C$48,AK6)),BRAIN!$C$48&", ",""),"") & IF(LEN(BRAIN!$C$49)>0,IF(ISNUMBER(SEARCH(BRAIN!$C$49,AK6)),BRAIN!$C$49&", ",""),"") & IF(LEN(BRAIN!$C$50)>0,IF(ISNUMBER(SEARCH(BRAIN!$C$50,AK6)),BRAIN!$C$50&", ",""),"") & IF(LEN(BRAIN!$C$51)>0,IF(ISNUMBER(SEARCH(BRAIN!$C$51,AK6)),BRAIN!$C$51&", ",""),"") & IF(LEN(BRAIN!$C$52)>0,IF(ISNUMBER(SEARCH(BRAIN!$C$52,AK6)),BRAIN!$C$52&", ",""),"") & IF(LEN(BRAIN!$C$53)>0,IF(ISNUMBER(SEARCH(BRAIN!$C$53,AK6)),BRAIN!$C$53&", ",""),"") & IF(LEN(BRAIN!$C$54)>0,IF(ISNUMBER(SEARCH(BRAIN!$C$54,AK6)),BRAIN!$C$54&", ",""),"") & IF(LEN(BRAIN!$C$55)>0,IF(ISNUMBER(SEARCH(BRAIN!$C$55,AK6)),BRAIN!$C$55&", ",""),"") & IF(LEN(BRAIN!$C$56)>0,IF(ISNUMBER(SEARCH(BRAIN!$C$56,AK6)),BRAIN!$C$56&", ",""),"") & IF(LEN(BRAIN!$C$57)>0,IF(ISNUMBER(SEARCH(BRAIN!$C$57,AK6)),BRAIN!$C$57&", ",""),"")),2)=", ",LEFT((IF(LEN(BRAIN!$C$26)>0,IF(ISNUMBER(SEARCH(BRAIN!$C$26,AK6)),BRAIN!$C$26&", ",""),"") & IF(LEN(BRAIN!$C$27)>0,IF(ISNUMBER(SEARCH(BRAIN!$C$27,AK6)),BRAIN!$C$27&", ",""),"") & IF(LEN(BRAIN!$C$28)>0,IF(ISNUMBER(SEARCH(BRAIN!$C$28,AK6)),BRAIN!$C$28&", ",""),"") & IF(LEN(BRAIN!$C$29)>0,IF(ISNUMBER(SEARCH(BRAIN!$C$29,AK6)),BRAIN!$C$29&", ",""),"") & IF(LEN(BRAIN!$C$30)>0,IF(ISNUMBER(SEARCH(BRAIN!$C$30,AK6)),BRAIN!$C$30&", ",""),"") & IF(LEN(BRAIN!$C$31)>0,IF(ISNUMBER(SEARCH(BRAIN!$C$31,AK6)),BRAIN!$C$31&", ",""),"") & IF(LEN(BRAIN!$C$32)>0,IF(ISNUMBER(SEARCH(BRAIN!$C$32,AK6)),BRAIN!$C$32&", ",""),"") & IF(LEN(BRAIN!$C$33)>0,IF(ISNUMBER(SEARCH(BRAIN!$C$33,AK6)),BRAIN!$C$33&", ",""),"") & IF(LEN(BRAIN!$C$34)>0,IF(ISNUMBER(SEARCH(BRAIN!$C$34,AK6)),BRAIN!$C$34&", ",""),"") & IF(LEN(BRAIN!$C$35)>0,IF(ISNUMBER(SEARCH(BRAIN!$C$35,AK6)),BRAIN!$C$35&", ",""),"") & IF(LEN(BRAIN!$C$36)>0,IF(ISNUMBER(SEARCH(BRAIN!$C$36,AK6)),BRAIN!$C$36&", ",""),"") & IF(LEN(BRAIN!$C$37)>0,IF(ISNUMBER(SEARCH(BRAIN!$C$37,AK6)),BRAIN!$C$37&", ",""),"") & IF(LEN(BRAIN!$C$38)>0,IF(ISNUMBER(SEARCH(BRAIN!$C$38,AK6)),BRAIN!$C$38&", ",""),"") & IF(LEN(BRAIN!$C$39)>0,IF(ISNUMBER(SEARCH(BRAIN!$C$39,AK6)),BRAIN!$C$39&", ",""),"") & IF(LEN(BRAIN!$C$40)>0,IF(ISNUMBER(SEARCH(BRAIN!$C$40,AK6)),BRAIN!$C$40&", ",""),"") & IF(LEN(BRAIN!$C$41)>0,IF(ISNUMBER(SEARCH(BRAIN!$C$41,AK6)),BRAIN!$C$41&", ",""),"") & IF(LEN(BRAIN!$C$42)>0,IF(ISNUMBER(SEARCH(BRAIN!$C$42,AK6)),BRAIN!$C$42&", ",""),"") & IF(LEN(BRAIN!$C$43)>0,IF(ISNUMBER(SEARCH(BRAIN!$C$43,AK6)),BRAIN!$C$43&", ",""),"") & IF(LEN(BRAIN!$C$44)>0,IF(ISNUMBER(SEARCH(BRAIN!$C$44,AK6)),BRAIN!$C$44&", ",""),"") & IF(LEN(BRAIN!$C$45)>0,IF(ISNUMBER(SEARCH(BRAIN!$C$45,AK6)),BRAIN!$C$45&", ",""),"") & IF(LEN(BRAIN!$C$46)>0,IF(ISNUMBER(SEARCH(BRAIN!$C$46,AK6)),BRAIN!$C$46&", ",""),"") & IF(LEN(BRAIN!$C$47)>0,IF(ISNUMBER(SEARCH(BRAIN!$C$47,AK6)),BRAIN!$C$47&", ",""),"") & IF(LEN(BRAIN!$C$48)>0,IF(ISNUMBER(SEARCH(BRAIN!$C$48,AK6)),BRAIN!$C$48&", ",""),"") & IF(LEN(BRAIN!$C$49)>0,IF(ISNUMBER(SEARCH(BRAIN!$C$49,AK6)),BRAIN!$C$49&", ",""),"") & IF(LEN(BRAIN!$C$50)>0,IF(ISNUMBER(SEARCH(BRAIN!$C$50,AK6)),BRAIN!$C$50&", ",""),"") & IF(LEN(BRAIN!$C$51)>0,IF(ISNUMBER(SEARCH(BRAIN!$C$51,AK6)),BRAIN!$C$51&", ",""),"") & IF(LEN(BRAIN!$C$52)>0,IF(ISNUMBER(SEARCH(BRAIN!$C$52,AK6)),BRAIN!$C$52&", ",""),"") & IF(LEN(BRAIN!$C$53)>0,IF(ISNUMBER(SEARCH(BRAIN!$C$53,AK6)),BRAIN!$C$53&", ",""),"") & IF(LEN(BRAIN!$C$54)>0,IF(ISNUMBER(SEARCH(BRAIN!$C$54,AK6)),BRAIN!$C$54&", ",""),"") & IF(LEN(BRAIN!$C$55)>0,IF(ISNUMBER(SEARCH(BRAIN!$C$55,AK6)),BRAIN!$C$55&", ",""),"") & IF(LEN(BRAIN!$C$56)>0,IF(ISNUMBER(SEARCH(BRAIN!$C$56,AK6)),BRAIN!$C$56&", ",""),"") & IF(LEN(BRAIN!$C$57)>0,IF(ISNUMBER(SEARCH(BRAIN!$C$57,AK6)),BRAIN!$C$57&", ",""),"")),LEN((IF(LEN(BRAIN!$C$26)>0,IF(ISNUMBER(SEARCH(BRAIN!$C$26,AK6)),BRAIN!$C$26&", ",""),"") & IF(LEN(BRAIN!$C$27)>0,IF(ISNUMBER(SEARCH(BRAIN!$C$27,AK6)),BRAIN!$C$27&", ",""),"") & IF(LEN(BRAIN!$C$28)>0,IF(ISNUMBER(SEARCH(BRAIN!$C$28,AK6)),BRAIN!$C$28&", ",""),"") & IF(LEN(BRAIN!$C$29)>0,IF(ISNUMBER(SEARCH(BRAIN!$C$29,AK6)),BRAIN!$C$29&", ",""),"") & IF(LEN(BRAIN!$C$30)>0,IF(ISNUMBER(SEARCH(BRAIN!$C$30,AK6)),BRAIN!$C$30&", ",""),"") & IF(LEN(BRAIN!$C$31)>0,IF(ISNUMBER(SEARCH(BRAIN!$C$31,AK6)),BRAIN!$C$31&", ",""),"") & IF(LEN(BRAIN!$C$32)>0,IF(ISNUMBER(SEARCH(BRAIN!$C$32,AK6)),BRAIN!$C$32&", ",""),"") & IF(LEN(BRAIN!$C$33)>0,IF(ISNUMBER(SEARCH(BRAIN!$C$33,AK6)),BRAIN!$C$33&", ",""),"") & IF(LEN(BRAIN!$C$34)>0,IF(ISNUMBER(SEARCH(BRAIN!$C$34,AK6)),BRAIN!$C$34&", ",""),"") & IF(LEN(BRAIN!$C$35)>0,IF(ISNUMBER(SEARCH(BRAIN!$C$35,AK6)),BRAIN!$C$35&", ",""),"") & IF(LEN(BRAIN!$C$36)>0,IF(ISNUMBER(SEARCH(BRAIN!$C$36,AK6)),BRAIN!$C$36&", ",""),"") & IF(LEN(BRAIN!$C$37)>0,IF(ISNUMBER(SEARCH(BRAIN!$C$37,AK6)),BRAIN!$C$37&", ",""),"") & IF(LEN(BRAIN!$C$38)>0,IF(ISNUMBER(SEARCH(BRAIN!$C$38,AK6)),BRAIN!$C$38&", ",""),"") & IF(LEN(BRAIN!$C$39)>0,IF(ISNUMBER(SEARCH(BRAIN!$C$39,AK6)),BRAIN!$C$39&", ",""),"") & IF(LEN(BRAIN!$C$40)>0,IF(ISNUMBER(SEARCH(BRAIN!$C$40,AK6)),BRAIN!$C$40&", ",""),"") & IF(LEN(BRAIN!$C$41)>0,IF(ISNUMBER(SEARCH(BRAIN!$C$41,AK6)),BRAIN!$C$41&", ",""),"") & IF(LEN(BRAIN!$C$42)>0,IF(ISNUMBER(SEARCH(BRAIN!$C$42,AK6)),BRAIN!$C$42&", ",""),"") & IF(LEN(BRAIN!$C$43)>0,IF(ISNUMBER(SEARCH(BRAIN!$C$43,AK6)),BRAIN!$C$43&", ",""),"") & IF(LEN(BRAIN!$C$44)>0,IF(ISNUMBER(SEARCH(BRAIN!$C$44,AK6)),BRAIN!$C$44&", ",""),"") & IF(LEN(BRAIN!$C$45)>0,IF(ISNUMBER(SEARCH(BRAIN!$C$45,AK6)),BRAIN!$C$45&", ",""),"") & IF(LEN(BRAIN!$C$46)>0,IF(ISNUMBER(SEARCH(BRAIN!$C$46,AK6)),BRAIN!$C$46&", ",""),"") & IF(LEN(BRAIN!$C$47)>0,IF(ISNUMBER(SEARCH(BRAIN!$C$47,AK6)),BRAIN!$C$47&", ",""),"") & IF(LEN(BRAIN!$C$48)>0,IF(ISNUMBER(SEARCH(BRAIN!$C$48,AK6)),BRAIN!$C$48&", ",""),"") & IF(LEN(BRAIN!$C$49)>0,IF(ISNUMBER(SEARCH(BRAIN!$C$49,AK6)),BRAIN!$C$49&", ",""),"") & IF(LEN(BRAIN!$C$50)>0,IF(ISNUMBER(SEARCH(BRAIN!$C$50,AK6)),BRAIN!$C$50&", ",""),"") & IF(LEN(BRAIN!$C$51)>0,IF(ISNUMBER(SEARCH(BRAIN!$C$51,AK6)),BRAIN!$C$51&", ",""),"") & IF(LEN(BRAIN!$C$52)>0,IF(ISNUMBER(SEARCH(BRAIN!$C$52,AK6)),BRAIN!$C$52&", ",""),"") & IF(LEN(BRAIN!$C$53)>0,IF(ISNUMBER(SEARCH(BRAIN!$C$53,AK6)),BRAIN!$C$53&", ",""),"") & IF(LEN(BRAIN!$C$54)>0,IF(ISNUMBER(SEARCH(BRAIN!$C$54,AK6)),BRAIN!$C$54&", ",""),"") & IF(LEN(BRAIN!$C$55)>0,IF(ISNUMBER(SEARCH(BRAIN!$C$55,AK6)),BRAIN!$C$55&", ",""),"") & IF(LEN(BRAIN!$C$56)>0,IF(ISNUMBER(SEARCH(BRAIN!$C$56,AK6)),BRAIN!$C$56&", ",""),"") & IF(LEN(BRAIN!$C$57)>0,IF(ISNUMBER(SEARCH(BRAIN!$C$57,AK6)),BRAIN!$C$57&", ",""),"")))-2),(IF(LEN(BRAIN!$C$26)>0,IF(ISNUMBER(SEARCH(BRAIN!$C$26,AK6)),BRAIN!$C$26&", ",""),"") & IF(LEN(BRAIN!$C$27)>0,IF(ISNUMBER(SEARCH(BRAIN!$C$27,AK6)),BRAIN!$C$27&", ",""),"") & IF(LEN(BRAIN!$C$28)>0,IF(ISNUMBER(SEARCH(BRAIN!$C$28,AK6)),BRAIN!$C$28&", ",""),"") & IF(LEN(BRAIN!$C$29)>0,IF(ISNUMBER(SEARCH(BRAIN!$C$29,AK6)),BRAIN!$C$29&", ",""),"") & IF(LEN(BRAIN!$C$30)>0,IF(ISNUMBER(SEARCH(BRAIN!$C$30,AK6)),BRAIN!$C$30&", ",""),"") & IF(LEN(BRAIN!$C$31)>0,IF(ISNUMBER(SEARCH(BRAIN!$C$31,AK6)),BRAIN!$C$31&", ",""),"") & IF(LEN(BRAIN!$C$32)>0,IF(ISNUMBER(SEARCH(BRAIN!$C$32,AK6)),BRAIN!$C$32&", ",""),"") & IF(LEN(BRAIN!$C$33)>0,IF(ISNUMBER(SEARCH(BRAIN!$C$33,AK6)),BRAIN!$C$33&", ",""),"") & IF(LEN(BRAIN!$C$34)>0,IF(ISNUMBER(SEARCH(BRAIN!$C$34,AK6)),BRAIN!$C$34&", ",""),"") & IF(LEN(BRAIN!$C$35)>0,IF(ISNUMBER(SEARCH(BRAIN!$C$35,AK6)),BRAIN!$C$35&", ",""),"") & IF(LEN(BRAIN!$C$36)>0,IF(ISNUMBER(SEARCH(BRAIN!$C$36,AK6)),BRAIN!$C$36&", ",""),"") & IF(LEN(BRAIN!$C$37)>0,IF(ISNUMBER(SEARCH(BRAIN!$C$37,AK6)),BRAIN!$C$37&", ",""),"") & IF(LEN(BRAIN!$C$38)>0,IF(ISNUMBER(SEARCH(BRAIN!$C$38,AK6)),BRAIN!$C$38&", ",""),"") & IF(LEN(BRAIN!$C$39)>0,IF(ISNUMBER(SEARCH(BRAIN!$C$39,AK6)),BRAIN!$C$39&", ",""),"") & IF(LEN(BRAIN!$C$40)>0,IF(ISNUMBER(SEARCH(BRAIN!$C$40,AK6)),BRAIN!$C$40&", ",""),"") & IF(LEN(BRAIN!$C$41)>0,IF(ISNUMBER(SEARCH(BRAIN!$C$41,AK6)),BRAIN!$C$41&", ",""),"") & IF(LEN(BRAIN!$C$42)>0,IF(ISNUMBER(SEARCH(BRAIN!$C$42,AK6)),BRAIN!$C$42&", ",""),"") & IF(LEN(BRAIN!$C$43)>0,IF(ISNUMBER(SEARCH(BRAIN!$C$43,AK6)),BRAIN!$C$43&", ",""),"") & IF(LEN(BRAIN!$C$44)>0,IF(ISNUMBER(SEARCH(BRAIN!$C$44,AK6)),BRAIN!$C$44&", ",""),"") & IF(LEN(BRAIN!$C$45)>0,IF(ISNUMBER(SEARCH(BRAIN!$C$45,AK6)),BRAIN!$C$45&", ",""),"") & IF(LEN(BRAIN!$C$46)>0,IF(ISNUMBER(SEARCH(BRAIN!$C$46,AK6)),BRAIN!$C$46&", ",""),"") & IF(LEN(BRAIN!$C$47)>0,IF(ISNUMBER(SEARCH(BRAIN!$C$47,AK6)),BRAIN!$C$47&", ",""),"") & IF(LEN(BRAIN!$C$48)>0,IF(ISNUMBER(SEARCH(BRAIN!$C$48,AK6)),BRAIN!$C$48&", ",""),"") & IF(LEN(BRAIN!$C$49)>0,IF(ISNUMBER(SEARCH(BRAIN!$C$49,AK6)),BRAIN!$C$49&", ",""),"") & IF(LEN(BRAIN!$C$50)>0,IF(ISNUMBER(SEARCH(BRAIN!$C$50,AK6)),BRAIN!$C$50&", ",""),"") & IF(LEN(BRAIN!$C$51)>0,IF(ISNUMBER(SEARCH(BRAIN!$C$51,AK6)),BRAIN!$C$51&", ",""),"") & IF(LEN(BRAIN!$C$52)>0,IF(ISNUMBER(SEARCH(BRAIN!$C$52,AK6)),BRAIN!$C$52&", ",""),"") & IF(LEN(BRAIN!$C$53)>0,IF(ISNUMBER(SEARCH(BRAIN!$C$53,AK6)),BRAIN!$C$53&", ",""),"") & IF(LEN(BRAIN!$C$54)>0,IF(ISNUMBER(SEARCH(BRAIN!$C$54,AK6)),BRAIN!$C$54&", ",""),"") & IF(LEN(BRAIN!$C$55)>0,IF(ISNUMBER(SEARCH(BRAIN!$C$55,AK6)),BRAIN!$C$55&", ",""),"") & IF(LEN(BRAIN!$C$56)>0,IF(ISNUMBER(SEARCH(BRAIN!$C$56,AK6)),BRAIN!$C$56&", ",""),"") & IF(LEN(BRAIN!$C$57)>0,IF(ISNUMBER(SEARCH(BRAIN!$C$57,AK6)),BRAIN!$C$57&", ",""),""))),"") | AN6: =IFERROR(IF(RIGHT((IF(LEN(BRAIN!$D$26)>0,IF(ISNUMBER(SEARCH(BRAIN!$D$26,AK6)),BRAIN!$D$26&", ",""),"") & IF(LEN(BRAIN!$D$27)>0,IF(ISNUMBER(SEARCH(BRAIN!$D$27,AK6)),BRAIN!$D$27&", ",""),"") & IF(LEN(BRAIN!$D$28)>0,IF(ISNUMBER(SEARCH(BRAIN!$D$28,AK6)),BRAIN!$D$28&", ",""),"") & IF(LEN(BRAIN!$D$29)>0,IF(ISNUMBER(SEARCH(BRAIN!$D$29,AK6)),BRAIN!$D$29&", ",""),"") & IF(LEN(BRAIN!$D$30)>0,IF(ISNUMBER(SEARCH(BRAIN!$D$30,AK6)),BRAIN!$D$30&", ",""),"") & IF(LEN(BRAIN!$D$31)>0,IF(ISNUMBER(SEARCH(BRAIN!$D$31,AK6)),BRAIN!$D$31&", ",""),"") & IF(LEN(BRAIN!$D$32)>0,IF(ISNUMBER(SEARCH(BRAIN!$D$32,AK6)),BRAIN!$D$32&", ",""),"") & IF(LEN(BRAIN!$D$33)>0,IF(ISNUMBER(SEARCH(BRAIN!$D$33,AK6)),BRAIN!$D$33&", ",""),"") & IF(LEN(BRAIN!$D$34)>0,IF(ISNUMBER(SEARCH(BRAIN!$D$34,AK6)),BRAIN!$D$34&", ",""),"") & IF(LEN(BRAIN!$D$35)>0,IF(ISNUMBER(SEARCH(BRAIN!$D$35,AK6)),BRAIN!$D$35&", ",""),"") & IF(LEN(BRAIN!$D$36)>0,IF(ISNUMBER(SEARCH(BRAIN!$D$36,AK6)),BRAIN!$D$36&", ",""),"") & IF(LEN(BRAIN!$D$37)>0,IF(ISNUMBER(SEARCH(BRAIN!$D$37,AK6)),BRAIN!$D$37&", ",""),"") & IF(LEN(BRAIN!$D$38)>0,IF(ISNUMBER(SEARCH(BRAIN!$D$38,AK6)),BRAIN!$D$38&", ",""),"") & IF(LEN(BRAIN!$D$39)>0,IF(ISNUMBER(SEARCH(BRAIN!$D$39,AK6)),BRAIN!$D$39&", ",""),"") & IF(LEN(BRAIN!$D$40)>0,IF(ISNUMBER(SEARCH(BRAIN!$D$40,AK6)),BRAIN!$D$40&", ",""),"") & IF(LEN(BRAIN!$D$41)>0,IF(ISNUMBER(SEARCH(BRAIN!$D$41,AK6)),BRAIN!$D$41&", ",""),"") & IF(LEN(BRAIN!$D$42)>0,IF(ISNUMBER(SEARCH(BRAIN!$D$42,AK6)),BRAIN!$D$42&", ",""),"") & IF(LEN(BRAIN!$D$43)>0,IF(ISNUMBER(SEARCH(BRAIN!$D$43,AK6)),BRAIN!$D$43&", ",""),"") & IF(LEN(BRAIN!$D$44)>0,IF(ISNUMBER(SEARCH(BRAIN!$D$44,AK6)),BRAIN!$D$44&", ",""),"") & IF(LEN(BRAIN!$D$45)>0,IF(ISNUMBER(SEARCH(BRAIN!$D$45,AK6)),BRAIN!$D$45&", ",""),"") & IF(LEN(BRAIN!$D$46)>0,IF(ISNUMBER(SEARCH(BRAIN!$D$46,AK6)),BRAIN!$D$46&", ",""),"") & IF(LEN(BRAIN!$D$47)>0,IF(ISNUMBER(SEARCH(BRAIN!$D$47,AK6)),BRAIN!$D$47&", ",""),"") & IF(LEN(BRAIN!$D$48)>0,IF(ISNUMBER(SEARCH(BRAIN!$D$48,AK6)),BRAIN!$D$48&", ",""),"") & IF(LEN(BRAIN!$D$49)>0,IF(ISNUMBER(SEARCH(BRAIN!$D$49,AK6)),BRAIN!$D$49&", ",""),"") & IF(LEN(BRAIN!$D$50)>0,IF(ISNUMBER(SEARCH(BRAIN!$D$50,AK6)),BRAIN!$D$50&", ",""),"") & IF(LEN(BRAIN!$D$51)>0,IF(ISNUMBER(SEARCH(BRAIN!$D$51,AK6)),BRAIN!$D$51&", ",""),"") & IF(LEN(BRAIN!$D$52)>0,IF(ISNUMBER(SEARCH(BRAIN!$D$52,AK6)),BRAIN!$D$52&", ",""),"") & IF(LEN(BRAIN!$D$53)>0,IF(ISNUMBER(SEARCH(BRAIN!$D$53,AK6)),BRAIN!$D$53&", ",""),"") & IF(LEN(BRAIN!$D$54)>0,IF(ISNUMBER(SEARCH(BRAIN!$D$54,AK6)),BRAIN!$D$54&", ",""),"") & IF(LEN(BRAIN!$D$55)>0,IF(ISNUMBER(SEARCH(BRAIN!$D$55,AK6)),BRAIN!$D$55&", ",""),"") & IF(LEN(BRAIN!$D$56)>0,IF(ISNUMBER(SEARCH(BRAIN!$D$56,AK6)),BRAIN!$D$56&", ",""),"") & IF(LEN(BRAIN!$D$57)>0,IF(ISNUMBER(SEARCH(BRAIN!$D$57,AK6)),BRAIN!$D$57&", ",""),"")),2)=", ",LEFT((IF(LEN(BRAIN!$D$26)>0,IF(ISNUMBER(SEARCH(BRAIN!$D$26,AK6)),BRAIN!$D$26&", ",""),"") & IF(LEN(BRAIN!$D$27)>0,IF(ISNUMBER(SEARCH(BRAIN!$D$27,AK6)),BRAIN!$D$27&", ",""),"") & IF(LEN(BRAIN!$D$28)>0,IF(ISNUMBER(SEARCH(BRAIN!$D$28,AK6)),BRAIN!$D$28&", ",""),"") & IF(LEN(BRAIN!$D$29)>0,IF(ISNUMBER(SEARCH(BRAIN!$D$29,AK6)),BRAIN!$D$29&", ",""),"") & IF(LEN(BRAIN!$D$30)>0,IF(ISNUMBER(SEARCH(BRAIN!$D$30,AK6)),BRAIN!$D$30&", ",""),"") & IF(LEN(BRAIN!$D$31)>0,IF(ISNUMBER(SEARCH(BRAIN!$D$31,AK6)),BRAIN!$D$31&", ",""),"") & IF(LEN(BRAIN!$D$32)>0,IF(ISNUMBER(SEARCH(BRAIN!$D$32,AK6)),BRAIN!$D$32&", ",""),"") & IF(LEN(BRAIN!$D$33)>0,IF(ISNUMBER(SEARCH(BRAIN!$D$33,AK6)),BRAIN!$D$33&", ",""),"") & IF(LEN(BRAIN!$D$34)>0,IF(ISNUMBER(SEARCH(BRAIN!$D$34,AK6)),BRAIN!$D$34&", ",""),"") & IF(LEN(BRAIN!$D$35)>0,IF(ISNUMBER(SEARCH(BRAIN!$D$35,AK6)),BRAIN!$D$35&", ",""),"") & IF(LEN(BRAIN!$D$36)>0,IF(ISNUMBER(SEARCH(BRAIN!$D$36,AK6)),BRAIN!$D$36&", ",""),"") & IF(LEN(BRAIN!$D$37)>0,IF(ISNUMBER(SEARCH(BRAIN!$D$37,AK6)),BRAIN!$D$37&", ",""),"") & IF(LEN(BRAIN!$D$38)>0,IF(ISNUMBER(SEARCH(BRAIN!$D$38,AK6)),BRAIN!$D$38&", ",""),"") & IF(LEN(BRAIN!$D$39)>0,IF(ISNUMBER(SEARCH(BRAIN!$D$39,AK6)),BRAIN!$D$39&", ",""),"") & IF(LEN(BRAIN!$D$40)>0,IF(ISNUMBER(SEARCH(BRAIN!$D$40,AK6)),BRAIN!$D$40&", ",""),"") & IF(LEN(BRAIN!$D$41)>0,IF(ISNUMBER(SEARCH(BRAIN!$D$41,AK6)),BRAIN!$D$41&", ",""),"") & IF(LEN(BRAIN!$D$42)>0,IF(ISNUMBER(SEARCH(BRAIN!$D$42,AK6)),BRAIN!$D$42&", ",""),"") & IF(LEN(BRAIN!$D$43)>0,IF(ISNUMBER(SEARCH(BRAIN!$D$43,AK6)),BRAIN!$D$43&", ",""),"") & IF(LEN(BRAIN!$D$44)>0,IF(ISNUMBER(SEARCH(BRAIN!$D$44,AK6)),BRAIN!$D$44&", ",""),"") & IF(LEN(BRAIN!$D$45)>0,IF(ISNUMBER(SEARCH(BRAIN!$D$45,AK6)),BRAIN!$D$45&", ",""),"") & IF(LEN(BRAIN!$D$46)>0,IF(ISNUMBER(SEARCH(BRAIN!$D$46,AK6)),BRAIN!$D$46&", ",""),"") & IF(LEN(BRAIN!$D$47)>0,IF(ISNUMBER(SEARCH(BRAIN!$D$47,AK6)),BRAIN!$D$47&", ",""),"") & IF(LEN(BRAIN!$D$48)>0,IF(ISNUMBER(SEARCH(BRAIN!$D$48,AK6)),BRAIN!$D$48&", ",""),"") & IF(LEN(BRAIN!$D$49)>0,IF(ISNUMBER(SEARCH(BRAIN!$D$49,AK6)),BRAIN!$D$49&", ",""),"") & IF(LEN(BRAIN!$D$50)>0,IF(ISNUMBER(SEARCH(BRAIN!$D$50,AK6)),BRAIN!$D$50&", ",""),"") & IF(LEN(BRAIN!$D$51)>0,IF(ISNUMBER(SEARCH(BRAIN!$D$51,AK6)),BRAIN!$D$51&", ",""),"") & IF(LEN(BRAIN!$D$52)>0,IF(ISNUMBER(SEARCH(BRAIN!$D$52,AK6)),BRAIN!$D$52&", ",""),"") & IF(LEN(BRAIN!$D$53)>0,IF(ISNUMBER(SEARCH(BRAIN!$D$53,AK6)),BRAIN!$D$53&", ",""),"") & IF(LEN(BRAIN!$D$54)>0,IF(ISNUMBER(SEARCH(BRAIN!$D$54,AK6)),BRAIN!$D$54&", ",""),"") & IF(LEN(BRAIN!$D$55)>0,IF(ISNUMBER(SEARCH(BRAIN!$D$55,AK6)),BRAIN!$D$55&", ",""),"") & IF(LEN(BRAIN!$D$56)>0,IF(ISNUMBER(SEARCH(BRAIN!$D$56,AK6)),BRAIN!$D$56&", ",""),"") & IF(LEN(BRAIN!$D$57)>0,IF(ISNUMBER(SEARCH(BRAIN!$D$57,AK6)),BRAIN!$D$57&", ",""),"")),LEN((IF(LEN(BRAIN!$D$26)>0,IF(ISNUMBER(SEARCH(BRAIN!$D$26,AK6)),BRAIN!$D$26&", ",""),"") & IF(LEN(BRAIN!$D$27)>0,IF(ISNUMBER(SEARCH(BRAIN!$D$27,AK6)),BRAIN!$D$27&", ",""),"") & IF(LEN(BRAIN!$D$28)>0,IF(ISNUMBER(SEARCH(BRAIN!$D$28,AK6)),BRAIN!$D$28&", ",""),"") & IF(LEN(BRAIN!$D$29)>0,IF(ISNUMBER(SEARCH(BRAIN!$D$29,AK6)),BRAIN!$D$29&", ",""),"") & IF(LEN(BRAIN!$D$30)>0,IF(ISNUMBER(SEARCH(BRAIN!$D$30,AK6)),BRAIN!$D$30&", ",""),"") & IF(LEN(BRAIN!$D$31)>0,IF(ISNUMBER(SEARCH(BRAIN!$D$31,AK6)),BRAIN!$D$31&", ",""),"") & IF(LEN(BRAIN!$D$32)>0,IF(ISNUMBER(SEARCH(BRAIN!$D$32,AK6)),BRAIN!$D$32&", ",""),"") & IF(LEN(BRAIN!$D$33)>0,IF(ISNUMBER(SEARCH(BRAIN!$D$33,AK6)),BRAIN!$D$33&", ",""),"") & IF(LEN(BRAIN!$D$34)>0,IF(ISNUMBER(SEARCH(BRAIN!$D$34,AK6)),BRAIN!$D$34&", ",""),"") & IF(LEN(BRAIN!$D$35)>0,IF(ISNUMBER(SEARCH(BRAIN!$D$35,AK6)),BRAIN!$D$35&", ",""),"") & IF(LEN(BRAIN!$D$36)>0,IF(ISNUMBER(SEARCH(BRAIN!$D$36,AK6)),BRAIN!$D$36&", ",""),"") & IF(LEN(BRAIN!$D$37)>0,IF(ISNUMBER(SEARCH(BRAIN!$D$37,AK6)),BRAIN!$D$37&", ",""),"") & IF(LEN(BRAIN!$D$38)>0,IF(ISNUMBER(SEARCH(BRAIN!$D$38,AK6)),BRAIN!$D$38&", ",""),"") & IF(LEN(BRAIN!$D$39)>0,IF(ISNUMBER(SEARCH(BRAIN!$D$39,AK6)),BRAIN!$D$39&", ",""),"") & IF(LEN(BRAIN!$D$40)>0,IF(ISNUMBER(SEARCH(BRAIN!$D$40,AK6)),BRAIN!$D$40&", ",""),"") & IF(LEN(BRAIN!$D$41)>0,IF(ISNUMBER(SEARCH(BRAIN!$D$41,AK6)),BRAIN!$D$41&", ",""),"") & IF(LEN(BRAIN!$D$42)>0,IF(ISNUMBER(SEARCH(BRAIN!$D$42,AK6)),BRAIN!$D$42&", ",""),"") & IF(LEN(BRAIN!$D$43)>0,IF(ISNUMBER(SEARCH(BRAIN!$D$43,AK6)),BRAIN!$D$43&", ",""),"") & IF(LEN(BRAIN!$D$44)>0,IF(ISNUMBER(SEARCH(BRAIN!$D$44,AK6)),BRAIN!$D$44&", ",""),"") & IF(LEN(BRAIN!$D$45)>0,IF(ISNUMBER(SEARCH(BRAIN!$D$45,AK6)),BRAIN!$D$45&", ",""),"") & IF(LEN(BRAIN!$D$46)>0,IF(ISNUMBER(SEARCH(BRAIN!$D$46,AK6)),BRAIN!$D$46&", ",""),"") & IF(LEN(BRAIN!$D$47)>0,IF(ISNUMBER(SEARCH(BRAIN!$D$47,AK6)),BRAIN!$D$47&", ",""),"") & IF(LEN(BRAIN!$D$48)>0,IF(ISNUMBER(SEARCH(BRAIN!$D$48,AK6)),BRAIN!$D$48&", ",""),"") & IF(LEN(BRAIN!$D$49)>0,IF(ISNUMBER(SEARCH(BRAIN!$D$49,AK6)),BRAIN!$D$49&", ",""),"") & IF(LEN(BRAIN!$D$50)>0,IF(ISNUMBER(SEARCH(BRAIN!$D$50,AK6)),BRAIN!$D$50&", ",""),"") & IF(LEN(BRAIN!$D$51)>0,IF(ISNUMBER(SEARCH(BRAIN!$D$51,AK6)),BRAIN!$D$51&", ",""),"") & IF(LEN(BRAIN!$D$52)>0,IF(ISNUMBER(SEARCH(BRAIN!$D$52,AK6)),BRAIN!$D$52&", ",""),"") & IF(LEN(BRAIN!$D$53)>0,IF(ISNUMBER(SEARCH(BRAIN!$D$53,AK6)),BRAIN!$D$53&", ",""),"") & IF(LEN(BRAIN!$D$54)>0,IF(ISNUMBER(SEARCH(BRAIN!$D$54,AK6)),BRAIN!$D$54&", ",""),"") & IF(LEN(BRAIN!$D$55)>0,IF(ISNUMBER(SEARCH(BRAIN!$D$55,AK6)),BRAIN!$D$55&", ",""),"") & IF(LEN(BRAIN!$D$56)>0,IF(ISNUMBER(SEARCH(BRAIN!$D$56,AK6)),BRAIN!$D$56&", ",""),"") & IF(LEN(BRAIN!$D$57)>0,IF(ISNUMBER(SEARCH(BRAIN!$D$57,AK6)),BRAIN!$D$57&", ",""),"")))-2),(IF(LEN(BRAIN!$D$26)>0,IF(ISNUMBER(SEARCH(BRAIN!$D$26,AK6)),BRAIN!$D$26&", ",""),"") & IF(LEN(BRAIN!$D$27)>0,IF(ISNUMBER(SEARCH(BRAIN!$D$27,AK6)),BRAIN!$D$27&", ",""),"") & IF(LEN(BRAIN!$D$28)>0,IF(ISNUMBER(SEARCH(BRAIN!$D$28,AK6)),BRAIN!$D$28&", ",""),"") & IF(LEN(BRAIN!$D$29)>0,IF(ISNUMBER(SEARCH(BRAIN!$D$29,AK6)),BRAIN!$D$29&", ",""),"") & IF(LEN(BRAIN!$D$30)>0,IF(ISNUMBER(SEARCH(BRAIN!$D$30,AK6)),BRAIN!$D$30&", ",""),"") & IF(LEN(BRAIN!$D$31)>0,IF(ISNUMBER(SEARCH(BRAIN!$D$31,AK6)),BRAIN!$D$31&", ",""),"") & IF(LEN(BRAIN!$D$32)>0,IF(ISNUMBER(SEARCH(BRAIN!$D$32,AK6)),BRAIN!$D$32&", ",""),"") & IF(LEN(BRAIN!$D$33)>0,IF(ISNUMBER(SEARCH(BRAIN!$D$33,AK6)),BRAIN!$D$33&", ",""),"") & IF(LEN(BRAIN!$D$34)>0,IF(ISNUMBER(SEARCH(BRAIN!$D$34,AK6)),BRAIN!$D$34&", ",""),"") & IF(LEN(BRAIN!$D$35)>0,IF(ISNUMBER(SEARCH(BRAIN!$D$35,AK6)),BRAIN!$D$35&", ",""),"") & IF(LEN(BRAIN!$D$36)>0,IF(ISNUMBER(SEARCH(BRAIN!$D$36,AK6)),BRAIN!$D$36&", ",""),"") & IF(LEN(BRAIN!$D$37)>0,IF(ISNUMBER(SEARCH(BRAIN!$D$37,AK6)),BRAIN!$D$37&", ",""),"") & IF(LEN(BRAIN!$D$38)>0,IF(ISNUMBER(SEARCH(BRAIN!$D$38,AK6)),BRAIN!$D$38&", ",""),"") & IF(LEN(BRAIN!$D$39)>0,IF(ISNUMBER(SEARCH(BRAIN!$D$39,AK6)),BRAIN!$D$39&", ",""),"") & IF(LEN(BRAIN!$D$40)>0,IF(ISNUMBER(SEARCH(BRAIN!$D$40,AK6)),BRAIN!$D$40&", ",""),"") & IF(LEN(BRAIN!$D$41)>0,IF(ISNUMBER(SEARCH(BRAIN!$D$41,AK6)),BRAIN!$D$41&", ",""),"") & IF(LEN(BRAIN!$D$42)>0,IF(ISNUMBER(SEARCH(BRAIN!$D$42,AK6)),BRAIN!$D$42&", ",""),"") & IF(LEN(BRAIN!$D$43)>0,IF(ISNUMBER(SEARCH(BRAIN!$D$43,AK6)),BRAIN!$D$43&", ",""),"") & IF(LEN(BRAIN!$D$44)>0,IF(ISNUMBER(SEARCH(BRAIN!$D$44,AK6)),BRAIN!$D$44&", ",""),"") & IF(LEN(BRAIN!$D$45)>0,IF(ISNUMBER(SEARCH(BRAIN!$D$45,AK6)),BRAIN!$D$45&", ",""),"") & IF(LEN(BRAIN!$D$46)>0,IF(ISNUMBER(SEARCH(BRAIN!$D$46,AK6)),BRAIN!$D$46&", ",""),"") & IF(LEN(BRAIN!$D$47)>0,IF(ISNUMBER(SEARCH(BRAIN!$D$47,AK6)),BRAIN!$D$47&", ",""),"") & IF(LEN(BRAIN!$D$48)>0,IF(ISNUMBER(SEARCH(BRAIN!$D$48,AK6)),BRAIN!$D$48&", ",""),"") & IF(LEN(BRAIN!$D$49)>0,IF(ISNUMBER(SEARCH(BRAIN!$D$49,AK6)),BRAIN!$D$49&", ",""),"") & IF(LEN(BRAIN!$D$50)>0,IF(ISNUMBER(SEARCH(BRAIN!$D$50,AK6)),BRAIN!$D$50&", ",""),"") & IF(LEN(BRAIN!$D$51)>0,IF(ISNUMBER(SEARCH(BRAIN!$D$51,AK6)),BRAIN!$D$51&", ",""),"") & IF(LEN(BRAIN!$D$52)>0,IF(ISNUMBER(SEARCH(BRAIN!$D$52,AK6)),BRAIN!$D$52&", ",""),"") & IF(LEN(BRAIN!$D$53)>0,IF(ISNUMBER(SEARCH(BRAIN!$D$53,AK6)),BRAIN!$D$53&", ",""),"") & IF(LEN(BRAIN!$D$54)>0,IF(ISNUMBER(SEARCH(BRAIN!$D$54,AK6)),BRAIN!$D$54&", ",""),"") & IF(LEN(BRAIN!$D$55)>0,IF(ISNUMBER(SEARCH(BRAIN!$D$55,AK6)),BRAIN!$D$55&", ",""),"") & IF(LEN(BRAIN!$D$56)>0,IF(ISNUMBER(SEARCH(BRAIN!$D$56,AK6)),BRAIN!$D$56&", ",""),"") & IF(LEN(BRAIN!$D$57)>0,IF(ISNUMBER(SEARCH(BRAIN!$D$57,AK6)),BRAIN!$D$57&", ",""),""))),"") | AO6: =IFERROR(IF(RIGHT((IF(LEN(BRAIN!$E$26)>0,IF(ISNUMBER(SEARCH(BRAIN!$E$26,AK6)),BRAIN!$E$26&", ",""),"") & IF(LEN(BRAIN!$E$27)>0,IF(ISNUMBER(SEARCH(BRAIN!$E$27,AK6)),BRAIN!$E$27&", ",""),"") & IF(LEN(BRAIN!$E$28)>0,IF(ISNUMBER(SEARCH(BRAIN!$E$28,AK6)),BRAIN!$E$28&", ",""),"") & IF(LEN(BRAIN!$E$29)>0,IF(ISNUMBER(SEARCH(BRAIN!$E$29,AK6)),BRAIN!$E$29&", ",""),"") & IF(LEN(BRAIN!$E$30)>0,IF(ISNUMBER(SEARCH(BRAIN!$E$30,AK6)),BRAIN!$E$30&", ",""),"") & IF(LEN(BRAIN!$E$31)>0,IF(ISNUMBER(SEARCH(BRAIN!$E$31,AK6)),BRAIN!$E$31&", ",""),"") & IF(LEN(BRAIN!$E$32)>0,IF(ISNUMBER(SEARCH(BRAIN!$E$32,AK6)),BRAIN!$E$32&", ",""),"") & IF(LEN(BRAIN!$E$33)>0,IF(ISNUMBER(SEARCH(BRAIN!$E$33,AK6)),BRAIN!$E$33&", ",""),"") & IF(LEN(BRAIN!$E$34)>0,IF(ISNUMBER(SEARCH(BRAIN!$E$34,AK6)),BRAIN!$E$34&", ",""),"") & IF(LEN(BRAIN!$E$35)>0,IF(ISNUMBER(SEARCH(BRAIN!$E$35,AK6)),BRAIN!$E$35&", ",""),"") & IF(LEN(BRAIN!$E$36)>0,IF(ISNUMBER(SEARCH(BRAIN!$E$36,AK6)),BRAIN!$E$36&", ",""),"") & IF(LEN(BRAIN!$E$37)>0,IF(ISNUMBER(SEARCH(BRAIN!$E$37,AK6)),BRAIN!$E$37&", ",""),"") & IF(LEN(BRAIN!$E$38)>0,IF(ISNUMBER(SEARCH(BRAIN!$E$38,AK6)),BRAIN!$E$38&", ",""),"") & IF(LEN(BRAIN!$E$39)>0,IF(ISNUMBER(SEARCH(BRAIN!$E$39,AK6)),BRAIN!$E$39&", ",""),"") & IF(LEN(BRAIN!$E$40)>0,IF(ISNUMBER(SEARCH(BRAIN!$E$40,AK6)),BRAIN!$E$40&", ",""),"") & IF(LEN(BRAIN!$E$41)>0,IF(ISNUMBER(SEARCH(BRAIN!$E$41,AK6)),BRAIN!$E$41&", ",""),"") & IF(LEN(BRAIN!$E$42)>0,IF(ISNUMBER(SEARCH(BRAIN!$E$42,AK6)),BRAIN!$E$42&", ",""),"") & IF(LEN(BRAIN!$E$43)>0,IF(ISNUMBER(SEARCH(BRAIN!$E$43,AK6)),BRAIN!$E$43&", ",""),"") & IF(LEN(BRAIN!$E$44)>0,IF(ISNUMBER(SEARCH(BRAIN!$E$44,AK6)),BRAIN!$E$44&", ",""),"") & IF(LEN(BRAIN!$E$45)>0,IF(ISNUMBER(SEARCH(BRAIN!$E$45,AK6)),BRAIN!$E$45&", ",""),"") & IF(LEN(BRAIN!$E$46)>0,IF(ISNUMBER(SEARCH(BRAIN!$E$46,AK6)),BRAIN!$E$46&", ",""),"") & IF(LEN(BRAIN!$E$47)>0,IF(ISNUMBER(SEARCH(BRAIN!$E$47,AK6)),BRAIN!$E$47&", ",""),"") & IF(LEN(BRAIN!$E$48)>0,IF(ISNUMBER(SEARCH(BRAIN!$E$48,AK6)),BRAIN!$E$48&", ",""),"") & IF(LEN(BRAIN!$E$49)>0,IF(ISNUMBER(SEARCH(BRAIN!$E$49,AK6)),BRAIN!$E$49&", ",""),"") & IF(LEN(BRAIN!$E$50)>0,IF(ISNUMBER(SEARCH(BRAIN!$E$50,AK6)),BRAIN!$E$50&", ",""),"") & IF(LEN(BRAIN!$E$51)>0,IF(ISNUMBER(SEARCH(BRAIN!$E$51,AK6)),BRAIN!$E$51&", ",""),"") & IF(LEN(BRAIN!$E$52)>0,IF(ISNUMBER(SEARCH(BRAIN!$E$52,AK6)),BRAIN!$E$52&", ",""),"") & IF(LEN(BRAIN!$E$53)>0,IF(ISNUMBER(SEARCH(BRAIN!$E$53,AK6)),BRAIN!$E$53&", ",""),"") & IF(LEN(BRAIN!$E$54)>0,IF(ISNUMBER(SEARCH(BRAIN!$E$54,AK6)),BRAIN!$E$54&", ",""),"") & IF(LEN(BRAIN!$E$55)>0,IF(ISNUMBER(SEARCH(BRAIN!$E$55,AK6)),BRAIN!$E$55&", ",""),"") & IF(LEN(BRAIN!$E$56)>0,IF(ISNUMBER(SEARCH(BRAIN!$E$56,AK6)),BRAIN!$E$56&", ",""),"") & IF(LEN(BRAIN!$E$57)>0,IF(ISNUMBER(SEARCH(BRAIN!$E$57,AK6)),BRAIN!$E$57&", ",""),"")),2)=", ",LEFT((IF(LEN(BRAIN!$E$26)>0,IF(ISNUMBER(SEARCH(BRAIN!$E$26,AK6)),BRAIN!$E$26&", ",""),"") & IF(LEN(BRAIN!$E$27)>0,IF(ISNUMBER(SEARCH(BRAIN!$E$27,AK6)),BRAIN!$E$27&", ",""),"") & IF(LEN(BRAIN!$E$28)>0,IF(ISNUMBER(SEARCH(BRAIN!$E$28,AK6)),BRAIN!$E$28&", ",""),"") & IF(LEN(BRAIN!$E$29)>0,IF(ISNUMBER(SEARCH(BRAIN!$E$29,AK6)),BRAIN!$E$29&", ",""),"") & IF(LEN(BRAIN!$E$30)>0,IF(ISNUMBER(SEARCH(BRAIN!$E$30,AK6)),BRAIN!$E$30&", ",""),"") & IF(LEN(BRAIN!$E$31)>0,IF(ISNUMBER(SEARCH(BRAIN!$E$31,AK6)),BRAIN!$E$31&", ",""),"") & IF(LEN(BRAIN!$E$32)>0,IF(ISNUMBER(SEARCH(BRAIN!$E$32,AK6)),BRAIN!$E$32&", ",""),"") & IF(LEN(BRAIN!$E$33)>0,IF(ISNUMBER(SEARCH(BRAIN!$E$33,AK6)),BRAIN!$E$33&", ",""),"") & IF(LEN(BRAIN!$E$34)>0,IF(ISNUMBER(SEARCH(BRAIN!$E$34,AK6)),BRAIN!$E$34&", ",""),"") & IF(LEN(BRAIN!$E$35)>0,IF(ISNUMBER(SEARCH(BRAIN!$E$35,AK6)),BRAIN!$E$35&", ",""),"") & IF(LEN(BRAIN!$E$36)>0,IF(ISNUMBER(SEARCH(BRAIN!$E$36,AK6)),BRAIN!$E$36&", ",""),"") & IF(LEN(BRAIN!$E$37)>0,IF(ISNUMBER(SEARCH(BRAIN!$E$37,AK6)),BRAIN!$E$37&", ",""),"") & IF(LEN(BRAIN!$E$38)>0,IF(ISNUMBER(SEARCH(BRAIN!$E$38,AK6)),BRAIN!$E$38&", ",""),"") & IF(LEN(BRAIN!$E$39)>0,IF(ISNUMBER(SEARCH(BRAIN!$E$39,AK6)),BRAIN!$E$39&", ",""),"") & IF(LEN(BRAIN!$E$40)>0,IF(ISNUMBER(SEARCH(BRAIN!$E$40,AK6)),BRAIN!$E$40&", ",""),"") & IF(LEN(BRAIN!$E$41)>0,IF(ISNUMBER(SEARCH(BRAIN!$E$41,AK6)),BRAIN!$E$41&", ",""),"") & IF(LEN(BRAIN!$E$42)>0,IF(ISNUMBER(SEARCH(BRAIN!$E$42,AK6)),BRAIN!$E$42&", ",""),"") & IF(LEN(BRAIN!$E$43)>0,IF(ISNUMBER(SEARCH(BRAIN!$E$43,AK6)),BRAIN!$E$43&", ",""),"") & IF(LEN(BRAIN!$E$44)>0,IF(ISNUMBER(SEARCH(BRAIN!$E$44,AK6)),BRAIN!$E$44&", ",""),"") & IF(LEN(BRAIN!$E$45)>0,IF(ISNUMBER(SEARCH(BRAIN!$E$45,AK6)),BRAIN!$E$45&", ",""),"") & IF(LEN(BRAIN!$E$46)>0,IF(ISNUMBER(SEARCH(BRAIN!$E$46,AK6)),BRAIN!$E$46&", ",""),"") & IF(LEN(BRAIN!$E$47)>0,IF(ISNUMBER(SEARCH(BRAIN!$E$47,AK6)),BRAIN!$E$47&", ",""),"") & IF(LEN(BRAIN!$E$48)>0,IF(ISNUMBER(SEARCH(BRAIN!$E$48,AK6)),BRAIN!$E$48&", ",""),"") & IF(LEN(BRAIN!$E$49)>0,IF(ISNUMBER(SEARCH(BRAIN!$E$49,AK6)),BRAIN!$E$49&", ",""),"") & IF(LEN(BRAIN!$E$50)>0,IF(ISNUMBER(SEARCH(BRAIN!$E$50,AK6)),BRAIN!$E$50&", ",""),"") & IF(LEN(BRAIN!$E$51)>0,IF(ISNUMBER(SEARCH(BRAIN!$E$51,AK6)),BRAIN!$E$51&", ",""),"") & IF(LEN(BRAIN!$E$52)>0,IF(ISNUMBER(SEARCH(BRAIN!$E$52,AK6)),BRAIN!$E$52&", ",""),"") & IF(LEN(BRAIN!$E$53)>0,IF(ISNUMBER(SEARCH(BRAIN!$E$53,AK6)),BRAIN!$E$53&", ",""),"") & IF(LEN(BRAIN!$E$54)>0,IF(ISNUMBER(SEARCH(BRAIN!$E$54,AK6)),BRAIN!$E$54&", ",""),"") & IF(LEN(BRAIN!$E$55)>0,IF(ISNUMBER(SEARCH(BRAIN!$E$55,AK6)),BRAIN!$E$55&", ",""),"") & IF(LEN(BRAIN!$E$56)>0,IF(ISNUMBER(SEARCH(BRAIN!$E$56,AK6)),BRAIN!$E$56&", ",""),"") & IF(LEN(BRAIN!$E$57)>0,IF(ISNUMBER(SEARCH(BRAIN!$E$57,AK6)),BRAIN!$E$57&", ",""),"")),LEN((IF(LEN(BRAIN!$E$26)>0,IF(ISNUMBER(SEARCH(BRAIN!$E$26,AK6)),BRAIN!$E$26&", ",""),"") & IF(LEN(BRAIN!$E$27)>0,IF(ISNUMBER(SEARCH(BRAIN!$E$27,AK6)),BRAIN!$E$27&", ",""),"") & IF(LEN(BRAIN!$E$28)>0,IF(ISNUMBER(SEARCH(BRAIN!$E$28,AK6)),BRAIN!$E$28&", ",""),"") & IF(LEN(BRAIN!$E$29)>0,IF(ISNUMBER(SEARCH(BRAIN!$E$29,AK6)),BRAIN!$E$29&", ",""),"") & IF(LEN(BRAIN!$E$30)>0,IF(ISNUMBER(SEARCH(BRAIN!$E$30,AK6)),BRAIN!$E$30&", ",""),"") & IF(LEN(BRAIN!$E$31)>0,IF(ISNUMBER(SEARCH(BRAIN!$E$31,AK6)),BRAIN!$E$31&", ",""),"") & IF(LEN(BRAIN!$E$32)>0,IF(ISNUMBER(SEARCH(BRAIN!$E$32,AK6)),BRAIN!$E$32&", ",""),"") & IF(LEN(BRAIN!$E$33)>0,IF(ISNUMBER(SEARCH(BRAIN!$E$33,AK6)),BRAIN!$E$33&", ",""),"") & IF(LEN(BRAIN!$E$34)>0,IF(ISNUMBER(SEARCH(BRAIN!$E$34,AK6)),BRAIN!$E$34&", ",""),"") & IF(LEN(BRAIN!$E$35)>0,IF(ISNUMBER(SEARCH(BRAIN!$E$35,AK6)),BRAIN!$E$35&", ",""),"") & IF(LEN(BRAIN!$E$36)>0,IF(ISNUMBER(SEARCH(BRAIN!$E$36,AK6)),BRAIN!$E$36&", ",""),"") & IF(LEN(BRAIN!$E$37)>0,IF(ISNUMBER(SEARCH(BRAIN!$E$37,AK6)),BRAIN!$E$37&", ",""),"") & IF(LEN(BRAIN!$E$38)>0,IF(ISNUMBER(SEARCH(BRAIN!$E$38,AK6)),BRAIN!$E$38&", ",""),"") & IF(LEN(BRAIN!$E$39)>0,IF(ISNUMBER(SEARCH(BRAIN!$E$39,AK6)),BRAIN!$E$39&", ",""),"") & IF(LEN(BRAIN!$E$40)>0,IF(ISNUMBER(SEARCH(BRAIN!$E$40,AK6)),BRAIN!$E$40&", ",""),"") & IF(LEN(BRAIN!$E$41)>0,IF(ISNUMBER(SEARCH(BRAIN!$E$41,AK6)),BRAIN!$E$41&", ",""),"") & IF(LEN(BRAIN!$E$42)>0,IF(ISNUMBER(SEARCH(BRAIN!$E$42,AK6)),BRAIN!$E$42&", ",""),"") & IF(LEN(BRAIN!$E$43)>0,IF(ISNUMBER(SEARCH(BRAIN!$E$43,AK6)),BRAIN!$E$43&", ",""),"") & IF(LEN(BRAIN!$E$44)>0,IF(ISNUMBER(SEARCH(BRAIN!$E$44,AK6)),BRAIN!$E$44&", ",""),"") & IF(LEN(BRAIN!$E$45)>0,IF(ISNUMBER(SEARCH(BRAIN!$E$45,AK6)),BRAIN!$E$45&", ",""),"") & IF(LEN(BRAIN!$E$46)>0,IF(ISNUMBER(SEARCH(BRAIN!$E$46,AK6)),BRAIN!$E$46&", ",""),"") & IF(LEN(BRAIN!$E$47)>0,IF(ISNUMBER(SEARCH(BRAIN!$E$47,AK6)),BRAIN!$E$47&", ",""),"") & IF(LEN(BRAIN!$E$48)>0,IF(ISNUMBER(SEARCH(BRAIN!$E$48,AK6)),BRAIN!$E$48&", ",""),"") & IF(LEN(BRAIN!$E$49)>0,IF(ISNUMBER(SEARCH(BRAIN!$E$49,AK6)),BRAIN!$E$49&", ",""),"") & IF(LEN(BRAIN!$E$50)>0,IF(ISNUMBER(SEARCH(BRAIN!$E$50,AK6)),BRAIN!$E$50&", ",""),"") & IF(LEN(BRAIN!$E$51)>0,IF(ISNUMBER(SEARCH(BRAIN!$E$51,AK6)),BRAIN!$E$51&", ",""),"") & IF(LEN(BRAIN!$E$52)>0,IF(ISNUMBER(SEARCH(BRAIN!$E$52,AK6)),BRAIN!$E$52&", ",""),"") & IF(LEN(BRAIN!$E$53)>0,IF(ISNUMBER(SEARCH(BRAIN!$E$53,AK6)),BRAIN!$E$53&", ",""),"") & IF(LEN(BRAIN!$E$54)>0,IF(ISNUMBER(SEARCH(BRAIN!$E$54,AK6)),BRAIN!$E$54&", ",""),"") & IF(LEN(BRAIN!$E$55)>0,IF(ISNUMBER(SEARCH(BRAIN!$E$55,AK6)),BRAIN!$E$55&", ",""),"") & IF(LEN(BRAIN!$E$56)>0,IF(ISNUMBER(SEARCH(BRAIN!$E$56,AK6)),BRAIN!$E$56&", ",""),"") & IF(LEN(BRAIN!$E$57)>0,IF(ISNUMBER(SEARCH(BRAIN!$E$57,AK6)),BRAIN!$E$57&", ",""),"")))-2),(IF(LEN(BRAIN!$E$26)>0,IF(ISNUMBER(SEARCH(BRAIN!$E$26,AK6)),BRAIN!$E$26&", ",""),"") & IF(LEN(BRAIN!$E$27)>0,IF(ISNUMBER(SEARCH(BRAIN!$E$27,AK6)),BRAIN!$E$27&", ",""),"") & IF(LEN(BRAIN!$E$28)>0,IF(ISNUMBER(SEARCH(BRAIN!$E$28,AK6)),BRAIN!$E$28&", ",""),"") & IF(LEN(BRAIN!$E$29)>0,IF(ISNUMBER(SEARCH(BRAIN!$E$29,AK6)),BRAIN!$E$29&", ",""),"") & IF(LEN(BRAIN!$E$30)>0,IF(ISNUMBER(SEARCH(BRAIN!$E$30,AK6)),BRAIN!$E$30&", ",""),"") & IF(LEN(BRAIN!$E$31)>0,IF(ISNUMBER(SEARCH(BRAIN!$E$31,AK6)),BRAIN!$E$31&", ",""),"") & IF(LEN(BRAIN!$E$32)>0,IF(ISNUMBER(SEARCH(BRAIN!$E$32,AK6)),BRAIN!$E$32&", ",""),"") & IF(LEN(BRAIN!$E$33)>0,IF(ISNUMBER(SEARCH(BRAIN!$E$33,AK6)),BRAIN!$E$33&", ",""),"") & IF(LEN(BRAIN!$E$34)>0,IF(ISNUMBER(SEARCH(BRAIN!$E$34,AK6)),BRAIN!$E$34&", ",""),"") & IF(LEN(BRAIN!$E$35)>0,IF(ISNUMBER(SEARCH(BRAIN!$E$35,AK6)),BRAIN!$E$35&", ",""),"") & IF(LEN(BRAIN!$E$36)>0,IF(ISNUMBER(SEARCH(BRAIN!$E$36,AK6)),BRAIN!$E$36&", ",""),"") & IF(LEN(BRAIN!$E$37)>0,IF(ISNUMBER(SEARCH(BRAIN!$E$37,AK6)),BRAIN!$E$37&", ",""),"") & IF(LEN(BRAIN!$E$38)>0,IF(ISNUMBER(SEARCH(BRAIN!$E$38,AK6)),BRAIN!$E$38&", ",""),"") & IF(LEN(BRAIN!$E$39)>0,IF(ISNUMBER(SEARCH(BRAIN!$E$39,AK6)),BRAIN!$E$39&", ",""),"") & IF(LEN(BRAIN!$E$40)>0,IF(ISNUMBER(SEARCH(BRAIN!$E$40,AK6)),BRAIN!$E$40&", ",""),"") & IF(LEN(BRAIN!$E$41)>0,IF(ISNUMBER(SEARCH(BRAIN!$E$41,AK6)),BRAIN!$E$41&", ",""),"") & IF(LEN(BRAIN!$E$42)>0,IF(ISNUMBER(SEARCH(BRAIN!$E$42,AK6)),BRAIN!$E$42&", ",""),"") & IF(LEN(BRAIN!$E$43)>0,IF(ISNUMBER(SEARCH(BRAIN!$E$43,AK6)),BRAIN!$E$43&", ",""),"") & IF(LEN(BRAIN!$E$44)>0,IF(ISNUMBER(SEARCH(BRAIN!$E$44,AK6)),BRAIN!$E$44&", ",""),"") & IF(LEN(BRAIN!$E$45)>0,IF(ISNUMBER(SEARCH(BRAIN!$E$45,AK6)),BRAIN!$E$45&", ",""),"") & IF(LEN(BRAIN!$E$46)>0,IF(ISNUMBER(SEARCH(BRAIN!$E$46,AK6)),BRAIN!$E$46&", ",""),"") & IF(LEN(BRAIN!$E$47)>0,IF(ISNUMBER(SEARCH(BRAIN!$E$47,AK6)),BRAIN!$E$47&", ",""),"") & IF(LEN(BRAIN!$E$48)>0,IF(ISNUMBER(SEARCH(BRAIN!$E$48,AK6)),BRAIN!$E$48&", ",""),"") & IF(LEN(BRAIN!$E$49)>0,IF(ISNUMBER(SEARCH(BRAIN!$E$49,AK6)),BRAIN!$E$49&", ",""),"") & IF(LEN(BRAIN!$E$50)>0,IF(ISNUMBER(SEARCH(BRAIN!$E$50,AK6)),BRAIN!$E$50&", ",""),"") & IF(LEN(BRAIN!$E$51)>0,IF(ISNUMBER(SEARCH(BRAIN!$E$51,AK6)),BRAIN!$E$51&", ",""),"") & IF(LEN(BRAIN!$E$52)>0,IF(ISNUMBER(SEARCH(BRAIN!$E$52,AK6)),BRAIN!$E$52&", ",""),"") & IF(LEN(BRAIN!$E$53)>0,IF(ISNUMBER(SEARCH(BRAIN!$E$53,AK6)),BRAIN!$E$53&", ",""),"") & IF(LEN(BRAIN!$E$54)>0,IF(ISNUMBER(SEARCH(BRAIN!$E$54,AK6)),BRAIN!$E$54&", ",""),"") & IF(LEN(BRAIN!$E$55)>0,IF(ISNUMBER(SEARCH(BRAIN!$E$55,AK6)),BRAIN!$E$55&", ",""),"") & IF(LEN(BRAIN!$E$56)>0,IF(ISNUMBER(SEARCH(BRAIN!$E$56,AK6)),BRAIN!$E$56&", ",""),"") & IF(LEN(BRAIN!$E$57)>0,IF(ISNUMBER(SEARCH(BRAIN!$E$57,AK6)),BRAIN!$E$57&", ",""),""))),"") -> customs, declaration, duty, hs code, handwritten, shipment, invoice, ocr, broker | AP6: =IFERROR(IF(RIGHT((IF(LEN(BRAIN!$F$26)>0,IF(ISNUMBER(SEARCH(BRAIN!$F$26,AK6)),BRAIN!$F$26&", ",""),"") & IF(LEN(BRAIN!$F$27)>0,IF(ISNUMBER(SEARCH(BRAIN!$F$27,AK6)),BRAIN!$F$27&", ",""),"") & IF(LEN(BRAIN!$F$28)>0,IF(ISNUMBER(SEARCH(BRAIN!$F$28,AK6)),BRAIN!$F$28&", ",""),"") & IF(LEN(BRAIN!$F$29)>0,IF(ISNUMBER(SEARCH(BRAIN!$F$29,AK6)),BRAIN!$F$29&", ",""),"") & IF(LEN(BRAIN!$F$30)>0,IF(ISNUMBER(SEARCH(BRAIN!$F$30,AK6)),BRAIN!$F$30&", ",""),"") & IF(LEN(BRAIN!$F$31)>0,IF(ISNUMBER(SEARCH(BRAIN!$F$31,AK6)),BRAIN!$F$31&", ",""),"") & IF(LEN(BRAIN!$F$32)>0,IF(ISNUMBER(SEARCH(BRAIN!$F$32,AK6)),BRAIN!$F$32&", ",""),"") & IF(LEN(BRAIN!$F$33)>0,IF(ISNUMBER(SEARCH(BRAIN!$F$33,AK6)),BRAIN!$F$33&", ",""),"") & IF(LEN(BRAIN!$F$34)>0,IF(ISNUMBER(SEARCH(BRAIN!$F$34,AK6)),BRAIN!$F$34&", ",""),"") & IF(LEN(BRAIN!$F$35)>0,IF(ISNUMBER(SEARCH(BRAIN!$F$35,AK6)),BRAIN!$F$35&", ",""),"") & IF(LEN(BRAIN!$F$36)>0,IF(ISNUMBER(SEARCH(BRAIN!$F$36,AK6)),BRAIN!$F$36&", ",""),"") & IF(LEN(BRAIN!$F$37)>0,IF(ISNUMBER(SEARCH(BRAIN!$F$37,AK6)),BRAIN!$F$37&", ",""),"") & IF(LEN(BRAIN!$F$38)>0,IF(ISNUMBER(SEARCH(BRAIN!$F$38,AK6)),BRAIN!$F$38&", ",""),"") & IF(LEN(BRAIN!$F$39)>0,IF(ISNUMBER(SEARCH(BRAIN!$F$39,AK6)),BRAIN!$F$39&", ",""),"") & IF(LEN(BRAIN!$F$40)>0,IF(ISNUMBER(SEARCH(BRAIN!$F$40,AK6)),BRAIN!$F$40&", ",""),"") & IF(LEN(BRAIN!$F$41)>0,IF(ISNUMBER(SEARCH(BRAIN!$F$41,AK6)),BRAIN!$F$41&", ",""),"") & IF(LEN(BRAIN!$F$42)>0,IF(ISNUMBER(SEARCH(BRAIN!$F$42,AK6)),BRAIN!$F$42&", ",""),"") & IF(LEN(BRAIN!$F$43)>0,IF(ISNUMBER(SEARCH(BRAIN!$F$43,AK6)),BRAIN!$F$43&", ",""),"") & IF(LEN(BRAIN!$F$44)>0,IF(ISNUMBER(SEARCH(BRAIN!$F$44,AK6)),BRAIN!$F$44&", ",""),"") & IF(LEN(BRAIN!$F$45)>0,IF(ISNUMBER(SEARCH(BRAIN!$F$45,AK6)),BRAIN!$F$45&", ",""),"") & IF(LEN(BRAIN!$F$46)>0,IF(ISNUMBER(SEARCH(BRAIN!$F$46,AK6)),BRAIN!$F$46&", ",""),"") & IF(LEN(BRAIN!$F$47)>0,IF(ISNUMBER(SEARCH(BRAIN!$F$47,AK6)),BRAIN!$F$47&", ",""),"") & IF(LEN(BRAIN!$F$48)>0,IF(ISNUMBER(SEARCH(BRAIN!$F$48,AK6)),BRAIN!$F$48&", ",""),"") & IF(LEN(BRAIN!$F$49)>0,IF(ISNUMBER(SEARCH(BRAIN!$F$49,AK6)),BRAIN!$F$49&", ",""),"") & IF(LEN(BRAIN!$F$50)>0,IF(ISNUMBER(SEARCH(BRAIN!$F$50,AK6)),BRAIN!$F$50&", ",""),"") & IF(LEN(BRAIN!$F$51)>0,IF(ISNUMBER(SEARCH(BRAIN!$F$51,AK6)),BRAIN!$F$51&", ",""),"") & IF(LEN(BRAIN!$F$52)>0,IF(ISNUMBER(SEARCH(BRAIN!$F$52,AK6)),BRAIN!$F$52&", ",""),"") & IF(LEN(BRAIN!$F$53)>0,IF(ISNUMBER(SEARCH(BRAIN!$F$53,AK6)),BRAIN!$F$53&", ",""),"") & IF(LEN(BRAIN!$F$54)>0,IF(ISNUMBER(SEARCH(BRAIN!$F$54,AK6)),BRAIN!$F$54&", ",""),"") & IF(LEN(BRAIN!$F$55)>0,IF(ISNUMBER(SEARCH(BRAIN!$F$55,AK6)),BRAIN!$F$55&", ",""),"") & IF(LEN(BRAIN!$F$56)>0,IF(ISNUMBER(SEARCH(BRAIN!$F$56,AK6)),BRAIN!$F$56&", ",""),"") & IF(LEN(BRAIN!$F$57)>0,IF(ISNUMBER(SEARCH(BRAIN!$F$57,AK6)),BRAIN!$F$57&", ",""),"")),2)=", ",LEFT((IF(LEN(BRAIN!$F$26)>0,IF(ISNUMBER(SEARCH(BRAIN!$F$26,AK6)),BRAIN!$F$26&", ",""),"") & IF(LEN(BRAIN!$F$27)>0,IF(ISNUMBER(SEARCH(BRAIN!$F$27,AK6)),BRAIN!$F$27&", ",""),"") & IF(LEN(BRAIN!$F$28)>0,IF(ISNUMBER(SEARCH(BRAIN!$F$28,AK6)),BRAIN!$F$28&", ",""),"") & IF(LEN(BRAIN!$F$29)>0,IF(ISNUMBER(SEARCH(BRAIN!$F$29,AK6)),BRAIN!$F$29&", ",""),"") & IF(LEN(BRAIN!$F$30)>0,IF(ISNUMBER(SEARCH(BRAIN!$F$30,AK6)),BRAIN!$F$30&", ",""),"") & IF(LEN(BRAIN!$F$31)>0,IF(ISNUMBER(SEARCH(BRAIN!$F$31,AK6)),BRAIN!$F$31&", ",""),"") & IF(LEN(BRAIN!$F$32)>0,IF(ISNUMBER(SEARCH(BRAIN!$F$32,AK6)),BRAIN!$F$32&", ",""),"") & IF(LEN(BRAIN!$F$33)>0,IF(ISNUMBER(SEARCH(BRAIN!$F$33,AK6)),BRAIN!$F$33&", ",""),"") & IF(LEN(BRAIN!$F$34)>0,IF(ISNUMBER(SEARCH(BRAIN!$F$34,AK6)),BRAIN!$F$34&", ",""),"") & IF(LEN(BRAIN!$F$35)>0,IF(ISNUMBER(SEARCH(BRAIN!$F$35,AK6)),BRAIN!$F$35&", ",""),"") & IF(LEN(BRAIN!$F$36)>0,IF(ISNUMBER(SEARCH(BRAIN!$F$36,AK6)),BRAIN!$F$36&", ",""),"") & IF(LEN(BRAIN!$F$37)>0,IF(ISNUMBER(SEARCH(BRAIN!$F$37,AK6)),BRAIN!$F$37&", ",""),"") & IF(LEN(BRAIN!$F$38)>0,IF(ISNUMBER(SEARCH(BRAIN!$F$38,AK6)),BRAIN!$F$38&", ",""),"") & IF(LEN(BRAIN!$F$39)>0,IF(ISNUMBER(SEARCH(BRAIN!$F$39,AK6)),BRAIN!$F$39&", ",""),"") & IF(LEN(BRAIN!$F$40)>0,IF(ISNUMBER(SEARCH(BRAIN!$F$40,AK6)),BRAIN!$F$40&", ",""),"") & IF(LEN(BRAIN!$F$41)>0,IF(ISNUMBER(SEARCH(BRAIN!$F$41,AK6)),BRAIN!$F$41&", ",""),"") & IF(LEN(BRAIN!$F$42)>0,IF(ISNUMBER(SEARCH(BRAIN!$F$42,AK6)),BRAIN!$F$42&", ",""),"") & IF(LEN(BRAIN!$F$43)>0,IF(ISNUMBER(SEARCH(BRAIN!$F$43,AK6)),BRAIN!$F$43&", ",""),"") & IF(LEN(BRAIN!$F$44)>0,IF(ISNUMBER(SEARCH(BRAIN!$F$44,AK6)),BRAIN!$F$44&", ",""),"") & IF(LEN(BRAIN!$F$45)>0,IF(ISNUMBER(SEARCH(BRAIN!$F$45,AK6)),BRAIN!$F$45&", ",""),"") & IF(LEN(BRAIN!$F$46)>0,IF(ISNUMBER(SEARCH(BRAIN!$F$46,AK6)),BRAIN!$F$46&", ",""),"") & IF(LEN(BRAIN!$F$47)>0,IF(ISNUMBER(SEARCH(BRAIN!$F$47,AK6)),BRAIN!$F$47&", ",""),"") & IF(LEN(BRAIN!$F$48)>0,IF(ISNUMBER(SEARCH(BRAIN!$F$48,AK6)),BRAIN!$F$48&", ",""),"") & IF(LEN(BRAIN!$F$49)>0,IF(ISNUMBER(SEARCH(BRAIN!$F$49,AK6)),BRAIN!$F$49&", ",""),"") & IF(LEN(BRAIN!$F$50)>0,IF(ISNUMBER(SEARCH(BRAIN!$F$50,AK6)),BRAIN!$F$50&", ",""),"") & IF(LEN(BRAIN!$F$51)>0,IF(ISNUMBER(SEARCH(BRAIN!$F$51,AK6)),BRAIN!$F$51&", ",""),"") & IF(LEN(BRAIN!$F$52)>0,IF(ISNUMBER(SEARCH(BRAIN!$F$52,AK6)),BRAIN!$F$52&", ",""),"") & IF(LEN(BRAIN!$F$53)>0,IF(ISNUMBER(SEARCH(BRAIN!$F$53,AK6)),BRAIN!$F$53&", ",""),"") & IF(LEN(BRAIN!$F$54)>0,IF(ISNUMBER(SEARCH(BRAIN!$F$54,AK6)),BRAIN!$F$54&", ",""),"") & IF(LEN(BRAIN!$F$55)>0,IF(ISNUMBER(SEARCH(BRAIN!$F$55,AK6)),BRAIN!$F$55&", ",""),"") & IF(LEN(BRAIN!$F$56)>0,IF(ISNUMBER(SEARCH(BRAIN!$F$56,AK6)),BRAIN!$F$56&", ",""),"") & IF(LEN(BRAIN!$F$57)>0,IF(ISNUMBER(SEARCH(BRAIN!$F$57,AK6)),BRAIN!$F$57&", ",""),"")),LEN((IF(LEN(BRAIN!$F$26)>0,IF(ISNUMBER(SEARCH(BRAIN!$F$26,AK6)),BRAIN!$F$26&", ",""),"") & IF(LEN(BRAIN!$F$27)>0,IF(ISNUMBER(SEARCH(BRAIN!$F$27,AK6)),BRAIN!$F$27&", ",""),"") & IF(LEN(BRAIN!$F$28)>0,IF(ISNUMBER(SEARCH(BRAIN!$F$28,AK6)),BRAIN!$F$28&", ",""),"") & IF(LEN(BRAIN!$F$29)>0,IF(ISNUMBER(SEARCH(BRAIN!$F$29,AK6)),BRAIN!$F$29&", ",""),"") & IF(LEN(BRAIN!$F$30)>0,IF(ISNUMBER(SEARCH(BRAIN!$F$30,AK6)),BRAIN!$F$30&", ",""),"") & IF(LEN(BRAIN!$F$31)>0,IF(ISNUMBER(SEARCH(BRAIN!$F$31,AK6)),BRAIN!$F$31&", ",""),"") & IF(LEN(BRAIN!$F$32)>0,IF(ISNUMBER(SEARCH(BRAIN!$F$32,AK6)),BRAIN!$F$32&", ",""),"") & IF(LEN(BRAIN!$F$33)>0,IF(ISNUMBER(SEARCH(BRAIN!$F$33,AK6)),BRAIN!$F$33&", ",""),"") & IF(LEN(BRAIN!$F$34)>0,IF(ISNUMBER(SEARCH(BRAIN!$F$34,AK6)),BRAIN!$F$34&", ",""),"") & IF(LEN(BRAIN!$F$35)>0,IF(ISNUMBER(SEARCH(BRAIN!$F$35,AK6)),BRAIN!$F$35&", ",""),"") & IF(LEN(BRAIN!$F$36)>0,IF(ISNUMBER(SEARCH(BRAIN!$F$36,AK6)),BRAIN!$F$36&", ",""),"") & IF(LEN(BRAIN!$F$37)>0,IF(ISNUMBER(SEARCH(BRAIN!$F$37,AK6)),BRAIN!$F$37&", ",""),"") & IF(LEN(BRAIN!$F$38)>0,IF(ISNUMBER(SEARCH(BRAIN!$F$38,AK6)),BRAIN!$F$38&", ",""),"") & IF(LEN(BRAIN!$F$39)>0,IF(ISNUMBER(SEARCH(BRAIN!$F$39,AK6)),BRAIN!$F$39&", ",""),"") & IF(LEN(BRAIN!$F$40)>0,IF(ISNUMBER(SEARCH(BRAIN!$F$40,AK6)),BRAIN!$F$40&", ",""),"") & IF(LEN(BRAIN!$F$41)>0,IF(ISNUMBER(SEARCH(BRAIN!$F$41,AK6)),BRAIN!$F$41&", ",""),"") & IF(LEN(BRAIN!$F$42)>0,IF(ISNUMBER(SEARCH(BRAIN!$F$42,AK6)),BRAIN!$F$42&", ",""),"") & IF(LEN(BRAIN!$F$43)>0,IF(ISNUMBER(SEARCH(BRAIN!$F$43,AK6)),BRAIN!$F$43&", ",""),"") & IF(LEN(BRAIN!$F$44)>0,IF(ISNUMBER(SEARCH(BRAIN!$F$44,AK6)),BRAIN!$F$44&", ",""),"") & IF(LEN(BRAIN!$F$45)>0,IF(ISNUMBER(SEARCH(BRAIN!$F$45,AK6)),BRAIN!$F$45&", ",""),"") & IF(LEN(BRAIN!$F$46)>0,IF(ISNUMBER(SEARCH(BRAIN!$F$46,AK6)),BRAIN!$F$46&", ",""),"") & IF(LEN(BRAIN!$F$47)>0,IF(ISNUMBER(SEARCH(BRAIN!$F$47,AK6)),BRAIN!$F$47&", ",""),"") & IF(LEN(BRAIN!$F$48)>0,IF(ISNUMBER(SEARCH(BRAIN!$F$48,AK6)),BRAIN!$F$48&", ",""),"") & IF(LEN(BRAIN!$F$49)>0,IF(ISNUMBER(SEARCH(BRAIN!$F$49,AK6)),BRAIN!$F$49&", ",""),"") & IF(LEN(BRAIN!$F$50)>0,IF(ISNUMBER(SEARCH(BRAIN!$F$50,AK6)),BRAIN!$F$50&", ",""),"") & IF(LEN(BRAIN!$F$51)>0,IF(ISNUMBER(SEARCH(BRAIN!$F$51,AK6)),BRAIN!$F$51&", ",""),"") & IF(LEN(BRAIN!$F$52)>0,IF(ISNUMBER(SEARCH(BRAIN!$F$52,AK6)),BRAIN!$F$52&", ",""),"") & IF(LEN(BRAIN!$F$53)>0,IF(ISNUMBER(SEARCH(BRAIN!$F$53,AK6)),BRAIN!$F$53&", ",""),"") & IF(LEN(BRAIN!$F$54)>0,IF(ISNUMBER(SEARCH(BRAIN!$F$54,AK6)),BRAIN!$F$54&", ",""),"") & IF(LEN(BRAIN!$F$55)>0,IF(ISNUMBER(SEARCH(BRAIN!$F$55,AK6)),BRAIN!$F$55&", ",""),"") & IF(LEN(BRAIN!$F$56)>0,IF(ISNUMBER(SEARCH(BRAIN!$F$56,AK6)),BRAIN!$F$56&", ",""),"") & IF(LEN(BRAIN!$F$57)>0,IF(ISNUMBER(SEARCH(BRAIN!$F$57,AK6)),BRAIN!$F$57&", ",""),"")))-2),(IF(LEN(BRAIN!$F$26)>0,IF(ISNUMBER(SEARCH(BRAIN!$F$26,AK6)),BRAIN!$F$26&", ",""),"") & IF(LEN(BRAIN!$F$27)>0,IF(ISNUMBER(SEARCH(BRAIN!$F$27,AK6)),BRAIN!$F$27&", ",""),"") & IF(LEN(BRAIN!$F$28)>0,IF(ISNUMBER(SEARCH(BRAIN!$F$28,AK6)),BRAIN!$F$28&", ",""),"") & IF(LEN(BRAIN!$F$29)>0,IF(ISNUMBER(SEARCH(BRAIN!$F$29,AK6)),BRAIN!$F$29&", ",""),"") & IF(LEN(BRAIN!$F$30)>0,IF(ISNUMBER(SEARCH(BRAIN!$F$30,AK6)),BRAIN!$F$30&", ",""),"") & IF(LEN(BRAIN!$F$31)>0,IF(ISNUMBER(SEARCH(BRAIN!$F$31,AK6)),BRAIN!$F$31&", ",""),"") & IF(LEN(BRAIN!$F$32)>0,IF(ISNUMBER(SEARCH(BRAIN!$F$32,AK6)),BRAIN!$F$32&", ",""),"") & IF(LEN(BRAIN!$F$33)>0,IF(ISNUMBER(SEARCH(BRAIN!$F$33,AK6)),BRAIN!$F$33&", ",""),"") & IF(LEN(BRAIN!$F$34)>0,IF(ISNUMBER(SEARCH(BRAIN!$F$34,AK6)),BRAIN!$F$34&", ",""),"") & IF(LEN(BRAIN!$F$35)>0,IF(ISNUMBER(SEARCH(BRAIN!$F$35,AK6)),BRAIN!$F$35&", ",""),"") & IF(LEN(BRAIN!$F$36)>0,IF(ISNUMBER(SEARCH(BRAIN!$F$36,AK6)),BRAIN!$F$36&", ",""),"") & IF(LEN(BRAIN!$F$37)>0,IF(ISNUMBER(SEARCH(BRAIN!$F$37,AK6)),BRAIN!$F$37&", ",""),"") & IF(LEN(BRAIN!$F$38)>0,IF(ISNUMBER(SEARCH(BRAIN!$F$38,AK6)),BRAIN!$F$38&", ",""),"") & IF(LEN(BRAIN!$F$39)>0,IF(ISNUMBER(SEARCH(BRAIN!$F$39,AK6)),BRAIN!$F$39&", ",""),"") & IF(LEN(BRAIN!$F$40)>0,IF(ISNUMBER(SEARCH(BRAIN!$F$40,AK6)),BRAIN!$F$40&", ",""),"") & IF(LEN(BRAIN!$F$41)>0,IF(ISNUMBER(SEARCH(BRAIN!$F$41,AK6)),BRAIN!$F$41&", ",""),"") & IF(LEN(BRAIN!$F$42)>0,IF(ISNUMBER(SEARCH(BRAIN!$F$42,AK6)),BRAIN!$F$42&", ",""),"") & IF(LEN(BRAIN!$F$43)>0,IF(ISNUMBER(SEARCH(BRAIN!$F$43,AK6)),BRAIN!$F$43&", ",""),"") & IF(LEN(BRAIN!$F$44)>0,IF(ISNUMBER(SEARCH(BRAIN!$F$44,AK6)),BRAIN!$F$44&", ",""),"") & IF(LEN(BRAIN!$F$45)>0,IF(ISNUMBER(SEARCH(BRAIN!$F$45,AK6)),BRAIN!$F$45&", ",""),"") & IF(LEN(BRAIN!$F$46)>0,IF(ISNUMBER(SEARCH(BRAIN!$F$46,AK6)),BRAIN!$F$46&", ",""),"") & IF(LEN(BRAIN!$F$47)>0,IF(ISNUMBER(SEARCH(BRAIN!$F$47,AK6)),BRAIN!$F$47&", ",""),"") & IF(LEN(BRAIN!$F$48)>0,IF(ISNUMBER(SEARCH(BRAIN!$F$48,AK6)),BRAIN!$F$48&", ",""),"") & IF(LEN(BRAIN!$F$49)>0,IF(ISNUMBER(SEARCH(BRAIN!$F$49,AK6)),BRAIN!$F$49&", ",""),"") & IF(LEN(BRAIN!$F$50)>0,IF(ISNUMBER(SEARCH(BRAIN!$F$50,AK6)),BRAIN!$F$50&", ",""),"") & IF(LEN(BRAIN!$F$51)>0,IF(ISNUMBER(SEARCH(BRAIN!$F$51,AK6)),BRAIN!$F$51&", ",""),"") & IF(LEN(BRAIN!$F$52)>0,IF(ISNUMBER(SEARCH(BRAIN!$F$52,AK6)),BRAIN!$F$52&", ",""),"") & IF(LEN(BRAIN!$F$53)>0,IF(ISNUMBER(SEARCH(BRAIN!$F$53,AK6)),BRAIN!$F$53&", ",""),"") & IF(LEN(BRAIN!$F$54)>0,IF(ISNUMBER(SEARCH(BRAIN!$F$54,AK6)),BRAIN!$F$54&", ",""),"") & IF(LEN(BRAIN!$F$55)>0,IF(ISNUMBER(SEARCH(BRAIN!$F$55,AK6)),BRAIN!$F$55&", ",""),"") & IF(LEN(BRAIN!$F$56)>0,IF(ISNUMBER(SEARCH(BRAIN!$F$56,AK6)),BRAIN!$F$56&", ",""),"") & IF(LEN(BRAIN!$F$57)>0,IF(ISNUMBER(SEARCH(BRAIN!$F$57,AK6)),BRAIN!$F$57&", ",""),""))),"") | AQ6: =IFERROR(IF(RIGHT((IF(LEN(BRAIN!$G$26)>0,IF(ISNUMBER(SEARCH(BRAIN!$G$26,AK6)),BRAIN!$G$26&", ",""),"") & IF(LEN(BRAIN!$G$27)>0,IF(ISNUMBER(SEARCH(BRAIN!$G$27,AK6)),BRAIN!$G$27&", ",""),"") & IF(LEN(BRAIN!$G$28)>0,IF(ISNUMBER(SEARCH(BRAIN!$G$28,AK6)),BRAIN!$G$28&", ",""),"") & IF(LEN(BRAIN!$G$29)>0,IF(ISNUMBER(SEARCH(BRAIN!$G$29,AK6)),BRAIN!$G$29&", ",""),"") & IF(LEN(BRAIN!$G$30)>0,IF(ISNUMBER(SEARCH(BRAIN!$G$30,AK6)),BRAIN!$G$30&", ",""),"") & IF(LEN(BRAIN!$G$31)>0,IF(ISNUMBER(SEARCH(BRAIN!$G$31,AK6)),BRAIN!$G$31&", ",""),"") & IF(LEN(BRAIN!$G$32)>0,IF(ISNUMBER(SEARCH(BRAIN!$G$32,AK6)),BRAIN!$G$32&", ",""),"") & IF(LEN(BRAIN!$G$33)>0,IF(ISNUMBER(SEARCH(BRAIN!$G$33,AK6)),BRAIN!$G$33&", ",""),"") & IF(LEN(BRAIN!$G$34)>0,IF(ISNUMBER(SEARCH(BRAIN!$G$34,AK6)),BRAIN!$G$34&", ",""),"") & IF(LEN(BRAIN!$G$35)>0,IF(ISNUMBER(SEARCH(BRAIN!$G$35,AK6)),BRAIN!$G$35&", ",""),"") & IF(LEN(BRAIN!$G$36)>0,IF(ISNUMBER(SEARCH(BRAIN!$G$36,AK6)),BRAIN!$G$36&", ",""),"") & IF(LEN(BRAIN!$G$37)>0,IF(ISNUMBER(SEARCH(BRAIN!$G$37,AK6)),BRAIN!$G$37&", ",""),"") & IF(LEN(BRAIN!$G$38)>0,IF(ISNUMBER(SEARCH(BRAIN!$G$38,AK6)),BRAIN!$G$38&", ",""),"") & IF(LEN(BRAIN!$G$39)>0,IF(ISNUMBER(SEARCH(BRAIN!$G$39,AK6)),BRAIN!$G$39&", ",""),"") & IF(LEN(BRAIN!$G$40)>0,IF(ISNUMBER(SEARCH(BRAIN!$G$40,AK6)),BRAIN!$G$40&", ",""),"") & IF(LEN(BRAIN!$G$41)>0,IF(ISNUMBER(SEARCH(BRAIN!$G$41,AK6)),BRAIN!$G$41&", ",""),"") & IF(LEN(BRAIN!$G$42)>0,IF(ISNUMBER(SEARCH(BRAIN!$G$42,AK6)),BRAIN!$G$42&", ",""),"") & IF(LEN(BRAIN!$G$43)>0,IF(ISNUMBER(SEARCH(BRAIN!$G$43,AK6)),BRAIN!$G$43&", ",""),"") & IF(LEN(BRAIN!$G$44)>0,IF(ISNUMBER(SEARCH(BRAIN!$G$44,AK6)),BRAIN!$G$44&", ",""),"") & IF(LEN(BRAIN!$G$45)>0,IF(ISNUMBER(SEARCH(BRAIN!$G$45,AK6)),BRAIN!$G$45&", ",""),"") & IF(LEN(BRAIN!$G$46)>0,IF(ISNUMBER(SEARCH(BRAIN!$G$46,AK6)),BRAIN!$G$46&", ",""),"") & IF(LEN(BRAIN!$G$47)>0,IF(ISNUMBER(SEARCH(BRAIN!$G$47,AK6)),BRAIN!$G$47&", ",""),"") & IF(LEN(BRAIN!$G$48)>0,IF(ISNUMBER(SEARCH(BRAIN!$G$48,AK6)),BRAIN!$G$48&", ",""),"") & IF(LEN(BRAIN!$G$49)>0,IF(ISNUMBER(SEARCH(BRAIN!$G$49,AK6)),BRAIN!$G$49&", ",""),"") & IF(LEN(BRAIN!$G$50)>0,IF(ISNUMBER(SEARCH(BRAIN!$G$50,AK6)),BRAIN!$G$50&", ",""),"") & IF(LEN(BRAIN!$G$51)>0,IF(ISNUMBER(SEARCH(BRAIN!$G$51,AK6)),BRAIN!$G$51&", ",""),"") & IF(LEN(BRAIN!$G$52)>0,IF(ISNUMBER(SEARCH(BRAIN!$G$52,AK6)),BRAIN!$G$52&", ",""),"") & IF(LEN(BRAIN!$G$53)>0,IF(ISNUMBER(SEARCH(BRAIN!$G$53,AK6)),BRAIN!$G$53&", ",""),"") & IF(LEN(BRAIN!$G$54)>0,IF(ISNUMBER(SEARCH(BRAIN!$G$54,AK6)),BRAIN!$G$54&", ",""),"") & IF(LEN(BRAIN!$G$55)>0,IF(ISNUMBER(SEARCH(BRAIN!$G$55,AK6)),BRAIN!$G$55&", ",""),"") & IF(LEN(BRAIN!$G$56)>0,IF(ISNUMBER(SEARCH(BRAIN!$G$56,AK6)),BRAIN!$G$56&", ",""),"") & IF(LEN(BRAIN!$G$57)>0,IF(ISNUMBER(SEARCH(BRAIN!$G$57,AK6)),BRAIN!$G$57&", ",""),"")),2)=", ",LEFT((IF(LEN(BRAIN!$G$26)>0,IF(ISNUMBER(SEARCH(BRAIN!$G$26,AK6)),BRAIN!$G$26&", ",""),"") & IF(LEN(BRAIN!$G$27)>0,IF(ISNUMBER(SEARCH(BRAIN!$G$27,AK6)),BRAIN!$G$27&", ",""),"") & IF(LEN(BRAIN!$G$28)>0,IF(ISNUMBER(SEARCH(BRAIN!$G$28,AK6)),BRAIN!$G$28&", ",""),"") & IF(LEN(BRAIN!$G$29)>0,IF(ISNUMBER(SEARCH(BRAIN!$G$29,AK6)),BRAIN!$G$29&", ",""),"") & IF(LEN(BRAIN!$G$30)>0,IF(ISNUMBER(SEARCH(BRAIN!$G$30,AK6)),BRAIN!$G$30&", ",""),"") & IF(LEN(BRAIN!$G$31)>0,IF(ISNUMBER(SEARCH(BRAIN!$G$31,AK6)),BRAIN!$G$31&", ",""),"") & IF(LEN(BRAIN!$G$32)>0,IF(ISNUMBER(SEARCH(BRAIN!$G$32,AK6)),BRAIN!$G$32&", ",""),"") & IF(LEN(BRAIN!$G$33)>0,IF(ISNUMBER(SEARCH(BRAIN!$G$33,AK6)),BRAIN!$G$33&", ",""),"") & IF(LEN(BRAIN!$G$34)>0,IF(ISNUMBER(SEARCH(BRAIN!$G$34,AK6)),BRAIN!$G$34&", ",""),"") & IF(LEN(BRAIN!$G$35)>0,IF(ISNUMBER(SEARCH(BRAIN!$G$35,AK6)),BRAIN!$G$35&", ",""),"") & IF(LEN(BRAIN!$G$36)>0,IF(ISNUMBER(SEARCH(BRAIN!$G$36,AK6)),BRAIN!$G$36&", ",""),"") & IF(LEN(BRAIN!$G$37)>0,IF(ISNUMBER(SEARCH(BRAIN!$G$37,AK6)),BRAIN!$G$37&", ",""),"") & IF(LEN(BRAIN!$G$38)>0,IF(ISNUMBER(SEARCH(BRAIN!$G$38,AK6)),BRAIN!$G$38&", ",""),"") & IF(LEN(BRAIN!$G$39)>0,IF(ISNUMBER(SEARCH(BRAIN!$G$39,AK6)),BRAIN!$G$39&", ",""),"") & IF(LEN(BRAIN!$G$40)>0,IF(ISNUMBER(SEARCH(BRAIN!$G$40,AK6)),BRAIN!$G$40&", ",""),"") & IF(LEN(BRAIN!$G$41)>0,IF(ISNUMBER(SEARCH(BRAIN!$G$41,AK6)),BRAIN!$G$41&", ",""),"") & IF(LEN(BRAIN!$G$42)>0,IF(ISNUMBER(SEARCH(BRAIN!$G$42,AK6)),BRAIN!$G$42&", ",""),"") & IF(LEN(BRAIN!$G$43)>0,IF(ISNUMBER(SEARCH(BRAIN!$G$43,AK6)),BRAIN!$G$43&", ",""),"") & IF(LEN(BRAIN!$G$44)>0,IF(ISNUMBER(SEARCH(BRAIN!$G$44,AK6)),BRAIN!$G$44&", ",""),"") & IF(LEN(BRAIN!$G$45)>0,IF(ISNUMBER(SEARCH(BRAIN!$G$45,AK6)),BRAIN!$G$45&", ",""),"") & IF(LEN(BRAIN!$G$46)>0,IF(ISNUMBER(SEARCH(BRAIN!$G$46,AK6)),BRAIN!$G$46&", ",""),"") & IF(LEN(BRAIN!$G$47)>0,IF(ISNUMBER(SEARCH(BRAIN!$G$47,AK6)),BRAIN!$G$47&", ",""),"") & IF(LEN(BRAIN!$G$48)>0,IF(ISNUMBER(SEARCH(BRAIN!$G$48,AK6)),BRAIN!$G$48&", ",""),"") & IF(LEN(BRAIN!$G$49)>0,IF(ISNUMBER(SEARCH(BRAIN!$G$49,AK6)),BRAIN!$G$49&", ",""),"") & IF(LEN(BRAIN!$G$50)>0,IF(ISNUMBER(SEARCH(BRAIN!$G$50,AK6)),BRAIN!$G$50&", ",""),"") & IF(LEN(BRAIN!$G$51)>0,IF(ISNUMBER(SEARCH(BRAIN!$G$51,AK6)),BRAIN!$G$51&", ",""),"") & IF(LEN(BRAIN!$G$52)>0,IF(ISNUMBER(SEARCH(BRAIN!$G$52,AK6)),BRAIN!$G$52&", ",""),"") & IF(LEN(BRAIN!$G$53)>0,IF(ISNUMBER(SEARCH(BRAIN!$G$53,AK6)),BRAIN!$G$53&", ",""),"") & IF(LEN(BRAIN!$G$54)>0,IF(ISNUMBER(SEARCH(BRAIN!$G$54,AK6)),BRAIN!$G$54&", ",""),"") & IF(LEN(BRAIN!$G$55)>0,IF(ISNUMBER(SEARCH(BRAIN!$G$55,AK6)),BRAIN!$G$55&", ",""),"") & IF(LEN(BRAIN!$G$56)>0,IF(ISNUMBER(SEARCH(BRAIN!$G$56,AK6)),BRAIN!$G$56&", ",""),"") & IF(LEN(BRAIN!$G$57)>0,IF(ISNUMBER(SEARCH(BRAIN!$G$57,AK6)),BRAIN!$G$57&", ",""),"")),LEN((IF(LEN(BRAIN!$G$26)>0,IF(ISNUMBER(SEARCH(BRAIN!$G$26,AK6)),BRAIN!$G$26&", ",""),"") & IF(LEN(BRAIN!$G$27)>0,IF(ISNUMBER(SEARCH(BRAIN!$G$27,AK6)),BRAIN!$G$27&", ",""),"") & IF(LEN(BRAIN!$G$28)>0,IF(ISNUMBER(SEARCH(BRAIN!$G$28,AK6)),BRAIN!$G$28&", ",""),"") & IF(LEN(BRAIN!$G$29)>0,IF(ISNUMBER(SEARCH(BRAIN!$G$29,AK6)),BRAIN!$G$29&", ",""),"") & IF(LEN(BRAIN!$G$30)>0,IF(ISNUMBER(SEARCH(BRAIN!$G$30,AK6)),BRAIN!$G$30&", ",""),"") & IF(LEN(BRAIN!$G$31)>0,IF(ISNUMBER(SEARCH(BRAIN!$G$31,AK6)),BRAIN!$G$31&", ",""),"") & IF(LEN(BRAIN!$G$32)>0,IF(ISNUMBER(SEARCH(BRAIN!$G$32,AK6)),BRAIN!$G$32&", ",""),"") & IF(LEN(BRAIN!$G$33)>0,IF(ISNUMBER(SEARCH(BRAIN!$G$33,AK6)),BRAIN!$G$33&", ",""),"") & IF(LEN(BRAIN!$G$34)>0,IF(ISNUMBER(SEARCH(BRAIN!$G$34,AK6)),BRAIN!$G$34&", ",""),"") & IF(LEN(BRAIN!$G$35)>0,IF(ISNUMBER(SEARCH(BRAIN!$G$35,AK6)),BRAIN!$G$35&", ",""),"") & IF(LEN(BRAIN!$G$36)>0,IF(ISNUMBER(SEARCH(BRAIN!$G$36,AK6)),BRAIN!$G$36&", ",""),"") & IF(LEN(BRAIN!$G$37)>0,IF(ISNUMBER(SEARCH(BRAIN!$G$37,AK6)),BRAIN!$G$37&", ",""),"") & IF(LEN(BRAIN!$G$38)>0,IF(ISNUMBER(SEARCH(BRAIN!$G$38,AK6)),BRAIN!$G$38&", ",""),"") & IF(LEN(BRAIN!$G$39)>0,IF(ISNUMBER(SEARCH(BRAIN!$G$39,AK6)),BRAIN!$G$39&", ",""),"") & IF(LEN(BRAIN!$G$40)>0,IF(ISNUMBER(SEARCH(BRAIN!$G$40,AK6)),BRAIN!$G$40&", ",""),"") & IF(LEN(BRAIN!$G$41)>0,IF(ISNUMBER(SEARCH(BRAIN!$G$41,AK6)),BRAIN!$G$41&", ",""),"") & IF(LEN(BRAIN!$G$42)>0,IF(ISNUMBER(SEARCH(BRAIN!$G$42,AK6)),BRAIN!$G$42&", ",""),"") & IF(LEN(BRAIN!$G$43)>0,IF(ISNUMBER(SEARCH(BRAIN!$G$43,AK6)),BRAIN!$G$43&", ",""),"") & IF(LEN(BRAIN!$G$44)>0,IF(ISNUMBER(SEARCH(BRAIN!$G$44,AK6)),BRAIN!$G$44&", ",""),"") & IF(LEN(BRAIN!$G$45)>0,IF(ISNUMBER(SEARCH(BRAIN!$G$45,AK6)),BRAIN!$G$45&", ",""),"") & IF(LEN(BRAIN!$G$46)>0,IF(ISNUMBER(SEARCH(BRAIN!$G$46,AK6)),BRAIN!$G$46&", ",""),"") & IF(LEN(BRAIN!$G$47)>0,IF(ISNUMBER(SEARCH(BRAIN!$G$47,AK6)),BRAIN!$G$47&", ",""),"") & IF(LEN(BRAIN!$G$48)>0,IF(ISNUMBER(SEARCH(BRAIN!$G$48,AK6)),BRAIN!$G$48&", ",""),"") & IF(LEN(BRAIN!$G$49)>0,IF(ISNUMBER(SEARCH(BRAIN!$G$49,AK6)),BRAIN!$G$49&", ",""),"") & IF(LEN(BRAIN!$G$50)>0,IF(ISNUMBER(SEARCH(BRAIN!$G$50,AK6)),BRAIN!$G$50&", ",""),"") & IF(LEN(BRAIN!$G$51)>0,IF(ISNUMBER(SEARCH(BRAIN!$G$51,AK6)),BRAIN!$G$51&", ",""),"") & IF(LEN(BRAIN!$G$52)>0,IF(ISNUMBER(SEARCH(BRAIN!$G$52,AK6)),BRAIN!$G$52&", ",""),"") & IF(LEN(BRAIN!$G$53)>0,IF(ISNUMBER(SEARCH(BRAIN!$G$53,AK6)),BRAIN!$G$53&", ",""),"") & IF(LEN(BRAIN!$G$54)>0,IF(ISNUMBER(SEARCH(BRAIN!$G$54,AK6)),BRAIN!$G$54&", ",""),"") & IF(LEN(BRAIN!$G$55)>0,IF(ISNUMBER(SEARCH(BRAIN!$G$55,AK6)),BRAIN!$G$55&", ",""),"") & IF(LEN(BRAIN!$G$56)>0,IF(ISNUMBER(SEARCH(BRAIN!$G$56,AK6)),BRAIN!$G$56&", ",""),"") & IF(LEN(BRAIN!$G$57)>0,IF(ISNUMBER(SEARCH(BRAIN!$G$57,AK6)),BRAIN!$G$57&", ",""),"")))-2),(IF(LEN(BRAIN!$G$26)>0,IF(ISNUMBER(SEARCH(BRAIN!$G$26,AK6)),BRAIN!$G$26&", ",""),"") & IF(LEN(BRAIN!$G$27)>0,IF(ISNUMBER(SEARCH(BRAIN!$G$27,AK6)),BRAIN!$G$27&", ",""),"") & IF(LEN(BRAIN!$G$28)>0,IF(ISNUMBER(SEARCH(BRAIN!$G$28,AK6)),BRAIN!$G$28&", ",""),"") & IF(LEN(BRAIN!$G$29)>0,IF(ISNUMBER(SEARCH(BRAIN!$G$29,AK6)),BRAIN!$G$29&", ",""),"") & IF(LEN(BRAIN!$G$30)>0,IF(ISNUMBER(SEARCH(BRAIN!$G$30,AK6)),BRAIN!$G$30&", ",""),"") & IF(LEN(BRAIN!$G$31)>0,IF(ISNUMBER(SEARCH(BRAIN!$G$31,AK6)),BRAIN!$G$31&", ",""),"") & IF(LEN(BRAIN!$G$32)>0,IF(ISNUMBER(SEARCH(BRAIN!$G$32,AK6)),BRAIN!$G$32&", ",""),"") & IF(LEN(BRAIN!$G$33)>0,IF(ISNUMBER(SEARCH(BRAIN!$G$33,AK6)),BRAIN!$G$33&", ",""),"") & IF(LEN(BRAIN!$G$34)>0,IF(ISNUMBER(SEARCH(BRAIN!$G$34,AK6)),BRAIN!$G$34&", ",""),"") & IF(LEN(BRAIN!$G$35)>0,IF(ISNUMBER(SEARCH(BRAIN!$G$35,AK6)),BRAIN!$G$35&", ",""),"") & IF(LEN(BRAIN!$G$36)>0,IF(ISNUMBER(SEARCH(BRAIN!$G$36,AK6)),BRAIN!$G$36&", ",""),"") & IF(LEN(BRAIN!$G$37)>0,IF(ISNUMBER(SEARCH(BRAIN!$G$37,AK6)),BRAIN!$G$37&", ",""),"") & IF(LEN(BRAIN!$G$38)>0,IF(ISNUMBER(SEARCH(BRAIN!$G$38,AK6)),BRAIN!$G$38&", ",""),"") & IF(LEN(BRAIN!$G$39)>0,IF(ISNUMBER(SEARCH(BRAIN!$G$39,AK6)),BRAIN!$G$39&", ",""),"") & IF(LEN(BRAIN!$G$40)>0,IF(ISNUMBER(SEARCH(BRAIN!$G$40,AK6)),BRAIN!$G$40&", ",""),"") & IF(LEN(BRAIN!$G$41)>0,IF(ISNUMBER(SEARCH(BRAIN!$G$41,AK6)),BRAIN!$G$41&", ",""),"") & IF(LEN(BRAIN!$G$42)>0,IF(ISNUMBER(SEARCH(BRAIN!$G$42,AK6)),BRAIN!$G$42&", ",""),"") & IF(LEN(BRAIN!$G$43)>0,IF(ISNUMBER(SEARCH(BRAIN!$G$43,AK6)),BRAIN!$G$43&", ",""),"") & IF(LEN(BRAIN!$G$44)>0,IF(ISNUMBER(SEARCH(BRAIN!$G$44,AK6)),BRAIN!$G$44&", ",""),"") & IF(LEN(BRAIN!$G$45)>0,IF(ISNUMBER(SEARCH(BRAIN!$G$45,AK6)),BRAIN!$G$45&", ",""),"") & IF(LEN(BRAIN!$G$46)>0,IF(ISNUMBER(SEARCH(BRAIN!$G$46,AK6)),BRAIN!$G$46&", ",""),"") & IF(LEN(BRAIN!$G$47)>0,IF(ISNUMBER(SEARCH(BRAIN!$G$47,AK6)),BRAIN!$G$47&", ",""),"") & IF(LEN(BRAIN!$G$48)>0,IF(ISNUMBER(SEARCH(BRAIN!$G$48,AK6)),BRAIN!$G$48&", ",""),"") & IF(LEN(BRAIN!$G$49)>0,IF(ISNUMBER(SEARCH(BRAIN!$G$49,AK6)),BRAIN!$G$49&", ",""),"") & IF(LEN(BRAIN!$G$50)>0,IF(ISNUMBER(SEARCH(BRAIN!$G$50,AK6)),BRAIN!$G$50&", ",""),"") & IF(LEN(BRAIN!$G$51)>0,IF(ISNUMBER(SEARCH(BRAIN!$G$51,AK6)),BRAIN!$G$51&", ",""),"") & IF(LEN(BRAIN!$G$52)>0,IF(ISNUMBER(SEARCH(BRAIN!$G$52,AK6)),BRAIN!$G$52&", ",""),"") & IF(LEN(BRAIN!$G$53)>0,IF(ISNUMBER(SEARCH(BRAIN!$G$53,AK6)),BRAIN!$G$53&", ",""),"") & IF(LEN(BRAIN!$G$54)>0,IF(ISNUMBER(SEARCH(BRAIN!$G$54,AK6)),BRAIN!$G$54&", ",""),"") & IF(LEN(BRAIN!$G$55)>0,IF(ISNUMBER(SEARCH(BRAIN!$G$55,AK6)),BRAIN!$G$55&", ",""),"") & IF(LEN(BRAIN!$G$56)>0,IF(ISNUMBER(SEARCH(BRAIN!$G$56,AK6)),BRAIN!$G$56&", ",""),"") & IF(LEN(BRAIN!$G$57)>0,IF(ISNUMBER(SEARCH(BRAIN!$G$57,AK6)),BRAIN!$G$57&", ",""),""))),"") -> manual, audit | AR6: =IFERROR(IF(RIGHT((IF(LEN(BRAIN!$H$26)>0,IF(ISNUMBER(SEARCH(BRAIN!$H$26,AK6)),BRAIN!$H$26&", ",""),"") & IF(LEN(BRAIN!$H$27)>0,IF(ISNUMBER(SEARCH(BRAIN!$H$27,AK6)),BRAIN!$H$27&", ",""),"") & IF(LEN(BRAIN!$H$28)>0,IF(ISNUMBER(SEARCH(BRAIN!$H$28,AK6)),BRAIN!$H$28&", ",""),"") & IF(LEN(BRAIN!$H$29)>0,IF(ISNUMBER(SEARCH(BRAIN!$H$29,AK6)),BRAIN!$H$29&", ",""),"") & IF(LEN(BRAIN!$H$30)>0,IF(ISNUMBER(SEARCH(BRAIN!$H$30,AK6)),BRAIN!$H$30&", ",""),"") & IF(LEN(BRAIN!$H$31)>0,IF(ISNUMBER(SEARCH(BRAIN!$H$31,AK6)),BRAIN!$H$31&", ",""),"") & IF(LEN(BRAIN!$H$32)>0,IF(ISNUMBER(SEARCH(BRAIN!$H$32,AK6)),BRAIN!$H$32&", ",""),"") & IF(LEN(BRAIN!$H$33)>0,IF(ISNUMBER(SEARCH(BRAIN!$H$33,AK6)),BRAIN!$H$33&", ",""),"") & IF(LEN(BRAIN!$H$34)>0,IF(ISNUMBER(SEARCH(BRAIN!$H$34,AK6)),BRAIN!$H$34&", ",""),"") & IF(LEN(BRAIN!$H$35)>0,IF(ISNUMBER(SEARCH(BRAIN!$H$35,AK6)),BRAIN!$H$35&", ",""),"") & IF(LEN(BRAIN!$H$36)>0,IF(ISNUMBER(SEARCH(BRAIN!$H$36,AK6)),BRAIN!$H$36&", ",""),"") & IF(LEN(BRAIN!$H$37)>0,IF(ISNUMBER(SEARCH(BRAIN!$H$37,AK6)),BRAIN!$H$37&", ",""),"") & IF(LEN(BRAIN!$H$38)>0,IF(ISNUMBER(SEARCH(BRAIN!$H$38,AK6)),BRAIN!$H$38&", ",""),"") & IF(LEN(BRAIN!$H$39)>0,IF(ISNUMBER(SEARCH(BRAIN!$H$39,AK6)),BRAIN!$H$39&", ",""),"") & IF(LEN(BRAIN!$H$40)>0,IF(ISNUMBER(SEARCH(BRAIN!$H$40,AK6)),BRAIN!$H$40&", ",""),"") & IF(LEN(BRAIN!$H$41)>0,IF(ISNUMBER(SEARCH(BRAIN!$H$41,AK6)),BRAIN!$H$41&", ",""),"") & IF(LEN(BRAIN!$H$42)>0,IF(ISNUMBER(SEARCH(BRAIN!$H$42,AK6)),BRAIN!$H$42&", ",""),"") & IF(LEN(BRAIN!$H$43)>0,IF(ISNUMBER(SEARCH(BRAIN!$H$43,AK6)),BRAIN!$H$43&", ",""),"") & IF(LEN(BRAIN!$H$44)>0,IF(ISNUMBER(SEARCH(BRAIN!$H$44,AK6)),BRAIN!$H$44&", ",""),"") & IF(LEN(BRAIN!$H$45)>0,IF(ISNUMBER(SEARCH(BRAIN!$H$45,AK6)),BRAIN!$H$45&", ",""),"") & IF(LEN(BRAIN!$H$46)>0,IF(ISNUMBER(SEARCH(BRAIN!$H$46,AK6)),BRAIN!$H$46&", ",""),"") & IF(LEN(BRAIN!$H$47)>0,IF(ISNUMBER(SEARCH(BRAIN!$H$47,AK6)),BRAIN!$H$47&", ",""),"") & IF(LEN(BRAIN!$H$48)>0,IF(ISNUMBER(SEARCH(BRAIN!$H$48,AK6)),BRAIN!$H$48&", ",""),"") & IF(LEN(BRAIN!$H$49)>0,IF(ISNUMBER(SEARCH(BRAIN!$H$49,AK6)),BRAIN!$H$49&", ",""),"") & IF(LEN(BRAIN!$H$50)>0,IF(ISNUMBER(SEARCH(BRAIN!$H$50,AK6)),BRAIN!$H$50&", ",""),"") & IF(LEN(BRAIN!$H$51)>0,IF(ISNUMBER(SEARCH(BRAIN!$H$51,AK6)),BRAIN!$H$51&", ",""),"") & IF(LEN(BRAIN!$H$52)>0,IF(ISNUMBER(SEARCH(BRAIN!$H$52,AK6)),BRAIN!$H$52&", ",""),"") & IF(LEN(BRAIN!$H$53)>0,IF(ISNUMBER(SEARCH(BRAIN!$H$53,AK6)),BRAIN!$H$53&", ",""),"") & IF(LEN(BRAIN!$H$54)>0,IF(ISNUMBER(SEARCH(BRAIN!$H$54,AK6)),BRAIN!$H$54&", ",""),"") & IF(LEN(BRAIN!$H$55)>0,IF(ISNUMBER(SEARCH(BRAIN!$H$55,AK6)),BRAIN!$H$55&", ",""),"") & IF(LEN(BRAIN!$H$56)>0,IF(ISNUMBER(SEARCH(BRAIN!$H$56,AK6)),BRAIN!$H$56&", ",""),"") & IF(LEN(BRAIN!$H$57)>0,IF(ISNUMBER(SEARCH(BRAIN!$H$57,AK6)),BRAIN!$H$57&", ",""),"")),2)=", ",LEFT((IF(LEN(BRAIN!$H$26)>0,IF(ISNUMBER(SEARCH(BRAIN!$H$26,AK6)),BRAIN!$H$26&", ",""),"") & IF(LEN(BRAIN!$H$27)>0,IF(ISNUMBER(SEARCH(BRAIN!$H$27,AK6)),BRAIN!$H$27&", ",""),"") & IF(LEN(BRAIN!$H$28)>0,IF(ISNUMBER(SEARCH(BRAIN!$H$28,AK6)),BRAIN!$H$28&", ",""),"") & IF(LEN(BRAIN!$H$29)>0,IF(ISNUMBER(SEARCH(BRAIN!$H$29,AK6)),BRAIN!$H$29&", ",""),"") & IF(LEN(BRAIN!$H$30)>0,IF(ISNUMBER(SEARCH(BRAIN!$H$30,AK6)),BRAIN!$H$30&", ",""),"") & IF(LEN(BRAIN!$H$31)>0,IF(ISNUMBER(SEARCH(BRAIN!$H$31,AK6)),BRAIN!$H$31&", ",""),"") & IF(LEN(BRAIN!$H$32)>0,IF(ISNUMBER(SEARCH(BRAIN!$H$32,AK6)),BRAIN!$H$32&", ",""),"") & IF(LEN(BRAIN!$H$33)>0,IF(ISNUMBER(SEARCH(BRAIN!$H$33,AK6)),BRAIN!$H$33&", ",""),"") & IF(LEN(BRAIN!$H$34)>0,IF(ISNUMBER(SEARCH(BRAIN!$H$34,AK6)),BRAIN!$H$34&", ",""),"") & IF(LEN(BRAIN!$H$35)>0,IF(ISNUMBER(SEARCH(BRAIN!$H$35,AK6)),BRAIN!$H$35&", ",""),"") & IF(LEN(BRAIN!$H$36)>0,IF(ISNUMBER(SEARCH(BRAIN!$H$36,AK6)),BRAIN!$H$36&", ",""),"") & IF(LEN(BRAIN!$H$37)>0,IF(ISNUMBER(SEARCH(BRAIN!$H$37,AK6)),BRAIN!$H$37&", ",""),"") & IF(LEN(BRAIN!$H$38)>0,IF(ISNUMBER(SEARCH(BRAIN!$H$38,AK6)),BRAIN!$H$38&", ",""),"") & IF(LEN(BRAIN!$H$39)>0,IF(ISNUMBER(SEARCH(BRAIN!$H$39,AK6)),BRAIN!$H$39&", ",""),"") & IF(LEN(BRAIN!$H$40)>0,IF(ISNUMBER(SEARCH(BRAIN!$H$40,AK6)),BRAIN!$H$40&", ",""),"") & IF(LEN(BRAIN!$H$41)>0,IF(ISNUMBER(SEARCH(BRAIN!$H$41,AK6)),BRAIN!$H$41&", ",""),"") & IF(LEN(BRAIN!$H$42)>0,IF(ISNUMBER(SEARCH(BRAIN!$H$42,AK6)),BRAIN!$H$42&", ",""),"") & IF(LEN(BRAIN!$H$43)>0,IF(ISNUMBER(SEARCH(BRAIN!$H$43,AK6)),BRAIN!$H$43&", ",""),"") & IF(LEN(BRAIN!$H$44)>0,IF(ISNUMBER(SEARCH(BRAIN!$H$44,AK6)),BRAIN!$H$44&", ",""),"") & IF(LEN(BRAIN!$H$45)>0,IF(ISNUMBER(SEARCH(BRAIN!$H$45,AK6)),BRAIN!$H$45&", ",""),"") & IF(LEN(BRAIN!$H$46)>0,IF(ISNUMBER(SEARCH(BRAIN!$H$46,AK6)),BRAIN!$H$46&", ",""),"") & IF(LEN(BRAIN!$H$47)>0,IF(ISNUMBER(SEARCH(BRAIN!$H$47,AK6)),BRAIN!$H$47&", ",""),"") & IF(LEN(BRAIN!$H$48)>0,IF(ISNUMBER(SEARCH(BRAIN!$H$48,AK6)),BRAIN!$H$48&", ",""),"") & IF(LEN(BRAIN!$H$49)>0,IF(ISNUMBER(SEARCH(BRAIN!$H$49,AK6)),BRAIN!$H$49&", ",""),"") & IF(LEN(BRAIN!$H$50)>0,IF(ISNUMBER(SEARCH(BRAIN!$H$50,AK6)),BRAIN!$H$50&", ",""),"") & IF(LEN(BRAIN!$H$51)>0,IF(ISNUMBER(SEARCH(BRAIN!$H$51,AK6)),BRAIN!$H$51&", ",""),"") & IF(LEN(BRAIN!$H$52)>0,IF(ISNUMBER(SEARCH(BRAIN!$H$52,AK6)),BRAIN!$H$52&", ",""),"") & IF(LEN(BRAIN!$H$53)>0,IF(ISNUMBER(SEARCH(BRAIN!$H$53,AK6)),BRAIN!$H$53&", ",""),"") & IF(LEN(BRAIN!$H$54)>0,IF(ISNUMBER(SEARCH(BRAIN!$H$54,AK6)),BRAIN!$H$54&", ",""),"") & IF(LEN(BRAIN!$H$55)>0,IF(ISNUMBER(SEARCH(BRAIN!$H$55,AK6)),BRAIN!$H$55&", ",""),"") & IF(LEN(BRAIN!$H$56)>0,IF(ISNUMBER(SEARCH(BRAIN!$H$56,AK6)),BRAIN!$H$56&", ",""),"") & IF(LEN(BRAIN!$H$57)>0,IF(ISNUMBER(SEARCH(BRAIN!$H$57,AK6)),BRAIN!$H$57&", ",""),"")),LEN((IF(LEN(BRAIN!$H$26)>0,IF(ISNUMBER(SEARCH(BRAIN!$H$26,AK6)),BRAIN!$H$26&", ",""),"") & IF(LEN(BRAIN!$H$27)>0,IF(ISNUMBER(SEARCH(BRAIN!$H$27,AK6)),BRAIN!$H$27&", ",""),"") & IF(LEN(BRAIN!$H$28)>0,IF(ISNUMBER(SEARCH(BRAIN!$H$28,AK6)),BRAIN!$H$28&", ",""),"") & IF(LEN(BRAIN!$H$29)>0,IF(ISNUMBER(SEARCH(BRAIN!$H$29,AK6)),BRAIN!$H$29&", ",""),"") & IF(LEN(BRAIN!$H$30)>0,IF(ISNUMBER(SEARCH(BRAIN!$H$30,AK6)),BRAIN!$H$30&", ",""),"") & IF(LEN(BRAIN!$H$31)>0,IF(ISNUMBER(SEARCH(BRAIN!$H$31,AK6)),BRAIN!$H$31&", ",""),"") & IF(LEN(BRAIN!$H$32)>0,IF(ISNUMBER(SEARCH(BRAIN!$H$32,AK6)),BRAIN!$H$32&", ",""),"") & IF(LEN(BRAIN!$H$33)>0,IF(ISNUMBER(SEARCH(BRAIN!$H$33,AK6)),BRAIN!$H$33&", ",""),"") & IF(LEN(BRAIN!$H$34)>0,IF(ISNUMBER(SEARCH(BRAIN!$H$34,AK6)),BRAIN!$H$34&", ",""),"") & IF(LEN(BRAIN!$H$35)>0,IF(ISNUMBER(SEARCH(BRAIN!$H$35,AK6)),BRAIN!$H$35&", ",""),"") & IF(LEN(BRAIN!$H$36)>0,IF(ISNUMBER(SEARCH(BRAIN!$H$36,AK6)),BRAIN!$H$36&", ",""),"") & IF(LEN(BRAIN!$H$37)>0,IF(ISNUMBER(SEARCH(BRAIN!$H$37,AK6)),BRAIN!$H$37&", ",""),"") & IF(LEN(BRAIN!$H$38)>0,IF(ISNUMBER(SEARCH(BRAIN!$H$38,AK6)),BRAIN!$H$38&", ",""),"") & IF(LEN(BRAIN!$H$39)>0,IF(ISNUMBER(SEARCH(BRAIN!$H$39,AK6)),BRAIN!$H$39&", ",""),"") & IF(LEN(BRAIN!$H$40)>0,IF(ISNUMBER(SEARCH(BRAIN!$H$40,AK6)),BRAIN!$H$40&", ",""),"") & IF(LEN(BRAIN!$H$41)>0,IF(ISNUMBER(SEARCH(BRAIN!$H$41,AK6)),BRAIN!$H$41&", ",""),"") & IF(LEN(BRAIN!$H$42)>0,IF(ISNUMBER(SEARCH(BRAIN!$H$42,AK6)),BRAIN!$H$42&", ",""),"") & IF(LEN(BRAIN!$H$43)>0,IF(ISNUMBER(SEARCH(BRAIN!$H$43,AK6)),BRAIN!$H$43&", ",""),"") & IF(LEN(BRAIN!$H$44)>0,IF(ISNUMBER(SEARCH(BRAIN!$H$44,AK6)),BRAIN!$H$44&", ",""),"") & IF(LEN(BRAIN!$H$45)>0,IF(ISNUMBER(SEARCH(BRAIN!$H$45,AK6)),BRAIN!$H$45&", ",""),"") & IF(LEN(BRAIN!$H$46)>0,IF(ISNUMBER(SEARCH(BRAIN!$H$46,AK6)),BRAIN!$H$46&", ",""),"") & IF(LEN(BRAIN!$H$47)>0,IF(ISNUMBER(SEARCH(BRAIN!$H$47,AK6)),BRAIN!$H$47&", ",""),"") & IF(LEN(BRAIN!$H$48)>0,IF(ISNUMBER(SEARCH(BRAIN!$H$48,AK6)),BRAIN!$H$48&", ",""),"") & IF(LEN(BRAIN!$H$49)>0,IF(ISNUMBER(SEARCH(BRAIN!$H$49,AK6)),BRAIN!$H$49&", ",""),"") & IF(LEN(BRAIN!$H$50)>0,IF(ISNUMBER(SEARCH(BRAIN!$H$50,AK6)),BRAIN!$H$50&", ",""),"") & IF(LEN(BRAIN!$H$51)>0,IF(ISNUMBER(SEARCH(BRAIN!$H$51,AK6)),BRAIN!$H$51&", ",""),"") & IF(LEN(BRAIN!$H$52)>0,IF(ISNUMBER(SEARCH(BRAIN!$H$52,AK6)),BRAIN!$H$52&", ",""),"") & IF(LEN(BRAIN!$H$53)>0,IF(ISNUMBER(SEARCH(BRAIN!$H$53,AK6)),BRAIN!$H$53&", ",""),"") & IF(LEN(BRAIN!$H$54)>0,IF(ISNUMBER(SEARCH(BRAIN!$H$54,AK6)),BRAIN!$H$54&", ",""),"") & IF(LEN(BRAIN!$H$55)>0,IF(ISNUMBER(SEARCH(BRAIN!$H$55,AK6)),BRAIN!$H$55&", ",""),"") & IF(LEN(BRAIN!$H$56)>0,IF(ISNUMBER(SEARCH(BRAIN!$H$56,AK6)),BRAIN!$H$56&", ",""),"") & IF(LEN(BRAIN!$H$57)>0,IF(ISNUMBER(SEARCH(BRAIN!$H$57,AK6)),BRAIN!$H$57&", ",""),"")))-2),(IF(LEN(BRAIN!$H$26)>0,IF(ISNUMBER(SEARCH(BRAIN!$H$26,AK6)),BRAIN!$H$26&", ",""),"") & IF(LEN(BRAIN!$H$27)>0,IF(ISNUMBER(SEARCH(BRAIN!$H$27,AK6)),BRAIN!$H$27&", ",""),"") & IF(LEN(BRAIN!$H$28)>0,IF(ISNUMBER(SEARCH(BRAIN!$H$28,AK6)),BRAIN!$H$28&", ",""),"") & IF(LEN(BRAIN!$H$29)>0,IF(ISNUMBER(SEARCH(BRAIN!$H$29,AK6)),BRAIN!$H$29&", ",""),"") & IF(LEN(BRAIN!$H$30)>0,IF(ISNUMBER(SEARCH(BRAIN!$H$30,AK6)),BRAIN!$H$30&", ",""),"") & IF(LEN(BRAIN!$H$31)>0,IF(ISNUMBER(SEARCH(BRAIN!$H$31,AK6)),BRAIN!$H$31&", ",""),"") & IF(LEN(BRAIN!$H$32)>0,IF(ISNUMBER(SEARCH(BRAIN!$H$32,AK6)),BRAIN!$H$32&", ",""),"") & IF(LEN(BRAIN!$H$33)>0,IF(ISNUMBER(SEARCH(BRAIN!$H$33,AK6)),BRAIN!$H$33&", ",""),"") & IF(LEN(BRAIN!$H$34)>0,IF(ISNUMBER(SEARCH(BRAIN!$H$34,AK6)),BRAIN!$H$34&", ",""),"") & IF(LEN(BRAIN!$H$35)>0,IF(ISNUMBER(SEARCH(BRAIN!$H$35,AK6)),BRAIN!$H$35&", ",""),"") & IF(LEN(BRAIN!$H$36)>0,IF(ISNUMBER(SEARCH(BRAIN!$H$36,AK6)),BRAIN!$H$36&", ",""),"") & IF(LEN(BRAIN!$H$37)>0,IF(ISNUMBER(SEARCH(BRAIN!$H$37,AK6)),BRAIN!$H$37&", ",""),"") & IF(LEN(BRAIN!$H$38)>0,IF(ISNUMBER(SEARCH(BRAIN!$H$38,AK6)),BRAIN!$H$38&", ",""),"") & IF(LEN(BRAIN!$H$39)>0,IF(ISNUMBER(SEARCH(BRAIN!$H$39,AK6)),BRAIN!$H$39&", ",""),"") & IF(LEN(BRAIN!$H$40)>0,IF(ISNUMBER(SEARCH(BRAIN!$H$40,AK6)),BRAIN!$H$40&", ",""),"") & IF(LEN(BRAIN!$H$41)>0,IF(ISNUMBER(SEARCH(BRAIN!$H$41,AK6)),BRAIN!$H$41&", ",""),"") & IF(LEN(BRAIN!$H$42)>0,IF(ISNUMBER(SEARCH(BRAIN!$H$42,AK6)),BRAIN!$H$42&", ",""),"") & IF(LEN(BRAIN!$H$43)>0,IF(ISNUMBER(SEARCH(BRAIN!$H$43,AK6)),BRAIN!$H$43&", ",""),"") & IF(LEN(BRAIN!$H$44)>0,IF(ISNUMBER(SEARCH(BRAIN!$H$44,AK6)),BRAIN!$H$44&", ",""),"") & IF(LEN(BRAIN!$H$45)>0,IF(ISNUMBER(SEARCH(BRAIN!$H$45,AK6)),BRAIN!$H$45&", ",""),"") & IF(LEN(BRAIN!$H$46)>0,IF(ISNUMBER(SEARCH(BRAIN!$H$46,AK6)),BRAIN!$H$46&", ",""),"") & IF(LEN(BRAIN!$H$47)>0,IF(ISNUMBER(SEARCH(BRAIN!$H$47,AK6)),BRAIN!$H$47&", ",""),"") & IF(LEN(BRAIN!$H$48)>0,IF(ISNUMBER(SEARCH(BRAIN!$H$48,AK6)),BRAIN!$H$48&", ",""),"") & IF(LEN(BRAIN!$H$49)>0,IF(ISNUMBER(SEARCH(BRAIN!$H$49,AK6)),BRAIN!$H$49&", ",""),"") & IF(LEN(BRAIN!$H$50)>0,IF(ISNUMBER(SEARCH(BRAIN!$H$50,AK6)),BRAIN!$H$50&", ",""),"") & IF(LEN(BRAIN!$H$51)>0,IF(ISNUMBER(SEARCH(BRAIN!$H$51,AK6)),BRAIN!$H$51&", ",""),"") & IF(LEN(BRAIN!$H$52)>0,IF(ISNUMBER(SEARCH(BRAIN!$H$52,AK6)),BRAIN!$H$52&", ",""),"") & IF(LEN(BRAIN!$H$53)>0,IF(ISNUMBER(SEARCH(BRAIN!$H$53,AK6)),BRAIN!$H$53&", ",""),"") & IF(LEN(BRAIN!$H$54)>0,IF(ISNUMBER(SEARCH(BRAIN!$H$54,AK6)),BRAIN!$H$54&", ",""),"") & IF(LEN(BRAIN!$H$55)>0,IF(ISNUMBER(SEARCH(BRAIN!$H$55,AK6)),BRAIN!$H$55&", ",""),"") & IF(LEN(BRAIN!$H$56)>0,IF(ISNUMBER(SEARCH(BRAIN!$H$56,AK6)),BRAIN!$H$56&", ",""),"") & IF(LEN(BRAIN!$H$57)>0,IF(ISNUMBER(SEARCH(BRAIN!$H$57,AK6)),BRAIN!$H$57&", ",""),""))),"")
